Workbook

Sheet FVA
A1: FONDO VALOR ACTIVO
A2: 45274
B4: FECHA | C4: DEPOSITO | D4: TOTAL | E4: UNID | F4: VOLUMEN | G4: GANANCIA | H4: RENTABILIDAD | J4: PRODUCTO | K4: DEPOSITO | L4: ACTIVO | M4: VARIACION | O4: INDICADORES
B5: {=INDIRECT("datos!a2:g22")} -> 13 | D5: 26552325 | E5: 1391.1308 | F5: 28747167 | G5: 3707.2705 | H5: 2272325 | J5: ACTIVO 1 | K5: =27*11680+51*11680+71*11480 -> 1726120 | L5: =SUMIF(CUENTAS!$1:$1,J5,CUENTAS!$2:$2) -> 2604140 | M5: =(L5-K5)/K5 -> 0.50866684 | O5: TIEMPO | P5: TASA | Q5: EA
B6: 14 | D6: 0.086859262 | E6: 0.079699031 | F6: 0.079849388 | G6: -0.26750041 | H6: 0.0016341539 | J6: ACTIVO 2 | K6: =1886815/38*12+33*54900 -> 2407536.3 | L6: =SUMIF(CUENTAS!$1:$1,J6,CUENTAS!$2:$2) -> 2470500 | M6: =(L6-K6)/K6 -> 0.026152745 | O6: =TODAY()-O7 -> 67 | P6: =(BALANCE!C10-GRAFICO!B77)/GRAFICO!B77 -> -0.004011439 | Q6: =(1+P6)^(365/O6)-1 -> -0.021659305
B7: 46098 | J7: ACTIVO 3 | K7: =6*70900 -> 425400 | L7: =SUMIF(CUENTAS!$1:$1,J7,CUENTAS!$2:$2) -> 373680 | M7: =(L7-abs(K7))/abs(K7) -> -0.12157969 | O7: 46023
B8: 46097 | J8: ACTIVO 4 | K8: =44081.18*80 -> 3526494.4 | L8: =SUMIF(CUENTAS!$1:$1,J8,CUENTAS!$2:$2) -> 3328000 | M8: =(L8-K8)/K8 -> -0.056286606 | O8: INVERSION | P8: VALORIZACION | Q8: RENTABILIDAD
B9: 46096 | J9: ACTIVO 20 | K9: 283000 | L9: =SUMIF(CUENTAS!$1:$1,J9,CUENTAS!$2:$2) -> 283608 | M9: =(L9-K9)/K9 -> 0.0021484099 | O9: =DATOS!C2 -> 26552325 | P9: =DATOS!E2 -> 28747167 | Q9: =P9-O9 -> 2194842
B10: 46095 | J10: ACTIVO 6 | K10: =2*70000 -> 140000 | L10: =SUMIF(CUENTAS!$1:$1,J10,CUENTAS!$2:$2) -> 135000 | M10: =(L10-K10)/K10 -> -0.035714286 | O10: EFECTIVO | P10: ACTIVOS | Q10: COMISION
B11: 46094 | J11: ACTIVO 7 | K11: =59*17040 -> 1005360 | L11: =SUMIF(CUENTAS!$1:$1,J11,CUENTAS!$2:$2) -> 962880 | M11: =(L11-K11)/K11 -> -0.042253521 | O11: =SUMIF(J5:J26,"cartera",L5:L26) -> 3876499.8 | P11: =SUM(L5:L24) -> 37025616 | Q11: =Q9*7% -> 153638.94
B12: 46093 | J12: ACTIVO 8 | K12: =64*15520+60*18700 -> 2115280 | L12: =SUMIF(CUENTAS!$1:$1,J12,CUENTAS!$2:$2) -> 2351040 | M12: =(L12-K12)/K12 -> 0.11145569 | O12: =AVERAGE(CUENTAS!$AA$60:AA1388) -> 1019726.7
B13: 46092 | J13: ACTIVO 9 | K13: =552000-150000 -> 402000 | L13: =SUMIF(CUENTAS!$1:$1,J13,CUENTAS!$2:$2) -> 814000 | M13: =(L13-K13)/K13 -> 1.0248756
B14: 46091 | J14: ACTIVO 10 | K14: =654000+1573000 -> 2227000 | L14: =SUMIF(CUENTAS!$1:$1,J14,CUENTAS!$2:$2) -> 1090000 | M14: =(L14-K14)/K14 -> -0.51055231
B15: 46090 | J15: ACTIVO 11 | K15: =654000+1197400 -> 1851400 | L15: =SUMIF(CUENTAS!$1:$1,J15,CUENTAS!$2:$2) -> 1195525 | M15: =(L15-K15)/K15 -> -0.35425894
B16: 46089 | C16: 2122000 | D16: 26552325 | E16: 1391.1308 | F16: 28747167 | G16: 3707.2705 | H16: 2272325 | J16: ACTIVO 12 | K16: =815330+1524360+600000 -> 2939690 | L16: =SUMIF(CUENTAS!$1:$1,J16,CUENTAS!$2:$2) -> 1704253 | M16: =(L16-K16)/K16 -> -0.42026098
B17: 46088 | D17: 24430325 | E17: 1288.4431 | F17: 26621460 | G17: 5061.1229 | H17: 2268617.7 | J17: ACTIVO 13 | K17: =882000+112000+180000+180000+220000+220000+85000+220000 -> 2099000 | L17: =SUMIF(CUENTAS!$1:$1,J17,CUENTAS!$2:$2) -> 578622.2 | M17: =(L17-K17)/K17 -> -0.72433435
B18: 46087 | D18: 24430325 | E18: 1288.4431 | F18: 26616399 | G18: -62284.025 | H18: 2263556.6 | J18: ACTIVO 14 | K18: 1000000 | L18: =SUMIF(CUENTAS!$1:$1,J18,CUENTAS!$2:$2) -> 5071335 | M18: =(L18-K18)/K18 -> 4.071335
B19: 46086 | D19: 24430325 | E19: 1288.4431 | F19: 26678683 | G19: -6089.1721 | H19: 2325840.6 | J19: ACTIVO 15 | K19: 1300000 | L19: =SUMIF(CUENTAS!$1:$1,J19,CUENTAS!$2:$2) -> 1344990.1 | M19: =(L19-K19)/K19 -> 0.034607748
B20: 46085 | D20: 24430325 | E20: 1288.4431 | F20: 26684772 | G20: -3934.3195 | H20: 2331929.8 | J20: ACTIVO 16 | K20: =3005000 -> 3005000 | L20: =SUMIF(CUENTAS!$1:$1,J20,CUENTAS!$2:$2) -> 3649929.6 | M20: =(L20-K20)/K20 -> 0.21461884
B21: 46084 | C21: 110000 | D21: 24430325 | E21: 1288.4431 | F21: 26688706 | G21: -35866.467 | H21: 2335864.1 | J21: ACTIVO 17 | K21: =493*2305 -> 1136365 | L21: =SUMIF(CUENTAS!$1:$1,J21,CUENTAS!$2:$2) -> 1019085 | M21: =(L21-K21)/K21 -> -0.10320628
B22: 46083 | D22: 24320325 | E22: 1283.1327 | F22: 26614573 | G22: -567681.61 | H22: 2371730.5 | J22: ACTIVO 18 | K22: 865000 | L22: =SUMIF(CUENTAS!$1:$1,J22,CUENTAS!$2:$2) -> 1139540.2 | M22: =(L22-K22)/K22 -> 0.31738755
B23: 46082 | D23: 24320325 | E23: 1283.1327 | F23: 27182254 | G23: -10341.762 | H23: 2939412.2 | J23: ACTIVO 19 | K23: =230000*5 -> 1150000 | L23: =SUMIF(CUENTAS!$1:$1,J23,CUENTAS!$2:$2) -> 3032988.4 | M23: =(L23-K23)/K23 -> 1.6373812
B24: 46081 | D24: 24320325 | E24: 1283.1327 | F24: 27192596 | G24: -10341.909 | H24: 2949753.9 | J24: CARTERA | K24: 3876000 | L24: =SUMIF(CUENTAS!$1:$1,J24,CUENTAS!$2:$2) -> 3876499.8 | M24: =(L24-K24)/K24 -> 0.00012894737
B25: 46080 | D25: 24320325 | E25: 1283.1327 | F25: 27202938 | G25: -383792.06 | H25: 2960095.8 | J25: APALANCAMIENTO | K25: =-3450000-4000000 -> -7450000 | L25: =-SUMIF(CUENTAS!$1:$1,J25,CUENTAS!$2:$2) -> -8273161.2 | M25: =(L25-K25)/K25 -> 0.11049144
J26: GASTOS | L26: =SUMIF(CUENTAS!$1:$1,J26,CUENTAS!$2:$2) -> 5288.0822

Sheet DATOS
A1: FECHA | B1: DEPOSITO | C1: TOTAL | D1: UNIDADES | E1: VOLUMEN | F1: GANANCIA | G1: RENTABILIDAD
A2: =IFERROR(__xludf.DUMMYFUNCTION("MIN(FILTER(ROW($C$4:$C1385),MMULT(N(LEN($C$4:$G1385)>0), TRANSPOSE(COLUMN($C$4:$G$4)^0)) = COLUMNS($C$4:$G1385)))"),13.0) -> 13 | C2: =INDIRECT(ADDRESS($A$2, COLUMN())) -> 26552325 | D2: =INDIRECT(ADDRESS($A$2, COLUMN())) -> 1391.1308 | E2: =INDIRECT(ADDRESS($A$2, COLUMN())) -> 28747167 | F2: =INDIRECT(ADDRESS($A$2, COLUMN())) -> 3707.2705 | G2: =INDIRECT(ADDRESS($A$2, COLUMN())) -> 2272325
A3: =A2+1 -> 14 | C3: =(INDIRECT(ADDRESS($A$2, COLUMN()))-INDIRECT(ADDRESS($A$3, COLUMN())))/INDIRECT(ADDRESS($A$3, COLUMN())) -> 0.086859262 | D3: =(INDIRECT(ADDRESS($A$2, COLUMN()))-INDIRECT(ADDRESS($A$3, COLUMN())))/INDIRECT(ADDRESS($A$3, COLUMN())) -> 0.079699031 | E3: =(INDIRECT(ADDRESS($A$2, COLUMN()))-INDIRECT(ADDRESS($A$3, COLUMN())))/INDIRECT(ADDRESS($A$3, COLUMN())) -> 0.079849388 | F3: =(INDIRECT(ADDRESS($A$2, COLUMN()))-INDIRECT(ADDRESS($A$3, COLUMN())))/INDIRECT(ADDRESS($A$3, COLUMN())) -> -0.26750041 | G3: =(INDIRECT(ADDRESS($A$2, COLUMN()))-INDIRECT(ADDRESS($A$3, COLUMN())))/INDIRECT(ADDRESS($A$3, COLUMN())) -> 0.0016341539
A4: 46098 | C4: =IF(D4="","",C5+B4) | D4: =IF(E4="","",D5) | E4: =IFERROR(__xludf.DUMMYFUNCTION("FILTER(CUENTAS!AB:AB,A4=CUENTAS!A:A) "),"") | F4: =(IF(E4<>0,E4-E5-B4,"")) | G4: =IF(E4="","",G5+F4) | H4: =IF(E4="","",1-C4/E4)
A5: 46097 | C5: =IF(D5="","",C6+B5) | D5: =IF(E5="","",D6) | E5: =IFERROR(__xludf.DUMMYFUNCTION("FILTER(CUENTAS!AB:AB,A5=CUENTAS!A:A) "),"") | F5: =(IF(E5<>0,E5-E6-B5,"")) | G5: =IF(E5="","",G6+F5) | H5: =IF(E5="","",1-C5/E5)
A6: 46096 | C6: =IF(D6="","",C7+B6) | D6: =IF(E6="","",D7) | E6: =IFERROR(__xludf.DUMMYFUNCTION("FILTER(CUENTAS!AB:AB,A6=CUENTAS!A:A) "),"") | F6: =(IF(E6<>0,E6-E7-B6,"")) | G6: =IF(E6="","",G7+F6) | H6: =IF(E6="","",1-C6/E6)
A7: 46095 | C7: =IF(D7="","",C8+B7) | D7: =IF(E7="","",D8) | E7: =IFERROR(__xludf.DUMMYFUNCTION("FILTER(CUENTAS!AB:AB,A7=CUENTAS!A:A) "),"") | F7: =(IF(E7<>0,E7-E8-B7,"")) | G7: =IF(E7="","",G8+F7) | H7: =IF(E7="","",1-C7/E7)
A8: 46094 | C8: =IF(D8="","",C9+B8) | D8: =IF(E8="","",D9) | E8: =IFERROR(__xludf.DUMMYFUNCTION("FILTER(CUENTAS!AB:AB,A8=CUENTAS!A:A) "),"") | F8: =(IF(E8<>0,E8-E9-B8,"")) | G8: =IF(E8="","",G9+F8) | H8: =IF(E8="","",1-C8/E8)
A9: 46093 | C9: =IF(D9="","",C10+B9) | D9: =IF(E9="","",D10) | E9: =IFERROR(__xludf.DUMMYFUNCTION("FILTER(CUENTAS!AB:AB,A9=CUENTAS!A:A) "),"") | F9: =(IF(E9<>0,E9-E10-B9,"")) | G9: =IF(E9="","",G10+F9) | H9: =IF(E9="","",1-C9/E9)
A10: 46092 | C10: =IF(D10="","",C11+B10) | D10: =IF(E10="","",D11) | E10: =IFERROR(__xludf.DUMMYFUNCTION("FILTER(CUENTAS!AB:AB,A10=CUENTAS!A:A) "),"") | F10: =(IF(E10<>0,E10-E11-B10,"")) | G10: =IF(E10="","",G11+F10) | H10: =IF(E10="","",1-C10/E10)
A11: 46091 | C11: =IF(D11="","",C12+B11) | D11: =IF(E11="","",D12) | E11: =IFERROR(__xludf.DUMMYFUNCTION("FILTER(CUENTAS!AB:AB,A11=CUENTAS!A:A) "),"") | F11: =(IF(E11<>0,E11-E12-B11,"")) | G11: =IF(E11="","",G12+F11) | H11: =IF(E11="","",1-C11/E11)
A12: 46090 | C12: =IF(D12="","",C13+B12) | D12: =IF(E12="","",D13) | E12: =IFERROR(__xludf.DUMMYFUNCTION("FILTER(CUENTAS!AB:AB,A12=CUENTAS!A:A) "),"") | F12: =(IF(E12<>0,E12-E13-B12,"")) | G12: =IF(E12="","",G13+F12) | H12: =IF(E12="","",1-C12/E12)
A13: 46089 | B13: 2122000 | C13: =IF(D13="","",C14+B13) -> 26552325 | D13: =IF(E13="","",D14)+102.687666 -> 1391.1308 | E13: =IFERROR(__xludf.DUMMYFUNCTION("FILTER(CUENTAS!AB:AB,A13=CUENTAS!A:A) "),2.8747167022311553E7) -> 28747167 | F13: =(IF(E13<>0,E13-E14-B13,"")) -> 3707.2705 | G13: =IF(E13="","",G14+F13) -> 2272325 | H13: =IF(E13="","",1-C13/E13) -> 0.076349852
A14: 46088 | C14: =IF(D14="","",C15+B14) -> 24430325 | D14: =IF(E14="","",D15) -> 1288.4431 | E14: =IFERROR(__xludf.DUMMYFUNCTION("FILTER(CUENTAS!AB:AB,A14=CUENTAS!A:A) "),2.6621459751843043E7) -> 26621460 | F14: =(IF(E14<>0,E14-E15-B14,"")) -> 5061.1229 | G14: =IF(E14="","",G15+F14) -> 2268617.7 | H14: =IF(E14="","",1-C14/E14) -> 0.082307083
A15: 46087 | C15: =IF(D15="","",C16+B15) -> 24430325 | D15: =IF(E15="","",D16) -> 1288.4431 | E15: =IFERROR(__xludf.DUMMYFUNCTION("FILTER(CUENTAS!AB:AB,A15=CUENTAS!A:A) "),2.661639862891269E7) -> 26616399 | F15: =(IF(E15<>0,E15-E16-B15,"")) -> -62284.025 | G15: =IF(E15="","",G16+F15) -> 2263556.6 | H15: =IF(E15="","",1-C15/E15) -> 0.082132583
A16: 46086 | C16: =IF(D16="","",C17+B16) -> 24430325 | D16: =IF(E16="","",D17) -> 1288.4431 | E16: =IFERROR(__xludf.DUMMYFUNCTION("FILTER(CUENTAS!AB:AB,A16=CUENTAS!A:A) "),2.6678682653491E7) -> 26678683 | F16: =(IF(E16<>0,E16-E17-B16,"")) -> -6089.1721 | G16: =IF(E16="","",G17+F16) -> 2325840.6 | H16: =IF(E16="","",1-C16/E16) -> 0.084275435
A17: 46085 | C17: =IF(D17="","",C18+B17) -> 24430325 | D17: =IF(E17="","",D18) -> 1288.4431 | E17: =IFERROR(__xludf.DUMMYFUNCTION("FILTER(CUENTAS!AB:AB,A17=CUENTAS!A:A) "),2.6684771825548477E7) -> 26684772 | F17: =(IF(E17<>0,E17-E18-B17,"")) -> -3934.3195 | G17: =IF(E17="","",G18+F17) -> 2331929.8 | H17: =IF(E17="","",1-C17/E17) -> 0.084484394
A18: 46084 | B18: =50000+60000 -> 110000 | C18: =IF(D18="","",C19+B18) -> 24430325 | D18: =IF(E18="","",D19)+2.413836+2.896603 -> 1288.4431 | E18: =IFERROR(__xludf.DUMMYFUNCTION("FILTER(CUENTAS!AB:AB,A18=CUENTAS!A:A) "),2.6688706145055633E7) -> 26688706 | F18: =(IF(E18<>0,E18-E19-B18,"")) -> -35866.467 | G18: =IF(E18="","",G19+F18) -> 2335864.1 | H18: =IF(E18="","",1-C18/E18) -> 0.084619354
A19: 46083 | C19: =IF(D19="","",C20+B19) -> 24320325 | D19: =IF(E19="","",D20) -> 1283.1327 | E19: =IFERROR(__xludf.DUMMYFUNCTION("FILTER(CUENTAS!AB:AB,A19=CUENTAS!A:A) "),2.6614572611982983E7) -> 26614573 | F19: =(IF(E19<>0,E19-E20-B19,"")) -> -567681.61 | G19: =IF(E19="","",G20+F19) -> 2371730.5 | H19: =IF(E19="","",1-C19/E19) -> 0.086202682
A20: 46082 | C20: =IF(D20="","",C21+B20) -> 24320325 | D20: =IF(E20="","",D21) -> 1283.1327 | E20: =IFERROR(__xludf.DUMMYFUNCTION("FILTER(CUENTAS!AB:AB,A20=CUENTAS!A:A) "),2.718225422630104E7) -> 27182254 | F20: =(IF(E20<>0,E20-E21-B20,"")) -> -10341.762 | G20: =IF(E20="","",G21+F20) -> 2939412.2 | H20: =IF(E20="","",1-C20/E20) -> 0.10528667
A21: 46081 | C21: =IF(D21="","",C22+B21) -> 24320325 | D21: =IF(E21="","",D22) -> 1283.1327 | E21: =IFERROR(__xludf.DUMMYFUNCTION("FILTER(CUENTAS!AB:AB,A21=CUENTAS!A:A) "),2.719259598798034E7) -> 27192596 | F21: =(IF(E21<>0,E21-E22-B21,"")) -> -10341.909 | G21: =IF(E21="","",G22+F21) -> 2949753.9 | H21: =IF(E21="","",1-C21/E21) -> 0.10562695
A22: 46080 | C22: =IF(D22="","",C23+B22) -> 24320325 | D22: =IF(E22="","",D23) -> 1283.1327 | E22: =IFERROR(__xludf.DUMMYFUNCTION("FILTER(CUENTAS!AB:AB,A22=CUENTAS!A:A) "),2.7202937896991413E7) -> 27202938 | F22: =(IF(E22<>0,E22-E23-B22,"")) -> -383792.06 | G22: =IF(E22="","",G23+F22) -> 2960095.8 | H22: =IF(E22="","",1-C22/E22) -> 0.10596697
A23: 46079 | C23: =IF(D23="","",C24+B23) -> 24320325 | D23: =IF(E23="","",D24) -> 1283.1327 | E23: =IFERROR(__xludf.DUMMYFUNCTION("FILTER(CUENTAS!AB:AB,A23=CUENTAS!A:A) "),2.7586729953304805E7) -> 27586730 | F23: =(IF(E23<>0,E23-E24-B23,"")) -> -464122.2 | G23: =IF(E23="","",G24+F23) -> 3343887.9 | H23: =IF(E23="","",1-C23/E23) -> 0.11840493
A24: 46078 | C24: =IF(D24="","",C25+B24) -> 24320325 | D24: =IF(E24="","",D25) -> 1283.1327 | E24: =IFERROR(__xludf.DUMMYFUNCTION("FILTER(CUENTAS!AB:AB,A24=CUENTAS!A:A) "),2.8050852156891055E7) -> 28050852 | F24: =(IF(E24<>0,E24-E25-B24,"")) -> 1367.6492 | G24: =IF(E24="","",G25+F24) -> 3808010.1 | H24: =IF(E24="","",1-C24/E24) -> 0.13299158
A25: 46077 | C25: =IF(D25="","",C26+B25) -> 24320325 | D25: =IF(E25="","",D26) -> 1283.1327 | E25: =IFERROR(__xludf.DUMMYFUNCTION("FILTER(CUENTAS!AB:AB,A25=CUENTAS!A:A) "),2.804948450772072E7) -> 28049485 | F25: =(IF(E25<>0,E25-E26-B25,"")) -> 56391.338 | G25: =IF(E25="","",G26+F25) -> 3806642.4 | H25: =IF(E25="","",1-C25/E25) -> 0.1329493
A26: 46076 | C26: =IF(D26="","",C27+B26) -> 24320325 | D26: =IF(E26="","",D27) -> 1283.1327 | E26: =IFERROR(__xludf.DUMMYFUNCTION("FILTER(CUENTAS!AB:AB,A26=CUENTAS!A:A) "),2.799309317022235E7) -> 27993093 | F26: =(IF(E26<>0,E26-E27-B26,"")) -> -186243.93 | G26: =IF(E26="","",G27+F26) -> 3750251.1 | H26: =IF(E26="","",1-C26/E26) -> 0.13120265
A27: 46075 | C27: =IF(D27="","",C28+B27) -> 24320325 | D27: =IF(E27="","",D28) -> 1283.1327 | E27: =IFERROR(__xludf.DUMMYFUNCTION("FILTER(CUENTAS!AB:AB,A27=CUENTAS!A:A) "),2.8179337103580892E7) -> 28179337 | F27: =(IF(E27<>0,E27-E28-B27,"")) -> -4939.0838 | G27: =IF(E27="","",G28+F27) -> 3936495 | H27: =IF(E27="","",1-C27/E27) -> 0.13694474
A28: 46074 | C28: =IF(D28="","",C29+B28) -> 24320325 | D28: =IF(E28="","",D29) -> 1283.1327 | E28: =IFERROR(__xludf.DUMMYFUNCTION("FILTER(CUENTAS!AB:AB,A28=CUENTAS!A:A) "),2.818427618742424E7) -> 28184276 | F28: =(IF(E28<>0,E28-E29-B28,"")) -> -4939.2343 | G28: =IF(E28="","",G29+F28) -> 3941434.1 | H28: =IF(E28="","",1-C28/E28) -> 0.13709599
A29: 46073 | C29: =IF(D29="","",C30+B29) -> 24320325 | D29: =IF(E29="","",D30) -> 1283.1327 | E29: =IFERROR(__xludf.DUMMYFUNCTION("FILTER(CUENTAS!AB:AB,A29=CUENTAS!A:A) "),2.81892154217223E7) -> 28189215 | F29: =(IF(E29<>0,E29-E30-B29,"")) -> 180220.62 | G29: =IF(E29="","",G30+F29) -> 3946373.4 | H29: =IF(E29="","",1-C29/E29) -> 0.13724718
A30: 46072 | C30: =IF(D30="","",C31+B30) -> 24320325 | D30: =IF(E30="","",D31) -> 1283.1327 | E30: =IFERROR(__xludf.DUMMYFUNCTION("FILTER(CUENTAS!AB:AB,A30=CUENTAS!A:A) "),2.8008994806445E7) -> 28008995 | F30: =(IF(E30<>0,E30-E31-B30,"")) -> 194640.46 | G30: =IF(E30="","",G31+F30) -> 3766152.7 | H30: =IF(E30="","",1-C30/E30) -> 0.1316959
A31: 46071 | C31: =IF(D31="","",C32+B31) -> 24320325 | D31: =IF(E31="","",D32) -> 1283.1327 | E31: =IFERROR(__xludf.DUMMYFUNCTION("FILTER(CUENTAS!AB:AB,A31=CUENTAS!A:A) "),2.781435434156225E7) -> 27814354 | F31: =(IF(E31<>0,E31-E32-B31,"")) -> 83900.315 | G31: =IF(E31="","",G32+F31) -> 3571512.3 | H31: =IF(E31="","",1-C31/E31) -> 0.12561964
A32: 46070 | B32: 90000 | C32: =IF(D32="","",C33+B32) -> 24320325 | D32: =IF(E32="","",D33)+4.164445 -> 1283.1327 | E32: =IFERROR(__xludf.DUMMYFUNCTION("FILTER(CUENTAS!AB:AB,A32=CUENTAS!A:A) "),2.773045402704398E7) -> 27730454 | F32: =(IF(E32<>0,E32-E33-B32,"")) -> 6160.1642 | G32: =IF(E32="","",G33+F32) -> 3487612 | H32: =IF(E32="","",1-C32/E32) -> 0.12297415
A33: 46069 | B33: 250000 | C33: =IF(D33="","",C34+B33) -> 24230325 | D33: =IF(E33="","",D34)+11.57048 -> 1278.9682 | E33: =IFERROR(__xludf.DUMMYFUNCTION("FILTER(CUENTAS!AB:AB,A33=CUENTAS!A:A) "),2.7634293862860125E7) -> 27634294 | F33: =(IF(E33<>0,E33-E34-B33,"")) -> -91959.986 | G33: =IF(E33="","",G34+F33) -> 3481451.8 | H33: =IF(E33="","",1-C33/E33) -> 0.12317915
A34: 46068 | B34: =104250-203044.2209+11687+73044 -> -14063.221 | C34: =IF(D34="","",C35+B34) -> 23980325 | D34: =IF(E34="","",D35)+4.808742-9.36583+0.539086 -> 1267.3977 | E34: =IFERROR(__xludf.DUMMYFUNCTION("FILTER(CUENTAS!AB:AB,A34=CUENTAS!A:A) "),2.7476253848980635E7) -> 27476254 | F34: =(IF(E34<>0,E34-E35-B34,""))+73044 -> -6339.9155 | G34: =IF(E34="","",G35+F34) -> 3573411.8 | H34: =IF(E34="","",1-C34/E34) -> 0.12723455
A35: 46067 | C35: =IF(D35="","",C36+B35) -> 23994388 | D35: =IF(E35="","",D36) -> 1271.4157 | E35: =IFERROR(__xludf.DUMMYFUNCTION("FILTER(CUENTAS!AB:AB,A35=CUENTAS!A:A) "),2.756970098537543E7) -> 27569701 | F35: =(IF(E35<>0,E35-E36-B35,"")) -> 361052.71 | G35: =IF(E35="","",G36+F35) -> 3579751.7 | H35: =IF(E35="","",1-C35/E35) -> 0.12968268
A36: 46066 | C36: =IF(D36="","",C37+B36) -> 23994388 | D36: =IF(E36="","",D37) -> 1271.4157 | E36: =IFERROR(__xludf.DUMMYFUNCTION("FILTER(CUENTAS!AB:AB,A36=CUENTAS!A:A) "),2.720864827201448E7) -> 27208648 | F36: =(IF(E36<>0,E36-E37-B36,"")) -> 138559.56 | G36: =IF(E36="","",G37+F36) -> 3218699 | H36: =IF(E36="","",1-C36/E36) -> 0.11813376
A37: 46065 | C37: =IF(D37="","",C38+B37) -> 23994388 | D37: =IF(E37="","",D38) -> 1271.4157 | E37: =IFERROR(__xludf.DUMMYFUNCTION("FILTER(CUENTAS!AB:AB,A37=CUENTAS!A:A) "),2.7070088708867736E7) -> 27070089 | F37: =(IF(E37<>0,E37-E38-B37,"")) -> -189680.59 | G37: =IF(E37="","",G38+F37) -> 3080139.4 | H37: =IF(E37="","",1-C37/E37) -> 0.11361989
A38: 46064 | C38: =IF(D38="","",C39+B38) -> 23994388 | D38: =IF(E38="","",D39) -> 1271.4157 | E38: =IFERROR(__xludf.DUMMYFUNCTION("FILTER(CUENTAS!AB:AB,A38=CUENTAS!A:A) "),2.725976929590516E7) -> 27259769 | F38: =(IF(E38<>0,E38-E39-B38,"")) -> -255520.74 | G38: =IF(E38="","",G39+F38) -> 3269820 | H38: =IF(E38="","",1-C38/E38) -> 0.11978755
A39: 46063 | C39: =IF(D39="","",C40+B39) -> 23994388 | D39: =IF(E39="","",D40) -> 1271.4157 | E39: =IFERROR(__xludf.DUMMYFUNCTION("FILTER(CUENTAS!AB:AB,A39=CUENTAS!A:A) "),2.7515290033096723E7) -> 27515290 | F39: =(IF(E39<>0,E39-E40-B39,"")) -> 10579.113 | G39: =IF(E39="","",G40+F39) -> 3525340.8 | H39: =IF(E39="","",1-C39/E39) -> 0.12796164
A40: 46062 | C40: =IF(D40="","",C41+B40) -> 23994388 | D40: =IF(E40="","",D41) -> 1271.4157 | E40: =IFERROR(__xludf.DUMMYFUNCTION("FILTER(CUENTAS!AB:AB,A40=CUENTAS!A:A) "),2.7504710920412406E7) -> 27504711 | F40: =(IF(E40<>0,E40-E41-B40,"")) -> 140518.96 | G40: =IF(E40="","",G41+F40) -> 3514761.6 | H40: =IF(E40="","",1-C40/E40) -> 0.12762623
A41: 46061 | C41: =IF(D41="","",C42+B41) -> 23994388 | D41: =IF(E41="","",D42) -> 1271.4157 | E41: =IFERROR(__xludf.DUMMYFUNCTION("FILTER(CUENTAS!AB:AB,A41=CUENTAS!A:A) "),2.7364191957822178E7) -> 27364192 | F41: =(IF(E41<>0,E41-E42-B41,"")) -> -6341.1875 | G41: =IF(E41="","",G42+F41) -> 3374242.7 | H41: =IF(E41="","",1-C41/E41) -> 0.12314647
A42: 46060 | C42: =IF(D42="","",C43+B42) -> 23994388 | D42: =IF(E42="","",D43) -> 1271.4157 | E42: =IFERROR(__xludf.DUMMYFUNCTION("FILTER(CUENTAS!AB:AB,A42=CUENTAS!A:A) "),2.7370533145296037E7) -> 27370533 | F42: =(IF(E42<>0,E42-E43-B42,"")) -> -6341.3375 | G42: =IF(E42="","",G43+F42) -> 3380583.9 | H42: =IF(E42="","",1-C42/E42) -> 0.12334962
A43: 46059 | C43: =IF(D43="","",C44+B43) -> 23994388 | D43: =IF(E43="","",D44) -> 1271.4157 | E43: =IFERROR(__xludf.DUMMYFUNCTION("FILTER(CUENTAS!AB:AB,A43=CUENTAS!A:A) "),2.7376874482803974E7) -> 27376874 | F43: =(IF(E43<>0,E43-E44-B43,"")) -> 198858.51 | G43: =IF(E43="","",G44+F43) -> 3386925.2 | H43: =IF(E43="","",1-C43/E43) -> 0.12355268
A44: 46058 | C44: =IF(D44="","",C45+B44) -> 23994388 | D44: =IF(E44="","",D45) -> 1271.4157 | E44: =IFERROR(__xludf.DUMMYFUNCTION("FILTER(CUENTAS!AB:AB,A44=CUENTAS!A:A) "),2.7178015970315985E7) -> 27178016 | F44: =(IF(E44<>0,E44-E45-B44,"")) -> -384581.64 | G44: =IF(E44="","",G45+F44) -> 3188066.7 | H44: =IF(E44="","",1-C44/E44) -> 0.11713981
A45: 46057 | C45: =IF(D45="","",C46+B45) -> 23994388 | D45: =IF(E45="","",D46) -> 1271.4157 | E45: =IFERROR(__xludf.DUMMYFUNCTION("FILTER(CUENTAS!AB:AB,A45=CUENTAS!A:A) "),2.756259760780207E7) -> 27562598 | F45: =(IF(E45<>0,E45-E46-B45,"")) -> -71881.787 | G45: =IF(E45="","",G46+F45) -> 3572648.3 | H45: =IF(E45="","",1-C45/E45) -> 0.12945838
A46: 46056 | C46: =IF(D46="","",C47+B46) -> 23994388 | D46: =IF(E46="","",D47) -> 1271.4157 | E46: =IFERROR(__xludf.DUMMYFUNCTION("FILTER(CUENTAS!AB:AB,A46=CUENTAS!A:A) "),2.7634479395232253E7) -> 27634479 | F46: =(IF(E46<>0,E46-E47-B46,"")) -> -2061.9373 | G46: =IF(E46="","",G47+F46) -> 3644530.1 | H46: =IF(E46="","",1-C46/E46) -> 0.1317228
A47: 46055 | C47: =IF(D47="","",C48+B47) -> 23994388 | D47: =IF(E47="","",D48) -> 1271.4157 | E47: =IFERROR(__xludf.DUMMYFUNCTION("FILTER(CUENTAS!AB:AB,A47=CUENTAS!A:A) "),2.7636541332576543E7) -> 27636541 | F47: =(IF(E47<>0,E47-E48-B47,"")) -> -217322.09 | G47: =IF(E47="","",G48+F47) -> 3646592 | H47: =IF(E47="","",1-C47/E47) -> 0.13178759
A48: 46054 | C48: =IF(D48="","",C49+B48) -> 23994388 | D48: =IF(E48="","",D49) -> 1271.4157 | E48: =IFERROR(__xludf.DUMMYFUNCTION("FILTER(CUENTAS!AB:AB,A48=CUENTAS!A:A) "),2.7853863419804964E7) -> 27853863 | F48: =(IF(E48<>0,E48-E49-B48,"")) -> -42.237083 | G48: =IF(E48="","",G49+F48) -> 3863914.1 | H48: =IF(E48="","",1-C48/E48) -> 0.13856157
A49: 46053 | C49: =IF(D49="","",C50+B49) -> 23994388 | D49: =IF(E49="","",D50) -> 1271.4157 | E49: =IFERROR(__xludf.DUMMYFUNCTION("FILTER(CUENTAS!AB:AB,A49=CUENTAS!A:A) "),2.7853905656887542E7) -> 27853906 | F49: =(IF(E49<>0,E49-E50-B49,"")) -> -26742.387 | G49: =IF(E49="","",G50+F49) -> 3863956.4 | H49: =IF(E49="","",1-C49/E49) -> 0.13856288
A50: 46052 | C50: =IF(D50="","",C51+B50) -> 23994388 | D50: =IF(E50="","",D51) -> 1271.4157 | E50: =IFERROR(__xludf.DUMMYFUNCTION("FILTER(CUENTAS!AB:AB,A50=CUENTAS!A:A) "),2.7880648043794326E7) -> 27880648 | F50: =(IF(E50<>0,E50-E51-B50,"")) -> 33537.463 | G50: =IF(E50="","",G51+F50) -> 3890698.8 | H50: =IF(E50="","",1-C50/E50) -> 0.13938915
A51: 46051 | B51: 1000000 | C51: =IF(D51="","",C52+B51) -> 23994388 | D51: =IF(E51="","",D52)+45.04911 -> 1271.4157 | E51: =IFERROR(__xludf.DUMMYFUNCTION("FILTER(CUENTAS!AB:AB,A51=CUENTAS!A:A) "),2.7847110580495346E7) -> 27847111 | F51: =(IF(E51<>0,E51-E52-B51,"")) -> -232662.69 | G51: =IF(E51="","",G52+F51) -> 3857161.3 | H51: =IF(E51="","",1-C51/E51) -> 0.13835268
A52: 46050 | C52: =IF(D52="","",C53+B52) -> 22994388 | D52: =IF(E52="","",D53) -> 1226.3666 | E52: =IFERROR(__xludf.DUMMYFUNCTION("FILTER(CUENTAS!AB:AB,A52=CUENTAS!A:A) "),2.7079773266960647E7) -> 27079773 | F52: =(IF(E52<>0,E52-E53-B52,"")) -> 119257.16 | G52: =IF(E52="","",G53+F52) -> 4089824 | H52: =IF(E52="","",1-C52/E52) -> 0.15086482
A53: 46049 | C53: =IF(D53="","",C54+B53) -> 22994388 | D53: =IF(E53="","",D54) -> 1226.3666 | E53: =IFERROR(__xludf.DUMMYFUNCTION("FILTER(CUENTAS!AB:AB,A53=CUENTAS!A:A) "),2.6960516103160284E7) -> 26960516 | F53: =(IF(E53<>0,E53-E54-B53,"")) -> -21322.986 | G53: =IF(E53="","",G54+F53) -> 3970566.8 | H53: =IF(E53="","",1-C53/E53) -> 0.14710875
A54: 46048 | C54: =IF(D54="","",C55+B54) -> 22994388 | D54: =IF(E54="","",D55) -> 1226.3666 | E54: =IFERROR(__xludf.DUMMYFUNCTION("FILTER(CUENTAS!AB:AB,A54=CUENTAS!A:A) "),2.698183908906432E7) -> 26981839 | F54: =(IF(E54<>0,E54-E55-B54,"")) -> 143956.86 | G54: =IF(E54="","",G55+F54) -> 3991889.8 | H54: =IF(E54="","",1-C54/E54) -> 0.14778277
A55: 46047 | B55: 230000 | C55: =IF(D55="","",C56+B55) -> 22994388 | D55: =IF(E55="","",D56)+1.351755+9.0117 -> 1226.3666 | E55: =IFERROR(__xludf.DUMMYFUNCTION("FILTER(CUENTAS!AB:AB,A55=CUENTAS!A:A) "),2.6837882224642817E7) -> 26837882 | F55: =(IF(E55<>0,E55-E56-B55,"")) -> 4956.7148 | G55: =IF(E55="","",G56+F55) -> 3847932.9 | H55: =IF(E55="","",1-C55/E55) -> 0.14321152
A56: 46046 | C56: =IF(D56="","",C57+B56) -> 22764388 | D56: =IF(E56="","",D57) -> 1216.0032 | E56: =IFERROR(__xludf.DUMMYFUNCTION("FILTER(CUENTAS!AB:AB,A56=CUENTAS!A:A) "),2.6602925509865843E7) -> 26602926 | F56: =(IF(E56<>0,E56-E57-B56,"")) -> 4956.5652 | G56: =IF(E56="","",G57+F56) -> 3842976.2 | H56: =IF(E56="","",1-C56/E56) -> 0.14429004
A57: 46045 | C57: =IF(D57="","",C58+B57) -> 22764388 | D57: =IF(E57="","",D58) -> 1216.0032 | E57: =IFERROR(__xludf.DUMMYFUNCTION("FILTER(CUENTAS!AB:AB,A57=CUENTAS!A:A) "),2.6597968944703486E7) -> 26597969 | F57: =(IF(E57<>0,E57-E58-B57,"")) -> 180856.42 | G57: =IF(E57="","",G58+F57) -> 3838019.7 | H57: =IF(E57="","",1-C57/E57) -> 0.14413058
A58: 46044 | C58: =IF(D58="","",C59+B58) -> 22764388 | D58: =IF(E58="","",D59) -> 1216.0032 | E58: =IFERROR(__xludf.DUMMYFUNCTION("FILTER(CUENTAS!AB:AB,A58=CUENTAS!A:A) "),2.6417112529125817E7) -> 26417113 | F58: =(IF(E58<>0,E58-E59-B58,"")) -> -45170.734 | G58: =IF(E58="","",G59+F58) -> 3657163.2 | H58: =IF(E58="","",1-C58/E58) -> 0.13827114
A59: 46043 | C59: =IF(D59="","",C60+B59) -> 22764388 | D59: =IF(E59="","",D60) -> 1216.0032 | E59: =IFERROR(__xludf.DUMMYFUNCTION("FILTER(CUENTAS!AB:AB,A59=CUENTAS!A:A) "),2.6462283263102937E7) -> 26462283 | F59: =(IF(E59<>0,E59-E60-B59,"")) -> 158389.12 | G59: =IF(E59="","",G60+F59) -> 3702334 | H59: =IF(E59="","",1-C59/E59) -> 0.1397421
A60: 46042 | C60: =IF(D60="","",C61+B60) -> 22764388 | D60: =IF(E60="","",D61) -> 1216.0032 | E60: =IFERROR(__xludf.DUMMYFUNCTION("FILTER(CUENTAS!AB:AB,A60=CUENTAS!A:A) "),2.630389414660493E7) -> 26303894 | F60: =(IF(E60<>0,E60-E61-B60,"")) -> 156844.97 | G60: =IF(E60="","",G61+F60) -> 3543944.9 | H60: =IF(E60="","",1-C60/E60) -> 0.13456205
A61: 46041 | B61: 938913.39 | C61: =IF(D61="","",C62+B61) -> 22764388 | D61: =IF(E61="","",D62) -> 1216.0032 | E61: =IFERROR(__xludf.DUMMYFUNCTION("FILTER(CUENTAS!AB:AB,A61=CUENTAS!A:A) "),2.61470491796019E7) -> 26147049 | F61: =(IF(E61<>0,E61-E62,"")) -> 207384.82 | G61: =IF(E61="","",G62+F61)-B61-250607 -> 3387099.9 | H61: =IF(E61="","",1-C61/E61) -> 0.12937066
A62: 46040 | B62: 200000 | C62: =IF(D62="","",C63+B62) -> 21825475 | D62: =IF(E62="","",D63)+9.24064 -> 1216.0032 | E62: =IFERROR(__xludf.DUMMYFUNCTION("FILTER(CUENTAS!AB:AB,A62=CUENTAS!A:A) "),2.593966436206395E7) -> 25939664 | F62: =(IF(E62<>0,E62-E63-B62,"")) -> 5574.6661 | G62: =IF(E62="","",G63+F62) -> 4369235.5 | H62: =IF(E62="","",1-C62/E62) -> 0.15860612
A63: 46039 | B63: =-1245186.2+39230 -> -1205956.2 | C63: =IF(D63="","",C64+B63) -> 21625475 | D63: =IF(E63="","",D64)-57.54239+1.812892 -> 1206.7625 | E63: =IFERROR(__xludf.DUMMYFUNCTION("FILTER(CUENTAS!AB:AB,A63=CUENTAS!A:A) "),2.573408969596081E7) -> 25734090 | F63: =(IF(E63<>0,E63-E64-B63,"")) -> 5674.5147 | G63: =IF(E63="","",G64+F63) -> 4363660.8 | H63: =IF(E63="","",1-C63/E63) -> 0.1596565
A64: 46038 | C64: =IF(D64="","",C65+B64) -> 22831431 | D64: =IF(E64="","",D65) -> 1262.492 | E64: =IFERROR(__xludf.DUMMYFUNCTION("FILTER(CUENTAS!AB:AB,A64=CUENTAS!A:A) "),2.6934371381262176E7) -> 26934371 | F64: =(IF(E64<>0,E64-E65-B64,"")) -> 300764.36 | G64: =IF(E64="","",G65+F64) -> 4357986.3 | H64: =IF(E64="","",1-C64/E64) -> 0.15233102
A65: 46037 | C65: =IF(D65="","",C66+B65) -> 22831431 | D65: =IF(E65="","",D66) -> 1262.492 | E65: =IFERROR(__xludf.DUMMYFUNCTION("FILTER(CUENTAS!AB:AB,A65=CUENTAS!A:A) "),2.663360701793779E7) -> 26633607 | F65: =(IF(E65<>0,E65-E66-B65,"")) -> 111024.21 | G65: =IF(E65="","",G66+F65) -> 4057221.9 | H65: =IF(E65="","",1-C65/E65) -> 0.14275858
A66: 46036 | C66: =IF(D66="","",C67+B66) -> 22831431 | D66: =IF(E66="","",D67) -> 1262.492 | E66: =IFERROR(__xludf.DUMMYFUNCTION("FILTER(CUENTAS!AB:AB,A66=CUENTAS!A:A) "),2.652258280595738E7) -> 26522583 | F66: =(IF(E66<>0,E66-E67-B66,"")) -> 13404.061 | G66: =IF(E66="","",G67+F66) -> 3946197.7 | H66: =IF(E66="","",1-C66/E66) -> 0.13917015
A67: 46035 | B67: 50000 | C67: =IF(D67="","",C68+B67) -> 22831431 | D67: =IF(E67="","",D68)+2.347643 -> 1262.492 | E67: =IFERROR(__xludf.DUMMYFUNCTION("FILTER(CUENTAS!AB:AB,A67=CUENTAS!A:A) "),2.650917874529068E7) -> 26509179 | F67: =(IF(E67<>0,E67-E68-B67,"")) -> -55596.091 | G67: =IF(E67="","",G68+F67) -> 3932793.6 | H67: =IF(E67="","",1-C67/E67) -> 0.13873488
A68: 46034 | C68: =IF(D68="","",C69+B68) -> 22781431 | D68: =IF(E68="","",D69) -> 1260.1444 | E68: =IFERROR(__xludf.DUMMYFUNCTION("FILTER(CUENTAS!AB:AB,A68=CUENTAS!A:A) "),2.6514774835907433E7) -> 26514775 | F68: =(IF(E68<>0,E68-E69-B68,"")) -> 5143.7581 | G68: =IF(E68="","",G69+F68) -> 3988389.7 | H68: =IF(E68="","",1-C68/E68) -> 0.14080239
A69: 46033 | C69: =IF(D69="","",C70+B69) -> 22781431 | D69: =IF(E69="","",D70) -> 1260.1444 | E69: =IFERROR(__xludf.DUMMYFUNCTION("FILTER(CUENTAS!AB:AB,A69=CUENTAS!A:A) "),2.6509631077777393E7) -> 26509631 | F69: =(IF(E69<>0,E69-E70-B69,"")) -> 5143.6069 | G69: =IF(E69="","",G70+F69) -> 3983246 | H69: =IF(E69="","",1-C69/E69) -> 0.14063568
A70: 46032 | C70: =IF(D70="","",C71+B70) -> 22781431 | D70: =IF(E70="","",D71) -> 1260.1444 | E70: =IFERROR(__xludf.DUMMYFUNCTION("FILTER(CUENTAS!AB:AB,A70=CUENTAS!A:A) "),2.6504487470870305E7) -> 26504487 | F70: =(IF(E70<>0,E70-E71-B70,"")) -> 5143.4557 | G70: =IF(E70="","",G71+F70) -> 3978102.4 | H70: =IF(E70="","",1-C70/E70) -> 0.14046891
A71: 46031 | C71: =IF(D71="","",C72+B71) -> 22781431 | D71: =IF(E71="","",D72) -> 1260.1444 | E71: =IFERROR(__xludf.DUMMYFUNCTION("FILTER(CUENTAS!AB:AB,A71=CUENTAS!A:A) "),2.649934401515594E7) -> 26499344 | F71: =(IF(E71<>0,E71-E72-B71,"")) -> 43823.305 | G71: =IF(E71="","",G72+F71) -> 3972958.9 | H71: =IF(E71="","",1-C71/E71) -> 0.14030207
A72: 46030 | C72: =IF(D72="","",C73+B72) -> 22781431 | D72: =IF(E72="","",D73) -> 1260.1444 | E72: =IFERROR(__xludf.DUMMYFUNCTION("FILTER(CUENTAS!AB:AB,A72=CUENTAS!A:A) "),2.645552071060406E7) -> 26455521 | F72: =(IF(E72<>0,E72-E73-B72,"")) -> 31523.153 | G72: =IF(E72="","",G73+F72) -> 3929135.6 | H72: =IF(E72="","",1-C72/E72) -> 0.13887799
A73: 46029 | C73: =IF(D73="","",C74+B73) -> 22781431 | D73: =IF(E73="","",D74) -> 1260.1444 | E73: =IFERROR(__xludf.DUMMYFUNCTION("FILTER(CUENTAS!AB:AB,A73=CUENTAS!A:A) "),2.6423997557184447E7) -> 26423998 | F73: =(IF(E73<>0,E73-E74-B73,"")) -> -25336.998 | G73: =IF(E73="","",G74+F73) -> 3897612.5 | H73: =IF(E73="","",1-C73/E73) -> 0.1378507
A74: 46028 | C74: =IF(D74="","",C75+B74) -> 22781431 | D74: =IF(E74="","",D75) -> 1260.1444 | E74: =IFERROR(__xludf.DUMMYFUNCTION("FILTER(CUENTAS!AB:AB,A74=CUENTAS!A:A) "),2.6449334554866873E7) -> 26449335 | F74: =(IF(E74<>0,E74-E75-B74,"")) -> -179420.97 | G74: =IF(E74="","",G75+F74) -> 3922949.5 | H74: =IF(E74="","",1-C74/E74) -> 0.13867659
A75: 46027 | C75: =IF(D75="","",C76+B75) -> 22781431 | D75: =IF(E75="","",D76) -> 1260.1444 | E75: =IFERROR(__xludf.DUMMYFUNCTION("FILTER(CUENTAS!AB:AB,A75=CUENTAS!A:A) "),2.662875552716553E7) -> 26628756 | F75: =(IF(E75<>0,E75-E76-B75,"")) -> 345722.72 | G75: =IF(E75="","",G76+F75) -> 4102370.4 | H75: =IF(E75="","",1-C75/E75) -> 0.14448007
A76: 46026 | C76: =IF(D76="","",C77+B76) -> 22781431 | D76: =IF(E76="","",D77) -> 1260.1444 | E76: =IFERROR(__xludf.DUMMYFUNCTION("FILTER(CUENTAS!AB:AB,A76=CUENTAS!A:A) "),2.6283032802968603E7) -> 26283033 | F76: =(IF(E76<>0,E76-E77-B76,"")) -> 2482.5852 | G76: =IF(E76="","",G77+F76) -> 3756647.7 | H76: =IF(E76="","",1-C76/E76) -> 0.1332267
A77: 46025 | C77: =IF(D77="","",C78+B77) -> 22781431 | D77: =IF(E77="","",D78) -> 1260.1444 | E77: =IFERROR(__xludf.DUMMYFUNCTION("FILTER(CUENTAS!AB:AB,A77=CUENTAS!A:A) "),2.6280550217790287E7) -> 26280550 | F77: =(IF(E77<>0,E77-E78-B77,"")) -> 2482.4462 | G77: =IF(E77="","",G78+F77) -> 3754165.1 | H77: =IF(E77="","",1-C77/E77) -> 0.13314482
A78: 46024 | C78: =IF(D78="","",C79+B78) -> 22781431 | D78: =IF(E78="","",D79) -> 1260.1444 | E78: =IFERROR(__xludf.DUMMYFUNCTION("FILTER(CUENTAS!AB:AB,A78=CUENTAS!A:A) "),2.6278067771602783E7) -> 26278068 | F78: =(IF(E78<>0,E78-E79-B78,"")) -> 132802.31 | G78: =IF(E78="","",G79+F78) -> 3751682.7 | H78: =IF(E78="","",1-C78/E78) -> 0.13306293
A79: 46023 | B79: 3300000 | C79: =IF(D79="","",C80+B79) -> 22781431 | D79: =IF(E79="","",D80)+4.750726 +9.501451+142.521771 -> 1260.1444 | E79: =IFERROR(__xludf.DUMMYFUNCTION("FILTER(CUENTAS!AB:AB,A79=CUENTAS!A:A) "),2.61452654643783E7) -> 26145265 | F79: =(IF(E79<>0,E79-E80-B79,"")) -> 2662.1723 | G79: =IF(E79="","",G80+F79) -> 3618880.4 | H79: =IF(E79="","",1-C79/E79) -> 0.12865941
A80: 46022 | C80: =IF(D80="","",C81+B80) -> 19481431 | D80: =IF(E80="","",D81) -> 1103.3704 | E80: =IFERROR(__xludf.DUMMYFUNCTION("FILTER(CUENTAS!AB:AB,A80=CUENTAS!A:A) "),2.2842603292089853E7) -> 22842603 | F80: =(IF(E80<>0,E80-E81-B80,"")) -> 2662.0374 | G80: =IF(E80="","",G81+F80) -> 3616218.2 | H80: =IF(E80="","",1-C80/E80) -> 0.14714488
A81: 46021 | B81: 200000 | C81: =IF(D81="","",C82+B81) -> 19481431 | D81: =IF(E81="","",D82)+9.50363 -> 1103.3704 | E81: =IFERROR(__xludf.DUMMYFUNCTION("FILTER(CUENTAS!AB:AB,A81=CUENTAS!A:A) "),2.2839941254710466E7) -> 22839941 | F81: =(IF(E81<>0,E81-E82-B81,"")) -> -624458.1 | G81: =IF(E81="","",G82+F81) -> 3613556.2 | H81: =IF(E81="","",1-C81/E81) -> 0.14704548
A82: 46020 | C82: =IF(D82="","",C83+B82) -> 19281431 | D82: =IF(E82="","",D83) -> 1093.8668 | E82: =IFERROR(__xludf.DUMMYFUNCTION("FILTER(CUENTAS!AB:AB,A82=CUENTAS!A:A) "),2.3264399352213155E7) -> 23264399 | F82: =(IF(E82<>0,E82-E83-B82,"")) -> 104461.77 | G82: =IF(E82="","",G83+F82) -> 4238014.3 | H82: =IF(E82="","",1-C82/E82) -> 0.17120443
A83: 46019 | C83: =IF(D83="","",C84+B83) -> 19281431 | D83: =IF(E83="","",D84) -> 1093.8668 | E83: =IFERROR(__xludf.DUMMYFUNCTION("FILTER(CUENTAS!AB:AB,A83=CUENTAS!A:A) "),2.3159937584570948E7) -> 23159938 | F83: =(IF(E83<>0,E83-E84-B83,"")) -> 2661.6328 | G83: =IF(E83="","",G84+F83) -> 4133552.5 | H83: =IF(E83="","",1-C83/E83) -> 0.16746619
A84: 46018 | C84: =IF(D84="","",C85+B84) -> 19281431 | D84: =IF(E84="","",D85) -> 1093.8668 | E84: =IFERROR(__xludf.DUMMYFUNCTION("FILTER(CUENTAS!AB:AB,A84=CUENTAS!A:A) "),2.3157275951756876E7) -> 23157276 | F84: =(IF(E84<>0,E84-E85-B84,"")) -> 2661.498 | G84: =IF(E84="","",G85+F84) -> 4130890.9 | H84: =IF(E84="","",1-C84/E84) -> 0.1673705
A85: 46017 | C85: =IF(D85="","",C86+B85) -> 19281431 | D85: =IF(E85="","",D86) -> 1093.8668 | E85: =IFERROR(__xludf.DUMMYFUNCTION("FILTER(CUENTAS!AB:AB,A85=CUENTAS!A:A) "),2.3154614453743994E7) -> 23154614 | F85: =(IF(E85<>0,E85-E86-B85,"")) -> 16321.363 | G85: =IF(E85="","",G86+F85) -> 4128229.4 | H85: =IF(E85="","",1-C85/E85) -> 0.16727479
A86: 46016 | B86: 2750000 | C86: =IF(D86="","",C87+B86) -> 19281431 | D86: =IF(E86="","",D87)+47.275173 +82.731553 -> 1093.8668 | E86: =IFERROR(__xludf.DUMMYFUNCTION("FILTER(CUENTAS!AB:AB,A86=CUENTAS!A:A) "),2.3138293090505328E7) -> 23138293 | F86: =(IF(E86<>0,E86-E87-B86,"")) -> 6981.2285 | G86: =IF(E86="","",G87+F86) -> 4111908 | H86: =IF(E86="","",1-C86/E86) -> 0.1666874
A87: 46015 | C87: =IF(D87="","",C88+B87) -> 16531431 | D87: =IF(E87="","",D88) -> 963.86008 | E87: =IFERROR(__xludf.DUMMYFUNCTION("FILTER(CUENTAS!AB:AB,A87=CUENTAS!A:A) "),2.0381311862013943E7) -> 20381312 | F87: =(IF(E87<>0,E87-E88-B87,"")) -> -5658.9062 | G87: =IF(E87="","",G88+F87) -> 4104926.8 | H87: =IF(E87="","",1-C87/E87) -> 0.18889269
A88: 46014 | C88: =IF(D88="","",C89+B88) -> 16531431 | D88: =IF(E88="","",D89) -> 963.86008 | E88: =IFERROR(__xludf.DUMMYFUNCTION("FILTER(CUENTAS!AB:AB,A88=CUENTAS!A:A) "),2.038697076824289E7) -> 20386971 | F88: =(IF(E88<>0,E88-E89-B88,"")) -> 97820.959 | G88: =IF(E88="","",G89+F88) -> 4110585.7 | H88: =IF(E88="","",1-C88/E88) -> 0.18911783
A89: 46013 | C89: =IF(D89="","",C90+B89) -> 16531431 | D89: =IF(E89="","",D90) -> 963.86008 | E89: =IFERROR(__xludf.DUMMYFUNCTION("FILTER(CUENTAS!AB:AB,A89=CUENTAS!A:A) "),2.0289149809165224E7) -> 20289150 | F89: =(IF(E89<>0,E89-E90-B89,"")) -> 60704.844 | G89: =IF(E89="","",G90+F89) -> 4012764.7 | H89: =IF(E89="","",1-C89/E89) -> 0.18520829
A90: 46012 | C90: =IF(D90="","",C91+B90) -> 16531431 | D90: =IF(E90="","",D91) -> 963.86008 | E90: =IFERROR(__xludf.DUMMYFUNCTION("FILTER(CUENTAS!AB:AB,A90=CUENTAS!A:A) "),2.0228444965557862E7) -> 20228445 | F90: =(IF(E90<>0,E90-E91-B90,"")) -> 12564.728 | G90: =IF(E90="","",G91+F90) -> 3952059.9 | H90: =IF(E90="","",1-C90/E90) -> 0.18276313
A91: 46011 | C91: =IF(D91="","",C92+B91) -> 16531431 | D91: =IF(E91="","",D92) -> 963.86008 | E91: =IFERROR(__xludf.DUMMYFUNCTION("FILTER(CUENTAS!AB:AB,A91=CUENTAS!A:A) "),2.021588023739771E7) -> 20215880 | F91: =(IF(E91<>0,E91-E92-B91,"")) -> 12564.613 | G91: =IF(E91="","",G92+F91) -> 3939495.1 | H91: =IF(E91="","",1-C91/E91) -> 0.18225519
A92: 46010 | C92: =IF(D92="","",C93+B92) -> 16531431 | D92: =IF(E92="","",D93) -> 963.86008 | E92: =IFERROR(__xludf.DUMMYFUNCTION("FILTER(CUENTAS!AB:AB,A92=CUENTAS!A:A) "),2.0203315624661688E7) -> 20203316 | F92: =(IF(E92<>0,E92-E93-B92,"")) -> -109855.5 | G92: =IF(E92="","",G93+F92) -> 3926930.5 | H92: =IF(E92="","",1-C92/E92) -> 0.18174663
A93: 46009 | C93: =IF(D93="","",C94+B93) -> 16531431 | D93: =IF(E93="","",D94) -> 963.86008 | E93: =IFERROR(__xludf.DUMMYFUNCTION("FILTER(CUENTAS!AB:AB,A93=CUENTAS!A:A) "),2.0313171127326705E7) -> 20313171 | F93: =(IF(E93<>0,E93-E94-B93,"")) -> -173915.62 | G93: =IF(E93="","",G94+F93) -> 4036786 | H93: =IF(E93="","",1-C93/E93) -> 0.18617182
A94: 46008 | C94: =IF(D94="","",C95+B94) -> 16531431 | D94: =IF(E94="","",D95) -> 963.86008 | E94: =IFERROR(__xludf.DUMMYFUNCTION("FILTER(CUENTAS!AB:AB,A94=CUENTAS!A:A) "),2.048708674536969E7) -> 20487087 | F94: =(IF(E94<>0,E94-E95-B94,"")) -> 81044.267 | G94: =IF(E94="","",G95+F94) -> 4210701.6 | H94: =IF(E94="","",1-C94/E94) -> 0.19308044
A95: 46007 | C95: =IF(D95="","",C96+B95) -> 16531431 | D95: =IF(E95="","",D96) -> 963.86008 | E95: =IFERROR(__xludf.DUMMYFUNCTION("FILTER(CUENTAS!AB:AB,A95=CUENTAS!A:A) "),2.040604247876757E7) -> 20406042 | F95: =(IF(E95<>0,E95-E96-B95,"")) -> -184715.85 | G95: =IF(E95="","",G96+F95) -> 4129657.4 | H95: =IF(E95="","",1-C95/E95) -> 0.18987569
A96: 46006 | C96: =IF(D96="","",C97+B96) -> 16531431 | D96: =IF(E96="","",D97) -> 963.86008 | E96: =IFERROR(__xludf.DUMMYFUNCTION("FILTER(CUENTAS!AB:AB,A96=CUENTAS!A:A) "),2.0590758327497285E7) -> 20590758 | F96: =(IF(E96<>0,E96-E97-B96,"")) -> -65515.964 | G96: =IF(E96="","",G97+F96) -> 4314373.2 | H96: =IF(E96="","",1-C96/E96) -> 0.19714316
A97: 46005 | C97: =IF(D97="","",C98+B97) -> 16531431 | D97: =IF(E97="","",D98) -> 963.86008 | E97: =IFERROR(__xludf.DUMMYFUNCTION("FILTER(CUENTAS!AB:AB,A97=CUENTAS!A:A) "),2.065627429153577E7) -> 20656274 | F97: =(IF(E97<>0,E97-E98-B97,"")) -> 2563.9207 | G97: =IF(E97="","",G98+F97) -> 4379889.2 | H97: =IF(E97="","",1-C97/E97) -> 0.1996896
A98: 46004 | C98: =IF(D98="","",C99+B98) -> 16531431 | D98: =IF(E98="","",D99) -> 963.86008 | E98: =IFERROR(__xludf.DUMMYFUNCTION("FILTER(CUENTAS!AB:AB,A98=CUENTAS!A:A) "),2.0653710370859966E7) -> 20653710 | F98: =(IF(E98<>0,E98-E99-B98,"")) -> 2563.8054 | G98: =IF(E98="","",G99+F98) -> 4377325.3 | H98: =IF(E98="","",1-C98/E98) -> 0.19959025
A99: 46003 | C99: =IF(D99="","",C100+B99) -> 16531431 | D99: =IF(E99="","",D100) -> 963.86008 | E99: =IFERROR(__xludf.DUMMYFUNCTION("FILTER(CUENTAS!AB:AB,A99=CUENTAS!A:A) "),2.0651146565446828E7) -> 20651147 | F99: =(IF(E99<>0,E99-E100-B99,"")) -> 27643.69 | G99: =IF(E99="","",G100+F99) -> 4374761.5 | H99: =IF(E99="","",1-C99/E99) -> 0.19949088
A100: 46002 | B100: 1500000 | C100: =IF(D100="","",C101+B100) -> 16531431 | D100: =IF(E100="","",D101)+70.104004 -> 963.86008 | E100: =IFERROR(__xludf.DUMMYFUNCTION("FILTER(CUENTAS!AB:AB,A100=CUENTAS!A:A) "),2.0623502875273306E7) -> 20623503 | F100: =(IF(E100<>0,E100-E101-B100,"")) -> 81103.575 | G100: =IF(E100="","",G101+F100) -> 4347117.8 | H100: =IF(E100="","",1-C100/E100) -> 0.19841788
...

Sheet GRAFICO
A1: FECHA | B1: valor unidad | C1: promedio | D1: desviacion de la media | E1: Pronóstico | F1: inferior | G1: EMA-50 | H1: EMA-15 | I1: EMA-5 | J1: superior | K1: variación % diaria | L1: desviación estandar | M1: desviacion anualizada | N1: var historica | O1: var(30d) | P1: MDD
A2: 46098 | B2: =IF(DATOS!E4<>"",DATOS!E4/DATOS!D4,"") | C2: =IF(B2<>"", AVERAGE($B2:B$826),"") | D2: =IF(B2<>"",B2-C2,"") | E2: =IF(B2<>"",TREND($B2:$B$751,$A2:$A$751,A2),"") | F2: =IF(B2<>"",H2 - 2.6*STDEV(B2:B16),"") | G2: =IF(B2<>"",(B2-G3)*2/51+G3,"") | H2: =IF(B2<>"",(B2-H3)*0.125+H3,"") | I2: =IF(B2<>"",(B2-I3)*1/3+I3,"") | J2: =IF(B2<>"",H2 + 2.6*STDEV(B2:B16),"") | K2: =IF(B2<>"",ln(B2)-ln(B3),"") | L2: =IF(B2<>"",SQRT(_xlfn.VAR.S($K2:K$750)),"") | M2: =IF(B2<>"",L2*SQRT(365),"") | N2: =IF(B2<>"",PERCENTILE($K2:K$750,0.05),"") | O2: =IF(B2<>"",PERCENTILE(K2:K31,0.05),"") | P2: =IF(B2<>"",B2/MAX($B2:B$826)-1,"")
A3: 46097 | B3: =IF(DATOS!E5<>"",DATOS!E5/DATOS!D5,"") | C3: =IF(B3<>"", AVERAGE($B3:B$826),"") | D3: =IF(B3<>"",B3-C3,"") | E3: =IF(B3<>"",TREND($B3:$B$751,$A3:$A$751,A3),"") | F3: =IF(B3<>"",H3 - 2.6*STDEV(B3:B17),"") | G3: =IF(B3<>"",(B3-G4)*2/51+G4,"") | H3: =IF(B3<>"",(B3-H4)*0.125+H4,"") | I3: =IF(B3<>"",(B3-I4)*1/3+I4,"") | J3: =IF(B3<>"",H3 + 2.6*STDEV(B3:B17),"") | K3: =IF(B3<>"",ln(B3)-ln(B4),"") | L3: =IF(B3<>"",SQRT(_xlfn.VAR.S($K3:K$750)),"") | M3: =IF(B3<>"",L3*SQRT(365),"") | N3: =IF(B3<>"",PERCENTILE($K3:K$750,0.05),"") | O3: =IF(B3<>"",PERCENTILE(K3:K32,0.05),"") | P3: =IF(B3<>"",B3/MAX($B3:B$826)-1,"")
A4: 46096 | B4: =IF(DATOS!E6<>"",DATOS!E6/DATOS!D6,"") | C4: =IF(B4<>"", AVERAGE($B4:B$826),"") | D4: =IF(B4<>"",B4-C4,"") | E4: =IF(B4<>"",TREND($B4:$B$751,$A4:$A$751,A4),"") | F4: =IF(B4<>"",H4 - 2.6*STDEV(B4:B18),"") | G4: =IF(B4<>"",(B4-G5)*2/51+G5,"") | H4: =IF(B4<>"",(B4-H5)*0.125+H5,"") | I4: =IF(B4<>"",(B4-I5)*1/3+I5,"") | J4: =IF(B4<>"",H4 + 2.6*STDEV(B4:B18),"") | K4: =IF(B4<>"",ln(B4)-ln(B5),"") | L4: =IF(B4<>"",SQRT(_xlfn.VAR.S($K4:K$750)),"") | M4: =IF(B4<>"",L4*SQRT(365),"") | N4: =IF(B4<>"",PERCENTILE($K4:K$750,0.05),"") | O4: =IF(B4<>"",PERCENTILE(K4:K33,0.05),"") | P4: =IF(B4<>"",B4/MAX($B4:B$826)-1,"")
A5: 46095 | B5: =IF(DATOS!E7<>"",DATOS!E7/DATOS!D7,"") | C5: =IF(B5<>"", AVERAGE($B5:B$826),"") | D5: =IF(B5<>"",B5-C5,"") | E5: =IF(B5<>"",TREND($B5:$B$751,$A5:$A$751,A5),"") | F5: =IF(B5<>"",H5 - 2.6*STDEV(B5:B19),"") | G5: =IF(B5<>"",(B5-G6)*2/51+G6,"") | H5: =IF(B5<>"",(B5-H6)*0.125+H6,"") | I5: =IF(B5<>"",(B5-I6)*1/3+I6,"") | J5: =IF(B5<>"",H5 + 2.6*STDEV(B5:B19),"") | K5: =IF(B5<>"",ln(B5)-ln(B6),"") | L5: =IF(B5<>"",SQRT(_xlfn.VAR.S($K5:K$750)),"") | M5: =IF(B5<>"",L5*SQRT(365),"") | N5: =IF(B5<>"",PERCENTILE($K5:K$750,0.05),"") | O5: =IF(B5<>"",PERCENTILE(K5:K34,0.05),"") | P5: =IF(B5<>"",B5/MAX($B5:B$826)-1,"")
A6: 46094 | B6: =IF(DATOS!E8<>"",DATOS!E8/DATOS!D8,"") | C6: =IF(B6<>"", AVERAGE($B6:B$826),"") | D6: =IF(B6<>"",B6-C6,"") | E6: =IF(B6<>"",TREND($B6:$B$751,$A6:$A$751,A6),"") | F6: =IF(B6<>"",H6 - 2.6*STDEV(B6:B20),"") | G6: =IF(B6<>"",(B6-G7)*2/51+G7,"") | H6: =IF(B6<>"",(B6-H7)*0.125+H7,"") | I6: =IF(B6<>"",(B6-I7)*1/3+I7,"") | J6: =IF(B6<>"",H6 + 2.6*STDEV(B6:B20),"") | K6: =IF(B6<>"",ln(B6)-ln(B7),"") | L6: =IF(B6<>"",SQRT(_xlfn.VAR.S($K6:K$750)),"") | M6: =IF(B6<>"",L6*SQRT(365),"") | N6: =IF(B6<>"",PERCENTILE($K6:K$750,0.05),"") | O6: =IF(B6<>"",PERCENTILE(K6:K35,0.05),"") | P6: =IF(B6<>"",B6/MAX($B6:B$826)-1,"")
A7: 46093 | B7: =IF(DATOS!E9<>"",DATOS!E9/DATOS!D9,"") | C7: =IF(B7<>"", AVERAGE($B7:B$826),"") | D7: =IF(B7<>"",B7-C7,"") | E7: =IF(B7<>"",TREND($B7:$B$751,$A7:$A$751,A7),"") | F7: =IF(B7<>"",H7 - 2.6*STDEV(B7:B21),"") | G7: =IF(B7<>"",(B7-G8)*2/51+G8,"") | H7: =IF(B7<>"",(B7-H8)*0.125+H8,"") | I7: =IF(B7<>"",(B7-I8)*1/3+I8,"") | J7: =IF(B7<>"",H7 + 2.6*STDEV(B7:B21),"") | K7: =IF(B7<>"",ln(B7)-ln(B8),"") | L7: =IF(B7<>"",SQRT(_xlfn.VAR.S($K7:K$750)),"") | M7: =IF(B7<>"",L7*SQRT(365),"") | N7: =IF(B7<>"",PERCENTILE($K7:K$750,0.05),"") | O7: =IF(B7<>"",PERCENTILE(K7:K36,0.05),"") | P7: =IF(B7<>"",B7/MAX($B7:B$826)-1,"")
A8: 46092 | B8: =IF(DATOS!E10<>"",DATOS!E10/DATOS!D10,"") | C8: =IF(B8<>"", AVERAGE($B8:B$826),"") | D8: =IF(B8<>"",B8-C8,"") | E8: =IF(B8<>"",TREND($B8:$B$751,$A8:$A$751,A8),"") | F8: =IF(B8<>"",H8 - 2.6*STDEV(B8:B22),"") | G8: =IF(B8<>"",(B8-G9)*2/51+G9,"") | H8: =IF(B8<>"",(B8-H9)*0.125+H9,"") | I8: =IF(B8<>"",(B8-I9)*1/3+I9,"") | J8: =IF(B8<>"",H8 + 2.6*STDEV(B8:B22),"") | K8: =IF(B8<>"",ln(B8)-ln(B9),"") | L8: =IF(B8<>"",SQRT(_xlfn.VAR.S($K8:K$750)),"") | M8: =IF(B8<>"",L8*SQRT(365),"") | N8: =IF(B8<>"",PERCENTILE($K8:K$750,0.05),"") | O8: =IF(B8<>"",PERCENTILE(K8:K37,0.05),"") | P8: =IF(B8<>"",B8/MAX($B8:B$826)-1,"")
A9: 46091 | B9: =IF(DATOS!E11<>"",DATOS!E11/DATOS!D11,"") | C9: =IF(B9<>"", AVERAGE($B9:B$826),"") | D9: =IF(B9<>"",B9-C9,"") | E9: =IF(B9<>"",TREND($B9:$B$751,$A9:$A$751,A9),"") | F9: =IF(B9<>"",H9 - 2.6*STDEV(B9:B23),"") | G9: =IF(B9<>"",(B9-G10)*2/51+G10,"") | H9: =IF(B9<>"",(B9-H10)*0.125+H10,"") | I9: =IF(B9<>"",(B9-I10)*1/3+I10,"") | J9: =IF(B9<>"",H9 + 2.6*STDEV(B9:B23),"") | K9: =IF(B9<>"",ln(B9)-ln(B10),"") | L9: =IF(B9<>"",SQRT(_xlfn.VAR.S($K9:K$750)),"") | M9: =IF(B9<>"",L9*SQRT(365),"") | N9: =IF(B9<>"",PERCENTILE($K9:K$750,0.05),"") | O9: =IF(B9<>"",PERCENTILE(K9:K38,0.05),"") | P9: =IF(B9<>"",B9/MAX($B9:B$826)-1,"")
A10: 46090 | B10: =IF(DATOS!E12<>"",DATOS!E12/DATOS!D12,"") | C10: =IF(B10<>"", AVERAGE($B10:B$826),"") | D10: =IF(B10<>"",B10-C10,"") | E10: =IF(B10<>"",TREND($B10:$B$751,$A10:$A$751,A10),"") | F10: =IF(B10<>"",H10 - 2.6*STDEV(B10:B24),"") | G10: =IF(B10<>"",(B10-G11)*2/51+G11,"") | H10: =IF(B10<>"",(B10-H11)*0.125+H11,"") | I10: =IF(B10<>"",(B10-I11)*1/3+I11,"") | J10: =IF(B10<>"",H10 + 2.6*STDEV(B10:B24),"") | K10: =IF(B10<>"",ln(B10)-ln(B11),"") | L10: =IF(B10<>"",SQRT(_xlfn.VAR.S($K10:K$750)),"") | M10: =IF(B10<>"",L10*SQRT(365),"") | N10: =IF(B10<>"",PERCENTILE($K10:K$750,0.05),"") | O10: =IF(B10<>"",PERCENTILE(K10:K39,0.05),"") | P10: =IF(B10<>"",B10/MAX($B10:B$826)-1,"")
A11: 46089 | B11: =IF(DATOS!E13<>"",DATOS!E13/DATOS!D13,"") -> 20664.604 | C11: =IF(B11<>"", AVERAGE($B11:B$826),"") -> 15221.289 | D11: =IF(B11<>"",B11-C11,"") -> 5443.3155 | E11: =IF(B11<>"",TREND($B11:$B$751,$A11:$A$751,A11),"") -> 21485.614 | F11: =IF(B11<>"",H11 - 2.6*STDEV(B11:B25),"") -> 19692.944 | G11: =IF(B11<>"",(B11-G12)*2/51+G12,"") -> 21326.784 | H11: =IF(B11<>"",(B11-H12)*0.125+H12,"") -> 21029.685 | I11: =IF(B11<>"",(B11-I12)*1/3+I12,"") -> 20714.835 | J11: =IF(B11<>"",H11 + 2.6*STDEV(B11:B25),"") -> 22366.425 | K11: =IF(B11<>"",ln(B11)-ln(B12),"") -> 0.0001392489 | L11: =IF(B11<>"",SQRT(_xlfn.VAR.S($K11:K$750)),"") -> 0.008090859 | M11: =IF(B11<>"",L11*SQRT(365),"") -> 0.15457564 | N11: =IF(B11<>"",PERCENTILE($K11:K$750,0.05),"") -> -0.0091653485 | O11: =IF(B11<>"",PERCENTILE(K11:K40,0.05),"") -> -0.01548073 | P11: =IF(B11<>"",B11/MAX($B11:B$826)-1,"") -> -0.064158292
A12: 46088 | B12: =IF(DATOS!E14<>"",DATOS!E14/DATOS!D14,"") -> 20661.727 | C12: =IF(B12<>"", AVERAGE($B12:B$826),"") -> 15214.61 | D12: =IF(B12<>"",B12-C12,"") -> 5447.1171 | E12: =IF(B12<>"",TREND($B12:$B$751,$A12:$A$751,A12),"") -> 21474.495 | F12: =IF(B12<>"",H12 - 2.6*STDEV(B12:B26),"") -> 19694.659 | G12: =IF(B12<>"",(B12-G13)*2/51+G13,"") -> 21353.812 | H12: =IF(B12<>"",(B12-H13)*0.125+H13,"") -> 21081.839 | I12: =IF(B12<>"",(B12-I13)*1/3+I13,"") -> 20739.95 | J12: =IF(B12<>"",H12 + 2.6*STDEV(B12:B26),"") -> 22469.02 | K12: =IF(B12<>"",ln(B12)-ln(B13),"") -> 0.00019013248 | L12: =IF(B12<>"",SQRT(_xlfn.VAR.S($K12:K$750)),"") -> 0.0080962874 | M12: =IF(B12<>"",L12*SQRT(365),"") -> 0.15467935 | N12: =IF(B12<>"",PERCENTILE($K12:K$750,0.05),"") -> -0.0091740085 | O12: =IF(B12<>"",PERCENTILE(K12:K41,0.05),"") -> -0.01548073 | P12: =IF(B12<>"",B12/MAX($B12:B$826)-1,"") -> -0.064288597
A13: 46087 | B13: =IF(DATOS!E15<>"",DATOS!E15/DATOS!D15,"") -> 20657.799 | C13: =IF(B13<>"", AVERAGE($B13:B$826),"") -> 15207.918 | D13: =IF(B13<>"",B13-C13,"") -> 5449.8808 | E13: =IF(B13<>"",TREND($B13:$B$751,$A13:$A$751,A13),"") -> 21463.329 | F13: =IF(B13<>"",H13 - 2.6*STDEV(B13:B27),"") -> 19744.272 | G13: =IF(B13<>"",(B13-G14)*2/51+G14,"") -> 21382.06 | H13: =IF(B13<>"",(B13-H14)*0.125+H14,"") -> 21141.855 | I13: =IF(B13<>"",(B13-I14)*1/3+I14,"") -> 20779.062 | J13: =IF(B13<>"",H13 + 2.6*STDEV(B13:B27),"") -> 22539.438 | K13: =IF(B13<>"",ln(B13)-ln(B14),"") -> -0.0023373284 | L13: =IF(B13<>"",SQRT(_xlfn.VAR.S($K13:K$750)),"") -> 0.0081017332 | M13: =IF(B13<>"",L13*SQRT(365),"") -> 0.1547834 | N13: =IF(B13<>"",PERCENTILE($K13:K$750,0.05),"") -> -0.0091826685 | O13: =IF(B13<>"",PERCENTILE(K13:K42,0.05),"") -> -0.015499362 | P13: =IF(B13<>"",B13/MAX($B13:B$826)-1,"") -> -0.06446649
... A45: 46055 | B45: =IF(DATOS!E47<>"",DATOS!E47/DATOS!D47,"") -> 21736.825 | C45: =IF(B45<>"", AVERAGE($B45:B$826),"") -> 14951.839 | D45: =IF(B45<>"",B45-C45,"") -> 6784.9857 | E45: =IF(B45<>"",TREND($B45:$B$751,$A45:$A$751,A45),"") -> 20920.569 | F45: =IF(B45<>"",H45 - 2.6*STDEV(B45:B59),"") -> 21383.934 | G45: =IF(B45<>"",(B45-G46)*2/51+G46,"") -> 21395.592 | H45: =IF(B45<>"",(B45-H46)*0.125+H46,"") -> 21775.337 | I45: =IF(B45<>"",(B45-I46)*1/3+I46,"") -> 21859.889 | J45: =IF(B45<>"",H45 + 2.6*STDEV(B45:B59),"") -> 22166.74 | K45: =IF(B45<>"",ln(B45)-ln(B46),"") -> -0.0078328208 | L45: =IF(B45<>"",SQRT(_xlfn.VAR.S($K45:K$750)),"") -> 0.0081248338 | M45: =IF(B45<>"",L45*SQRT(365),"") -> 0.15522473 | N45: =IF(B45<>"",PERCENTILE($K45:K$750,0.05),"") -> -0.0088478878 | O45: =IF(B45<>"",PERCENTILE(K45:K74,0.05),"") -> -0.0073503518 | P45: =IF(B45<>"",B45/MAX($B45:B$826)-1,"") -> -0.015600447
A46: 46054 | B46: =IF(DATOS!E48<>"",DATOS!E48/DATOS!D48,"") -> 21907.754 | C46: =IF(B46<>"", AVERAGE($B46:B$826),"") -> 14943.152 | D46: =IF(B46<>"",B46-C46,"") -> 6964.6025 | E46: =IF(B46<>"",TREND($B46:$B$751,$A46:$A$751,A46),"") -> 20900.464 | F46: =IF(B46<>"",H46 - 2.6*STDEV(B46:B60),"") -> 21261.054 | G46: =IF(B46<>"",(B46-G47)*2/51+G47,"") -> 21381.664 | H46: =IF(B46<>"",(B46-H47)*0.125+H47,"") -> 21780.839 | I46: =IF(B46<>"",(B46-I47)*1/3+I47,"") -> 21921.421 | J46: =IF(B46<>"",H46 + 2.6*STDEV(B46:B60),"") -> 22300.623 | K46: =IF(B46<>"",ln(B46)-ln(B47),"") -> -1.5163803e-06 | L46: =IF(B46<>"",SQRT(_xlfn.VAR.S($K46:K$750)),"") -> 0.0081237156 | M46: =IF(B46<>"",L46*SQRT(365),"") -> 0.15520337 | N46: =IF(B46<>"",PERCENTILE($K46:K$750,0.05),"") -> -0.0088501881 | O46: =IF(B46<>"",PERCENTILE(K46:K75,0.05),"") -> -0.00465092 | P46: =IF(B46<>"",B46/MAX($B46:B$826)-1,"") -> -0.0078595442 | U46: =(B46-H46)/STDEV(B46:B60) -> 0.63484102
A47: 46053 | B47: =IF(DATOS!E49<>"",DATOS!E49/DATOS!D49,"") -> 21907.787 | C47: =IF(B47<>"", AVERAGE($B47:B$826),"") -> 14934.223 | D47: =IF(B47<>"",B47-C47,"") -> 6973.5647 | E47: =IF(B47<>"",TREND($B47:$B$751,$A47:$A$751,A47),"") -> 20879.279 | F47: =IF(B47<>"",H47 - 2.6*STDEV(B47:B61),"") -> 21151.239 | G47: =IF(B47<>"",(B47-G48)*2/51+G48,"") -> 21360.191 | H47: =IF(B47<>"",(B47-H48)*0.125+H48,"") -> 21762.708 | I47: =IF(B47<>"",(B47-I48)*1/3+I48,"") -> 21928.255 | J47: =IF(B47<>"",H47 + 2.6*STDEV(B47:B61),"") -> 22374.177 | K47: =IF(B47<>"",ln(B47)-ln(B48),"") -> -0.00095963409 | L47: =IF(B47<>"",SQRT(_xlfn.VAR.S($K47:K$750)),"") -> 0.0081293944 | M47: =IF(B47<>"",L47*SQRT(365),"") -> 0.15531186 | N47: =IF(B47<>"",PERCENTILE($K47:K$750,0.05),"") -> -0.0088524883 | O47: =IF(B47<>"",PERCENTILE(K47:K76,0.05),"") -> -0.00465092 | P47: =IF(B47<>"",B47/MAX($B47:B$826)-1,"") -> -0.0078580398 | U47: =(B47-H47)/STDEV(B47:B61) -> 0.61688694
A48: 46052 | B48: =IF(DATOS!E50<>"",DATOS!E50/DATOS!D50,"") -> 21928.821 | C48: =IF(B48<>"", AVERAGE($B48:B$826),"") -> 14925.271 | D48: =IF(B48<>"",B48-C48,"") -> 7003.5502 | E48: =IF(B48<>"",TREND($B48:$B$751,$A48:$A$751,A48),"") -> 20857.977 | F48: =IF(B48<>"",H48 - 2.6*STDEV(B48:B62),"") -> 21069.68 | G48: =IF(B48<>"",(B48-G49)*2/51+G49,"") -> 21337.84 | H48: =IF(B48<>"",(B48-H49)*0.125+H49,"") -> 21741.982 | I48: =IF(B48<>"",(B48-I49)*1/3+I49,"") -> 21938.489 | J48: =IF(B48<>"",H48 + 2.6*STDEV(B48:B62),"") -> 22414.284 | K48: =IF(B48<>"",ln(B48)-ln(B49),"") -> 0.001203618 | L48: =IF(B48<>"",SQRT(_xlfn.VAR.S($K48:K$750)),"") -> 0.0081348277 | M48: =IF(B48<>"",L48*SQRT(365),"") -> 0.15541566 | N48: =IF(B48<>"",PERCENTILE($K48:K$750,0.05),"") -> -0.0088547886 | O48: =IF(B48<>"",PERCENTILE(K48:K77,0.05),"") -> -0.00465092 | P48: =IF(B48<>"",B48/MAX($B48:B$826)-1,"") -> -0.0069054895 | U48: =(B48-H48)/STDEV(B48:B62) -> 0.72256402
A49: 46051 | B49: =IF(DATOS!E51<>"",DATOS!E51/DATOS!D51,"") -> 21902.443 | C49: =IF(B49<>"", AVERAGE($B49:B$826),"") -> 14916.269 | D49: =IF(B49<>"",B49-C49,"") -> 6986.1741 | E49: =IF(B49<>"",TREND($B49:$B$751,$A49:$A$751,A49),"") -> 20836.439 | F49: =IF(B49<>"",H49 - 2.6*STDEV(B49:B63),"") -> 20931.053 | G49: =IF(B49<>"",(B49-G50)*2/51+G50,"") -> 21313.718 | H49: =IF(B49<>"",(B49-H50)*0.125+H50,"") -> 21715.291 | I49: =IF(B49<>"",(B49-I50)*1/3+I50,"") -> 21943.323 | J49: =IF(B49<>"",H49 + 2.6*STDEV(B49:B63),"") -> 22499.529 | K49: =IF(B49<>"",ln(B49)-ln(B50),"") -> -0.0081330608 | L49: =IF(B49<>"",SQRT(_xlfn.VAR.S($K49:K$750)),"") -> 0.008140626 | M49: =IF(B49<>"",L49*SQRT(365),"") -> 0.15552644 | N49: =IF(B49<>"",PERCENTILE($K49:K$750,0.05),"") -> -0.0088570888 | O49: =IF(B49<>"",PERCENTILE(K49:K78,0.05),"") -> -0.00465092 | P49: =IF(B49<>"",B49/MAX($B49:B$826)-1,"") -> -0.0081000769 | U49: =(B49-H49)/STDEV(B49:B63) -> 0.62046934
A50: 46050 | B50: =IF(DATOS!E52<>"",DATOS!E52/DATOS!D52,"") -> 22081.303 | C50: =IF(B50<>"", AVERAGE($B50:B$826),"") -> 14907.278 | D50: =IF(B50<>"",B50-C50,"") -> 7174.0256 | E50: =IF(B50<>"",TREND($B50:$B$751,$A50:$A$751,A50),"") -> 20814.932 | F50: =IF(B50<>"",H50 - 2.6*STDEV(B50:B64),"") -> 20799.866 | G50: =IF(B50<>"",(B50-G51)*2/51+G51,"") -> 21289.689 | H50: =IF(B50<>"",(B50-H51)*0.125+H51,"") -> 21688.555 | I50: =IF(B50<>"",(B50-I51)*1/3+I51,"") -> 21963.763 | J50: =IF(B50<>"",H50 + 2.6*STDEV(B50:B64),"") -> 22577.243 | K50: =IF(B50<>"",ln(B50)-ln(B51),"") -> 0.0044136461 | L50: =IF(B50<>"",SQRT(_xlfn.VAR.S($K50:K$750)),"") -> 0.008139023 | M50: =IF(B50<>"",L50*SQRT(365),"") -> 0.15549582 | N50: =IF(B50<>"",PERCENTILE($K50:K$750,0.05),"") -> -0.0088593891 | O50: =IF(B50<>"",PERCENTILE(K50:K79,0.05),"") -> -0.00465092 | P50: =IF(B50<>"",B50/MAX($B50:B$826)-1,"") -> 0 | U50: =(B50-H50)/STDEV(B50:B64) -> 1.1490485
A51: 46049 | B51: =IF(DATOS!E53<>"",DATOS!E53/DATOS!D53,"") -> 21984.059 | C51: =IF(B51<>"", AVERAGE($B51:B$826),"") -> 14898.033 | D51: =IF(B51<>"",B51-C51,"") -> 7086.0262 | E51: =IF(B51<>"",TREND($B51:$B$751,$A51:$A$751,A51),"") -> 20792.286 | F51: =IF(B51<>"",H51 - 2.6*STDEV(B51:B65),"") -> 20713.499 | G51: =IF(B51<>"",(B51-G52)*2/51+G52,"") -> 21257.378 | H51: =IF(B51<>"",(B51-H52)*0.125+H52,"") -> 21632.448 | I51: =IF(B51<>"",(B51-I52)*1/3+I52,"") -> 21904.993 | J51: =IF(B51<>"",H51 + 2.6*STDEV(B51:B65),"") -> 22551.397 | K51: =IF(B51<>"",ln(B51)-ln(B52),"") -> -0.00079058421 | L51: =IF(B51<>"",SQRT(_xlfn.VAR.S($K51:K$750)),"") -> 0.0081438582 | M51: =IF(B51<>"",L51*SQRT(365),"") -> 0.15558819 | N51: =IF(B51<>"",PERCENTILE($K51:K$750,0.05),"") -> -0.0088649687 | O51: =IF(B51<>"",PERCENTILE(K51:K80,0.05),"") -> -0.00465092 | P51: =IF(B51<>"",B51/MAX($B51:B$826)-1,"") -> -0.00079027178 | U51: =(B51-H51)/STDEV(B51:B65) -> 0.99481974
A52: 46048 | B52: =IF(DATOS!E54<>"",DATOS!E54/DATOS!D54,"") -> 22001.446 | C52: =IF(B52<>"", AVERAGE($B52:B$826),"") -> 14888.889 | D52: =IF(B52<>"",B52-C52,"") -> 7112.5565 | E52: =IF(B52<>"",TREND($B52:$B$751,$A52:$A$751,A52),"") -> 20770.072 | F52: =IF(B52<>"",H52 - 2.6*STDEV(B52:B66),"") -> 20657.565 | G52: =IF(B52<>"",(B52-G53)*2/51+G53,"") -> 21227.718 | H52: =IF(B52<>"",(B52-H53)*0.125+H53,"") -> 21582.218 | I52: =IF(B52<>"",(B52-I53)*1/3+I53,"") -> 21865.459 | J52: =IF(B52<>"",H52 + 2.6*STDEV(B52:B66),"") -> 22506.87 | K52: =IF(B52<>"",ln(B52)-ln(B53),"") -> 0.0053496081 | L52: =IF(B52<>"",SQRT(_xlfn.VAR.S($K52:K$750)),"") -> 0.0081493874 | M52: =IF(B52<>"",L52*SQRT(365),"") -> 0.15569383 | N52: =IF(B52<>"",PERCENTILE($K52:K$750,0.05),"") -> -0.0088705484 | O52: =IF(B52<>"",PERCENTILE(K52:K81,0.05),"") -> -0.00465092 | P52: =IF(B52<>"",B52/MAX($B52:B$826)-1,"") -> 0 | U52: =(B52-H52)/STDEV(B52:B66) -> 1.1788147
A53: 46047 | B53: =IF(DATOS!E55<>"",DATOS!E55/DATOS!D55,"") -> 21884.061 | C53: =IF(B53<>"", AVERAGE($B53:B$826),"") -> 14879.7 | D53: =IF(B53<>"",B53-C53,"") -> 7004.361 | E53: =IF(B53<>"",TREND($B53:$B$751,$A53:$A$751,A53),"") -> 20747.636 | F53: =IF(B53<>"",H53 - 2.6*STDEV(B53:B67),"") -> 20627.723 | G53: =IF(B53<>"",(B53-G54)*2/51+G54,"") -> 21196.137 | H53: =IF(B53<>"",(B53-H54)*0.125+H54,"") -> 21522.328 | I53: =IF(B53<>"",(B53-I54)*1/3+I54,"") -> 21797.466 | J53: =IF(B53<>"",H53 + 2.6*STDEV(B53:B67),"") -> 22416.933 | K53: =IF(B53<>"",ln(B53)-ln(B54),"") -> 0.00030677002 | L53: =IF(B53<>"",SQRT(_xlfn.VAR.S($K53:K$750)),"") -> 0.0081536146 | M53: =IF(B53<>"",L53*SQRT(365),"") -> 0.15577459 | N53: =IF(B53<>"",PERCENTILE($K53:K$750,0.05),"") -> -0.008876128 | O53: =IF(B53<>"",PERCENTILE(K53:K82,0.05),"") -> -0.00465092 | P53: =IF(B53<>"",B53/MAX($B53:B$826)-1,"") -> 0 | U53: =(B53-H53)/STDEV(B53:B67) -> 1.0513088
A54: 46046 | B54: =IF(DATOS!E56<>"",DATOS!E56/DATOS!D56,"") -> 21877.349 | C54: =IF(B54<>"", AVERAGE($B54:B$826),"") -> 14870.639 | D54: =IF(B54<>"",B54-C54,"") -> 7006.71 | E54: =IF(B54<>"",TREND($B54:$B$751,$A54:$A$751,A54),"") -> 20725.749 | F54: =IF(B54<>"",H54 - 2.6*STDEV(B54:B68),"") -> 20603.327 | G54: =IF(B54<>"",(B54-G55)*2/51+G55,"") -> 21168.058 | H54: =IF(B54<>"",(B54-H55)*0.125+H55,"") -> 21470.652 | I54: =IF(B54<>"",(B54-I55)*1/3+I55,"") -> 21754.169 | J54: =IF(B54<>"",H54 + 2.6*STDEV(B54:B68),"") -> 22337.976 | K54: =IF(B54<>"",ln(B54)-ln(B55),"") -> 0.0001863339 | L54: =IF(B54<>"",SQRT(_xlfn.VAR.S($K54:K$750)),"") -> 0.00815942 | M54: =IF(B54<>"",L54*SQRT(365),"") -> 0.1558855 | N54: =IF(B54<>"",PERCENTILE($K54:K$750,0.05),"") -> -0.0088817077 | O54: =IF(B54<>"",PERCENTILE(K54:K83,0.05),"") -> -0.00465092 | P54: =IF(B54<>"",B54/MAX($B54:B$826)-1,"") -> 0 | U54: =(B54-H54)/STDEV(B54:B68) -> 1.2191658
A55: 46045 | B55: =IF(DATOS!E57<>"",DATOS!E57/DATOS!D57,"") -> 21873.273 | C55: =IF(B55<>"", AVERAGE($B55:B$826),"") -> 14861.563 | D55: =IF(B55<>"",B55-C55,"") -> 7011.7099 | E55: =IF(B55<>"",TREND($B55:$B$751,$A55:$A$751,A55),"") -> 20703.78 | F55: =IF(B55<>"",H55 - 2.6*STDEV(B55:B69),"") -> 20598.716 | G55: =IF(B55<>"",(B55-G56)*2/51+G56,"") -> 21139.108 | H55: =IF(B55<>"",(B55-H56)*0.125+H56,"") -> 21412.552 | I55: =IF(B55<>"",(B55-I56)*1/3+I56,"") -> 21692.579 | J55: =IF(B55<>"",H55 + 2.6*STDEV(B55:B69),"") -> 22226.388 | K55: =IF(B55<>"",ln(B55)-ln(B56),"") -> 0.0068228554 | L55: =IF(B55<>"",SQRT(_xlfn.VAR.S($K55:K$750)),"") -> 0.0081652205 | M55: =IF(B55<>"",L55*SQRT(365),"") -> 0.15599632 | N55: =IF(B55<>"",PERCENTILE($K55:K$750,0.05),"") -> -0.0088872873 | O55: =IF(B55<>"",PERCENTILE(K55:K84,0.05),"") -> -0.00465092 | P55: =IF(B55<>"",B55/MAX($B55:B$826)-1,"") -> 0 | U55: =(B55-H55)/STDEV(B55:B69) -> 1.4718853
A56: 46044 | B56: =IF(DATOS!E58<>"",DATOS!E58/DATOS!D58,"") -> 21724.542 | C56: =IF(B56<>"", AVERAGE($B56:B$826),"") -> 14852.468 | D56: =IF(B56<>"",B56-C56,"") -> 6872.074 | E56: =IF(B56<>"",TREND($B56:$B$751,$A56:$A$751,A56),"") -> 20681.713 | F56: =IF(B56<>"",H56 - 2.6*STDEV(B56:B70),"") -> 20614.105 | G56: =IF(B56<>"",(B56-G57)*2/51+G57,"") -> 21109.142 | H56: =IF(B56<>"",(B56-H57)*0.125+H57,"") -> 21346.735 | I56: =IF(B56<>"",(B56-I57)*1/3+I57,"") -> 21602.232 | J56: =IF(B56<>"",H56 + 2.6*STDEV(B56:B70),"") -> 22079.365 | K56: =IF(B56<>"",ln(B56)-ln(B57),"") -> -0.0017084441 | L56: =IF(B56<>"",SQRT(_xlfn.VAR.S($K56:K$750)),"") -> 0.0081681702 | M56: =IF(B56<>"",L56*SQRT(365),"") -> 0.15605267 | N56: =IF(B56<>"",PERCENTILE($K56:K$750,0.05),"") -> -0.0088928669 | O56: =IF(B56<>"",PERCENTILE(K56:K85,0.05),"") -> -0.00465092 | P56: =IF(B56<>"",B56/MAX($B56:B$826)-1,"") -> -0.0017069855 | U56: =(B56-H56)/STDEV(B56:B70) -> 1.340785
A57: 46043 | B57: =IF(DATOS!E59<>"",DATOS!E59/DATOS!D59,"") -> 21761.689 | C57: =IF(B57<>"", AVERAGE($B57:B$826),"") -> 14843.544 | D57: =IF(B57<>"",B57-C57,"") -> 6918.1456 | E57: =IF(B57<>"",TREND($B57:$B$751,$A57:$A$751,A57),"") -> 20660.379 | F57: =IF(B57<>"",H57 - 2.6*STDEV(B57:B71),"") -> 20620.11 | G57: =IF(B57<>"",(B57-G58)*2/51+G58,"") -> 21084.023 | H57: =IF(B57<>"",(B57-H58)*0.125+H58,"") -> 21292.762 | I57: =IF(B57<>"",(B57-I58)*1/3+I58,"") -> 21541.076 | J57: =IF(B57<>"",H57 + 2.6*STDEV(B57:B71),"") -> 21965.415 | K57: =IF(B57<>"",ln(B57)-ln(B58),"") -> 0.0060034515 | L57: =IF(B57<>"",SQRT(_xlfn.VAR.S($K57:K$750)),"") -> 0.008173387 | M57: =IF(B57<>"",L57*SQRT(365),"") -> 0.15615234 | N57: =IF(B57<>"",PERCENTILE($K57:K$750,0.05),"") -> -0.0088984466 | O57: =IF(B57<>"",PERCENTILE(K57:K86,0.05),"") -> -0.00465092 | P57: =IF(B57<>"",B57/MAX($B57:B$826)-1,"") -> 0 | U57: =(B57-H57)/STDEV(B57:B71) -> 1.8125417
... A94: 46006 | B94: =IF(DATOS!E96<>"",DATOS!E96/DATOS!D96,"") -> 21362.808 | C94: =IF(B94<>"", AVERAGE($B94:B$826),"") -> 14527.831 | D94: =IF(B94<>"",B94-C94,"") -> 6834.9777 | E94: =IF(B94<>"",TREND($B94:$B$751,$A94:$A$751,A94),"") -> 19926.974 | F94: =IF(B94<>"",H94 - 2.6*STDEV(B94:B108),"") -> 20898.462 | G94: =IF(B94<>"",(B94-G95)*2/51+G95,"") -> 20874.37 | H94: =IF(B94<>"",(B94-H95)*0.125+H95,"") -> 21258.11 | I94: =IF(B94<>"",(B94-I95)*1/3+I95,"") -> 21374.336 | J94: =IF(B94<>"",H94 + 2.6*STDEV(B94:B108),"") -> 21617.758 | K94: =IF(B94<>"",ln(B94)-ln(B95),"") -> -0.0031767628 | L94: =IF(B94<>"",SQRT(_xlfn.VAR.S($K94:K$750)),"") -> 0.0082612966 | M94: =IF(B94<>"",L94*SQRT(365),"") -> 0.15783185 | N94: =IF(B94<>"",PERCENTILE($K94:K$750,0.05),"") -> -0.0088817077 | O94: =IF(B94<>"",PERCENTILE(K94:K123,0.05),"") -> -0.0098495926 | P94: =IF(B94<>"",B94/MAX($B94:B$826)-1,"") -> -0.0053365244 | U94: =(B94-H94)/STDEV(B94:B108) -> 0.75689398
A95: 46005 | B95: =DATOS!E97/DATOS!D97 -> 21430.781 | C95: =IF(B95<>"", AVERAGE($B95:B$826),"") -> 14518.493 | D95: =IF(B95<>"",B95-C95,"") -> 6912.2876 | E95: =IF(B95<>"",TREND($B95:$B$751,$A95:$A$751,A95),"") -> 19903.299 | F95: =IF(B95<>"",H95 - 2.6*STDEV(B95:B109),"") -> 20851.863 | G95: =IF(B95<>"",(B95-G96)*2/51+G96,"") -> 20854.433 | H95: =IF(B95<>"",(B95-H96)*0.125+H96,"") -> 21243.153 | I95: =IF(B95<>"",(B95-I96)*1/3+I96,"") -> 21380.1 | J95: =IF(B95<>"",H95 + 2.6*STDEV(B95:B109),"") -> 21634.444 | K95: =IF(B95<>"",ln(B95)-ln(B96),"") -> 0.0001241308 | L95: =IF(B95<>"",SQRT(_xlfn.VAR.S($K95:K$750)),"") -> 0.0082659176 | M95: =IF(B95<>"",L95*SQRT(365),"") -> 0.15792013 | N95: =IF(B95<>"",PERCENTILE($K95:K$750,0.05),"") -> -0.0088872873 | O95: =IF(B95<>"",PERCENTILE(K95:K124,0.05),"") -> -0.0098495926 | P95: =-IF(B95<>"",B95/MAX($B95:B$826)-1,"") -> 0.0021716902 | U95: =(B95-H95)/STDEV(B95:B109) -> 1.2467265
A96: 46004 | B96: =DATOS!E98/DATOS!D98 -> 21428.121 | C96: =AVERAGE($B96:B$826) -> 14509.037 | D96: =B96-C96 -> 6919.0834 | E96: =TREND($B96:$B$751,$A96:$A$751,A96) -> 19879.072 | F96: =IF(B96<>"",H96 - 2.6*STDEV(B96:B110),"") -> 20822.101 | G96: =(B96-G97)*2/51+G97 -> 20830.909 | H96: =(B96-H97)*0.125+H97 -> 21216.349 | I96: =(B96-I97)*1/3+I97 -> 21354.759 | J96: =IF(B96<>"",H96 + 2.6*STDEV(B96:B110),"") -> 21610.598 | K96: =ln(B96)-ln(B97) -> 0.00012414063 | L96: =SQRT(_xlfn.VAR.S($K96:K$750)) -> 0.0082721473 | M96: =L96*SQRT(365) -> 0.15803915 | N96: =PERCENTILE($K96:K$750,0.05) -> -0.0088928669 | O96: =PERCENTILE(K96:K125, 0.05) -> -0.0098495926 | P96: =-IF(B96<>"",B96/MAX($B96:B$826)-1,"") -> 0.0022955437 | U96: =(B96-H96)/STDEV(B96:B110) -> 1.3965971
A97: 46003 | B97: =DATOS!E99/DATOS!D99 -> 21425.461 | C97: =AVERAGE($B97:B$826) -> 14499.559 | D97: =B97-C97 -> 6925.9017 | E97: =TREND($B97:$B$751,$A97:$A$751,A97) -> 19854.72 | F97: =IF(B97<>"",H97 - 2.6*STDEV(B97:B111),"") -> 20803.853 | G97: =(B97-G98)*2/51+G98 -> 20806.533 | H97: =(B97-H98)*0.125+H98 -> 21186.096 | I97: =(B97-I98)*1/3+I98 -> 21318.079 | J97: =IF(B97<>"",H97 + 2.6*STDEV(B97:B111),"") -> 21568.34 | K97: =ln(B97)-ln(B98) -> 0.0013394999 | L97: =SQRT(_xlfn.VAR.S($K97:K$750)) -> 0.0082783912 | M97: =L97*SQRT(365) -> 0.15815844 | N97: =PERCENTILE($K97:K$750,0.05) -> -0.0088984466 | O97: =PERCENTILE(K97:K126, 0.05) -> -0.0098495926 | P97: =-IF(B97<>"",B97/MAX($B97:B$826)-1,"") -> 0.0024193917 | U97: =(B97-H97)/STDEV(B97:B111) -> 1.6281463
A98: 46002 | B98: =DATOS!E100/DATOS!D100 -> 21396.781 | C98: =AVERAGE($B98:B$826) -> 14490.059 | D98: =B98-C98 -> 6906.7221 | E98: =TREND($B98:$B$751,$A98:$A$751,A98) -> 19830.242 | F98: =IF(B98<>"",H98 - 2.6*STDEV(B98:B112),"") -> 20757.821 | G98: =(B98-G99)*2/51+G99 -> 20781.271 | H98: =(B98-H99)*0.125+H99 -> 21151.901 | I98: =(B98-I99)*1/3+I99 -> 21264.388 | J98: =IF(B98<>"",H98 + 2.6*STDEV(B98:B112),"") -> 21545.981 | K98: =ln(B98)-ln(B99) -> 0.0042500602 | L98: =SQRT(_xlfn.VAR.S($K98:K$750)) -> 0.0082847318 | M98: =L98*SQRT(365) -> 0.15827958 | N98: =PERCENTILE($K98:K$750,0.05) -> -0.0089040262 | O98: =PERCENTILE(K98:K127, 0.05) -> -0.0098495926 | P98: =-IF(B98<>"",B98/MAX($B98:B$826)-1,"") -> 0.0037547562 | U98: =(B98-H98)/STDEV(B98:B112) -> 1.6156283
A99: 46001 | B99: =DATOS!E101/DATOS!D101 -> 21306.036 | C99: =AVERAGE($B99:B$826) -> 14480.571 | D99: =B99-C99 -> 6825.4647 | E99: =TREND($B99:$B$751,$A99:$A$751,A99) -> 19805.798 | F99: =IF(B99<>"",H99 - 2.6*STDEV(B99:B113),"") -> 20728.893 | G99: =(B99-G100)*2/51+G100 -> 20756.148 | H99: =(B99-H100)*0.125+H100 -> 21116.919 | I99: =(B99-I100)*1/3+I100 -> 21198.191 | J99: =IF(B99<>"",H99 + 2.6*STDEV(B99:B113),"") -> 21504.944 | K99: =ln(B99)-ln(B100) -> 0.0034573974 | L99: =SQRT(_xlfn.VAR.S($K99:K$750)) -> 0.0082901707 | M99: =L99*SQRT(365) -> 0.15838349 | N99: =PERCENTILE($K99:K$750,0.05) -> -0.0089096059 | O99: =PERCENTILE(K99:K128, 0.05) -> -0.0098495926 | P99: =-IF(B99<>"",B99/MAX($B99:B$826)-1,"") -> 0.0079798737 | U99: =(B99-H99)/STDEV(B99:B113) -> 1.2671997
A100: 46000 | B100: =DATOS!E102/DATOS!D102 -> 21232.5 | C100: =AVERAGE($B100:B$826) -> 14471.183 | D100: =B100-C100 -> 6761.317 | E100: =TREND($B100:$B$751,$A100:$A$751,A100) -> 19781.767 | F100: =IF(B100<>"",H100 - 2.6*STDEV(B100:B114),"") -> 20691.273 | G100: =(B100-G101)*2/51+G101 -> 20733.703 | H100: =(B100-H101)*0.125+H101 -> 21089.902 | I100: =(B100-I101)*1/3+I101 -> 21144.268 | J100: =IF(B100<>"",H100 + 2.6*STDEV(B100:B114),"") -> 21488.53 | K100: =ln(B100)-ln(B101) -> 0.0066011559 | L100: =SQRT(_xlfn.VAR.S($K100:K$750)) -> 0.0082960263 | M100: =L100*SQRT(365) -> 0.15849536 | N100: =PERCENTILE($K100:K$750,0.05) -> -0.0089151855 | O100: =PERCENTILE(K100:K129, 0.05) -> -0.0098495926 | P100: =-IF(B100<>"",B100/MAX($B100:B$826)-1,"") -> 0.011403759 | U100: =(B100-H100)/STDEV(B100:B114) -> 0.93007757
A101: 45999 | B101: =DATOS!E103/DATOS!D103 -> 21092.802 | C101: =AVERAGE($B101:B$826) -> 14461.87 | D101: =B101-C101 -> 6630.9326 | E101: =TREND($B101:$B$751,$A101:$A$751,A101) -> 19758.048 | F101: =IF(B101<>"",H101 - 2.6*STDEV(B101:B115),"") -> 20567.357 | G101: =(B101-G102)*2/51+G102 -> 20713.344 | H101: =(B101-H102)*0.125+H102 -> 21069.531 | I101: =(B101-I102)*1/3+I102 -> 21100.153 | J101: =IF(B101<>"",H101 + 2.6*STDEV(B101:B115),"") -> 21571.704 | K101: =ln(B101)-ln(B102) -> 0.00027456464 | L101: =SQRT(_xlfn.VAR.S($K101:K$750)) -> 0.0082995917 | M101: =L101*SQRT(365) -> 0.15856348 | N101: =PERCENTILE($K101:K$750,0.05) -> -0.0089207652 | O101: =PERCENTILE(K101:K130, 0.05) -> -0.0098495926 | P101: =-IF(B101<>"",B101/MAX($B101:B$826)-1,"") -> 0.017908145 | U101: =(B101-H101)/STDEV(B101:B115) -> 0.12049016
A102: 45998 | B102: =DATOS!E104/DATOS!D104 -> 21087.012 | C102: =AVERAGE($B102:B$826) -> 14452.724 | D102: =B102-C102 -> 6634.2882 | E102: =TREND($B102:$B$751,$A102:$A$751,A102) -> 19735.05 | F102: =IF(B102<>"",H102 - 2.6*STDEV(B102:B116),"") -> 20566.275 | G102: =(B102-G103)*2/51+G103 -> 20697.856 | H102: =(B102-H103)*0.125+H103 -> 21066.206 | I102: =(B102-I103)*1/3+I103 -> 21103.828 | J102: =IF(B102<>"",H102 + 2.6*STDEV(B102:B116),"") -> 21566.137 | K102: =ln(B102)-ln(B103) -> 0.00027463394 | L102: =SQRT(_xlfn.VAR.S($K102:K$750)) -> 0.0083059327 | M102: =L102*SQRT(365) -> 0.15868462 | N102: =PERCENTILE($K102:K$750,0.05) -> -0.0089263448 | O102: =PERCENTILE(K102:K131, 0.05) -> -0.0098495926 | P102: =-IF(B102<>"",B102/MAX($B102:B$826)-1,"") -> 0.018177756 | U102: =(B102-H102)/STDEV(B102:B116) -> 0.10820589
A103: 45997 | B103: =DATOS!E105/DATOS!D105 -> 21081.221 | C103: =AVERAGE($B103:B$826) -> 14443.56 | D103: =B103-C103 -> 6637.6612 | E103: =TREND($B103:$B$751,$A103:$A$751,A103) -> 19711.952 | F103: =IF(B103<>"",H103 - 2.6*STDEV(B103:B117),"") -> 20566.997 | G103: =(B103-G104)*2/51+G104 -> 20681.972 | H103: =(B103-H104)*0.125+H104 -> 21063.234 | I103: =(B103-I104)*1/3+I104 -> 21112.236 | J103: =IF(B103<>"",H103 + 2.6*STDEV(B103:B117),"") -> 21559.47 | K103: =ln(B103)-ln(B104) -> 0.00027470327 | L103: =SQRT(_xlfn.VAR.S($K103:K$750)) -> 0.0083122883 | M103: =L103*SQRT(365) -> 0.15880604 | N103: =PERCENTILE($K103:K$750,0.05) -> -0.0089319244 | O103: =PERCENTILE(K103:K132, 0.05) -> -0.0098495926 | P103: =-IF(B103<>"",B103/MAX($B103:B$826)-1,"") -> 0.018447361 | U103: =(B103-H103)/STDEV(B103:B117) -> 0.094245976
A104: 45996 | B104: =DATOS!E106/DATOS!D106 -> 21075.431 | C104: =AVERAGE($B104:B$826) -> 14434.38 | D104: =B104-C104 -> 6641.0516 | E104: =TREND($B104:$B$751,$A104:$A$751,A104) -> 19688.753 | F104: =IF(B104<>"",H104 - 2.6*STDEV(B104:B118),"") -> 20569.164 | G104: =(B104-G105)*2/51+G105 -> 20665.676 | H104: =(B104-H105)*0.125+H105 -> 21060.664 | I104: =(B104-I105)*1/3+I105 -> 21127.743 | J104: =IF(B104<>"",H104 + 2.6*STDEV(B104:B118),"") -> 21552.164 | K104: =ln(B104)-ln(B105) -> -0.0063202494 | L104: =SQRT(_xlfn.VAR.S($K104:K$750)) -> 0.0083186585 | M104: =L104*SQRT(365) -> 0.15892775 | N104: =PERCENTILE($K104:K$750,0.05) -> -0.0089375041 | O104: =PERCENTILE(K104:K133, 0.05) -> -0.0098495926 | P104: =-IF(B104<>"",B104/MAX($B104:B$826)-1,"") -> 0.018716959 | U104: =(B104-H104)/STDEV(B104:B118) -> 0.078117407
A105: 45995 | B105: =DATOS!E107/DATOS!D107 -> 21209.055 | C105: =AVERAGE($B105:B$826) -> 14425.181 | D105: =B105-C105 -> 6783.8735 | E105: =TREND($B105:$B$751,$A105:$A$751,A105) -> 19665.453 | F105: =IF(B105<>"",H105 - 2.6*STDEV(B105:B119),"") -> 20572.621 | G105: =(B105-G106)*2/51+G106 -> 20648.952 | H105: =(B105-H106)*0.125+H106 -> 21058.554 | I105: =(B105-I106)*1/3+I106 -> 21153.899 | J105: =IF(B105<>"",H105 + 2.6*STDEV(B105:B119),"") -> 21544.488 | K105: =ln(B105)-ln(B106) -> 0.00023026742 | L105: =SQRT(_xlfn.VAR.S($K105:K$750)) -> 0.0083199889 | M105: =L105*SQRT(365) -> 0.15895316 | N105: =PERCENTILE($K105:K$750,0.05) -> -0.0089430837 | O105: =PERCENTILE(K105:K134, 0.05) -> -0.0097339162 | P105: =-IF(B105<>"",B105/MAX($B105:B$826)-1,"") -> 0.012495365 | U105: =(B105-H105)/STDEV(B105:B119) -> 0.80525759
A106: 45994 | B106: =DATOS!E108/DATOS!D108 -> 21204.172 | C106: =AVERAGE($B106:B$826) -> 14415.772 | D106: =B106-C106 -> 6788.3993 | E106: =TREND($B106:$B$751,$A106:$A$751,A106) -> 19641.189 | F106: =IF(B106<>"",H106 - 2.6*STDEV(B106:B120),"") -> 20544.677 | G106: =(B106-G107)*2/51+G107 -> 20626.09 | H106: =(B106-H107)*0.125+H107 -> 21037.054 | I106: =(B106-I107)*1/3+I107 -> 21126.32 | J106: =IF(B106<>"",H106 + 2.6*STDEV(B106:B120),"") -> 21529.432 | K106: =ln(B106)-ln(B107) -> -0.0036003184 | L106: =SQRT(_xlfn.VAR.S($K106:K$750)) -> 0.0083263759 | M106: =L106*SQRT(365) -> 0.15907519 | N106: =PERCENTILE($K106:K$750,0.05) -> -0.0089486634 | O106: =PERCENTILE(K106:K135, 0.05) -> -0.0097339162 | P106: =-IF(B106<>"",B106/MAX($B106:B$826)-1,"") -> 0.012722729 | U106: =(B106-H106)/STDEV(B106:B120) -> 0.88246406
A107: 45993 | B107: =DATOS!E109/DATOS!D109 -> 21280.651 | C107: =AVERAGE($B107:B$826) -> 14406.344 | D107: =B107-C107 -> 6874.307 | E107: =TREND($B107:$B$751,$A107:$A$751,A107) -> 19616.811 | F107: =IF(B107<>"",H107 - 2.6*STDEV(B107:B121),"") -> 20474.273 | G107: =(B107-G108)*2/51+G108 -> 20602.495 | H107: =(B107-H108)*0.125+H108 -> 21013.18 | I107: =(B107-I108)*1/3+I108 -> 21087.394 | J107: =IF(B107<>"",H107 + 2.6*STDEV(B107:B121),"") -> 21552.088 | K107: =ln(B107)-ln(B108) -> 0.0081302169 | L107: =SQRT(_xlfn.VAR.S($K107:K$750)) -> 0.0083307848 | M107: =L107*SQRT(365) -> 0.15915942 | N107: =PERCENTILE($K107:K$750,0.05) -> -0.008954243 | O107: =PERCENTILE(K107:K136, 0.05) -> -0.0097339162 | P107: =-IF(B107<>"",B107/MAX($B107:B$826)-1,"") -> 0.0091618105 | U107: =(B107-H107)/STDEV(B107:B121) -> 1.2904327
... A375: 45725 | B375: =DATOS!E377/DATOS!D377 -> 13964.3 | C375: =AVERAGE($B375:B$826) -> 12528.95 | D375: =B375-C375 -> 1435.3498 | E375: =TREND($B375:$B$751,$A375:$A$751,A375) -> 15264.981 | F375: =IF(B375<>"",H375 - 2.6*STDEV(B375:B389),"") -> 13753.416 | G375: =(B375-G376)*2/51+G376 -> 14516.808 | H375: =(B375-H376)*0.125+H376 -> 14133.14 | I375: =(B375-I376)*1/3+I376 -> 13947.276 | J375: =IF(B375<>"",H375 + 2.6*STDEV(B375:B389),"") -> 14512.864 | K375: =ln(B375)-ln(B376) -> 0.00023107948 | L375: =SQRT(_xlfn.VAR.S($K375:K$750)) -> 0.0071524998 | M375: =L375*SQRT(365) -> 0.13664832 | N375: =PERCENTILE($K375:K$750,0.05) -> -0.0076062006 | O375: =PERCENTILE(K375:K404, 0.05) -> -0.023620127 | P375: =-IF(B375<>"",B375/MAX($B375:B$826)-1,"") -> 0.11253505 | U375: =(B375-H375)/STDEV(B375:B389) -> -1.1560602
A376: 45724 | B376: 13961.073 | C376: =AVERAGE($B376:B$826) -> 12525.768 | D376: =B376-C376 -> 1435.306 | E376: =TREND($B376:$B$751,$A376:$A$751,A376) -> 15266.731 | F376: =IF(B376<>"",H376 - 2.6*STDEV(B376:B390),"") -> 13777.3 | G376: =(B376-G377)*2/51+G377 -> 14539.359 | H376: =(B376-H377)*0.125+H377 -> 14157.26 | I376: =(B376-I377)*1/3+I377 -> 13938.764 | J376: =IF(B376<>"",H376 + 2.6*STDEV(B376:B390),"") -> 14537.22 | K376: =ln(B376)-ln(B377) -> 0.0056057752 | L376: =SQRT(_xlfn.VAR.S($K376:K$750)) -> 0.0071620008 | M376: =L376*SQRT(365) -> 0.13682983 | N376: =PERCENTILE($K376:K$750,0.05) -> -0.0076404982 | O376: =PERCENTILE(K376:K405, 0.05) -> -0.023620127 | P376: =-IF(B376<>"",B376/MAX($B376:B$826)-1,"") -> 0.1127401 | U376: =(B376-H376)/STDEV(B376:B390) -> -1.3424704
A377: 45723 | B377: 13883.03 | C377: =AVERAGE($B377:B$826) -> 12522.578 | D377: =B377-C377 -> 1360.4518 | E377: =TREND($B377:$B$751,$A377:$A$751,A377) -> 15268.516 | F377: =IF(B377<>"",H377 - 2.6*STDEV(B377:B391),"") -> 13805.709 | G377: =(B377-G378)*2/51+G378 -> 14562.963 | H377: =(B377-H378)*0.125+H378 -> 14185.286 | I377: =(B377-I378)*1/3+I378 -> 13927.609 | J377: =IF(B377<>"",H377 + 2.6*STDEV(B377:B391),"") -> 14564.864 | K377: =ln(B377)-ln(B378) -> -0.0011379992 | L377: =SQRT(_xlfn.VAR.S($K377:K$750)) -> 0.0071672176 | M377: =L377*SQRT(365) -> 0.1369295 | N377: =PERCENTILE($K377:K$750,0.05) -> -0.0076747958 | O377: =PERCENTILE(K377:K406, 0.05) -> -0.023620127 | P377: =-IF(B377<>"",B377/MAX($B377:B$826)-1,"") -> 0.11769997 | U377: =(B377-H377)/STDEV(B377:B391) -> -2.0703765
A378: 45722 | B378: 13898.838 | C378: =AVERAGE($B378:B$826) -> 12519.548 | D378: =B378-C378 -> 1379.2897 | E378: =TREND($B378:$B$751,$A378:$A$751,A378) -> 15271.135 | F378: =IF(B378<>"",H378 - 2.6*STDEV(B378:B392),"") -> 13346.359 | G378: =(B378-G379)*2/51+G379 -> 14590.715 | H378: =(B378-H379)*0.125+H379 -> 14228.466 | I378: =(B378-I379)*1/3+I379 -> 13949.899 | J378: =IF(B378<>"",H378 + 2.6*STDEV(B378:B392),"") -> 15110.573 | K378: =ln(B378)-ln(B379) -> -0.0070064305 | L378: =SQRT(_xlfn.VAR.S($K378:K$750)) -> 0.0071761674 | M378: =L378*SQRT(365) -> 0.13710049 | N378: =PERCENTILE($K378:K$750,0.05) -> -0.0077090933 | O378: =PERCENTILE(K378:K407, 0.05) -> -0.023620127 | P378: =-IF(B378<>"",B378/MAX($B378:B$826)-1,"") -> 0.11669534 | U378: =(B378-H378)/STDEV(B378:B392) -> -0.9715762
A379: 45721 | B379: 13996.561 | C379: =AVERAGE($B379:B$826) -> 12516.469 | D379: =B379-C379 -> 1480.0916 | E379: =TREND($B379:$B$751,$A379:$A$751,A379) -> 15273.594 | F379: =IF(B379<>"",H379 - 2.6*STDEV(B379:B393),"") -> 13121.617 | G379: =(B379-G380)*2/51+G380 -> 14618.955 | H379: =(B379-H380)*0.125+H380 -> 14275.556 | I379: =(B379-I380)*1/3+I380 -> 13975.429 | J379: =IF(B379<>"",H379 + 2.6*STDEV(B379:B393),"") -> 15429.494 | K379: =ln(B379)-ln(B380) -> 0.0088582091 | L379: =SQRT(_xlfn.VAR.S($K379:K$750)) -> 0.0071744631 | M379: =L379*SQRT(365) -> 0.13706793 | N379: =PERCENTILE($K379:K$750,0.05) -> -0.0077433909 | O379: =PERCENTILE(K379:K408, 0.05) -> -0.023620127 | P379: =-IF(B379<>"",B379/MAX($B379:B$826)-1,"") -> 0.1104848 | U379: =(B379-H379)/STDEV(B379:B393) -> -0.62861826
A380: 45720 | B380: 13873.124 | C380: =AVERAGE($B380:B$826) -> 12513.158 | D380: =B380-C380 -> 1359.9658 | E380: =TREND($B380:$B$751,$A380:$A$751,A380) -> 15275.008 | F380: =IF(B380<>"",H380 - 2.6*STDEV(B380:B394),"") -> 12961.349 | G380: =(B380-G381)*2/51+G381 -> 14644.359 | H380: =(B380-H381)*0.125+H381 -> 14315.412 | I380: =(B380-I381)*1/3+I381 -> 13964.864 | J380: =IF(B380<>"",H380 + 2.6*STDEV(B380:B394),"") -> 15669.476 | K380: =ln(B380)-ln(B381) -> 0.0018606018 | L380: =SQRT(_xlfn.VAR.S($K380:K$750)) -> 0.0071718538 | M380: =L380*SQRT(365) -> 0.13701807 | N380: =PERCENTILE($K380:K$750,0.05) -> -0.0077776885 | O380: =PERCENTILE(K380:K409, 0.05) -> -0.023620127 | P380: =-IF(B380<>"",B380/MAX($B380:B$826)-1,"") -> 0.11832951 | U380: =(B380-H380)/STDEV(B380:B394) -> -0.84925825
A381: 45719 | B381: 13847.336 | C381: =AVERAGE($B381:B$826) -> 12510.109 | D381: =B381-C381 -> 1337.2267 | E381: =TREND($B381:$B$751,$A381:$A$751,A381) -> 15277.75 | F381: =IF(B381<>"",H381 - 2.6*STDEV(B381:B395),"") -> 12762.787 | G381: =(B381-G382)*2/51+G382 -> 14675.838 | H381: =(B381-H382)*0.125+H382 -> 14378.596 | I381: =(B381-I382)*1/3+I382 -> 14010.734 | J381: =IF(B381<>"",H381 + 2.6*STDEV(B381:B395),"") -> 15994.405 | K381: =ln(B381)-ln(B382) -> -0.011830977 | L381: =SQRT(_xlfn.VAR.S($K381:K$750)) -> 0.0071813381 | M381: =L381*SQRT(365) -> 0.13719927 | N381: =PERCENTILE($K381:K$750,0.05) -> -0.007811986 | O381: =PERCENTILE(K381:K410, 0.05) -> -0.023620127 | P381: =-IF(B381<>"",B381/MAX($B381:B$826)-1,"") -> 0.11996842 | U381: =(B381-H381)/STDEV(B381:B395) -> -0.85485225
A382: 45718 | B382: 14012.136 | C382: =AVERAGE($B382:B$826) -> 12507.104 | D382: =B382-C382 -> 1505.0322 | E382: =TREND($B382:$B$751,$A382:$A$751,A382) -> 15280.779 | F382: =IF(B382<>"",H382 - 2.6*STDEV(B382:B396),"") -> 12685.851 | G382: =(B382-G383)*2/51+G383 -> 14709.654 | H382: =(B382-H383)*0.125+H383 -> 14454.491 | I382: =(B382-I383)*1/3+I383 -> 14092.433 | J382: =IF(B382<>"",H382 + 2.6*STDEV(B382:B396),"") -> 16223.131 | K382: =ln(B382)-ln(B383) -> 0.00021193761 | L382: =SQRT(_xlfn.VAR.S($K382:K$750)) -> 0.0071609812 | M382: =L382*SQRT(365) -> 0.13681035 | N382: =PERCENTILE($K382:K$750,0.05) -> -0.0073636375 | O382: =PERCENTILE(K382:K411, 0.05) -> -0.023620127 | P382: =-IF(B382<>"",B382/MAX($B382:B$826)-1,"") -> 0.10949496 | U382: =(B382-H382)/STDEV(B382:B396) -> -0.65028609
A383: 45717 | B383: 14009.167 | C383: =AVERAGE($B383:B$826) -> 12503.714 | D383: =B383-C383 -> 1505.4525 | E383: =TREND($B383:$B$751,$A383:$A$751,A383) -> 15282.035 | F383: =IF(B383<>"",H383 - 2.6*STDEV(B383:B397),"") -> 12635.965 | G383: =(B383-G384)*2/51+G384 -> 14738.124 | H383: =(B383-H384)*0.125+H384 -> 14517.684 | I383: =(B383-I384)*1/3+I384 -> 14132.581 | J383: =IF(B383<>"",H383 + 2.6*STDEV(B383:B397),"") -> 16399.404 | K383: =ln(B383)-ln(B384) -> 0.00021198254 | L383: =SQRT(_xlfn.VAR.S($K383:K$750)) -> 0.0071706657 | M383: =L383*SQRT(365) -> 0.13699538 | N383: =PERCENTILE($K383:K$750,0.05) -> -0.0073725219 | O383: =PERCENTILE(K383:K412, 0.05) -> -0.023620127 | P383: =-IF(B383<>"",B383/MAX($B383:B$826)-1,"") -> 0.10968367 | U383: =(B383-H383)/STDEV(B383:B397) -> -0.70262628
A384: 45716 | B384: 14006.197 | C384: =AVERAGE($B384:B$826) -> 12500.316 | D384: =B384-C384 -> 1505.8815 | E384: =TREND($B384:$B$751,$A384:$A$751,A384) -> 15283.317 | F384: =IF(B384<>"",H384 - 2.6*STDEV(B384:B398),"") -> 12649.374 | G384: =(B384-G385)*2/51+G385 -> 14767.878 | H384: =(B384-H385)*0.125+H385 -> 14590.329 | I384: =(B384-I385)*1/3+I385 -> 14194.288 | J384: =IF(B384<>"",H384 + 2.6*STDEV(B384:B398),"") -> 16531.285 | K384: =ln(B384)-ln(B385) -> -0.019941953 | L384: =SQRT(_xlfn.VAR.S($K384:K$750)) -> 0.0071803895 | M384: =L384*SQRT(365) -> 0.13718115 | N384: =PERCENTILE($K384:K$750,0.05) -> -0.0073814063 | O384: =PERCENTILE(K384:K413, 0.05) -> -0.023620127 | P384: =-IF(B384<>"",B384/MAX($B384:B$826)-1,"") -> 0.10987238 | U384: =(B384-H384)/STDEV(B384:B398) -> -0.78247236
A385: 45715 | B385: 14288.312 | C385: =AVERAGE($B385:B$826) -> 12496.909 | D385: =B385-C385 -> 1791.403 | E385: =TREND($B385:$B$751,$A385:$A$751,A385) -> 15284.627 | F385: =IF(B385<>"",H385 - 2.6*STDEV(B385:B399),"") -> 12740.884 | G385: =(B385-G386)*2/51+G386 -> 14798.967 | H385: =(B385-H386)*0.125+H386 -> 14673.777 | I385: =(B385-I386)*1/3+I386 -> 14288.334 | J385: =IF(B385<>"",H385 + 2.6*STDEV(B385:B399),"") -> 16606.67 | K385: =ln(B385)-ln(B386) -> -0.00078350882 | L385: =SQRT(_xlfn.VAR.S($K385:K$750)) -> 0.0071075587 | M385: =L385*SQRT(365) -> 0.13578972 | N385: =PERCENTILE($K385:K$750,0.05) -> -0.0071944888 | O385: =PERCENTILE(K385:K414, 0.05) -> -0.018766758 | P385: =-IF(B385<>"",B385/MAX($B385:B$826)-1,"") -> 0.091943321 | U385: =(B385-H385)/STDEV(B385:B399) -> -0.51850228
A386: 45714 | B386: 14299.511 | C386: =AVERAGE($B386:B$826) -> 12492.847 | D386: =B386-C386 -> 1806.6645 | E386: =TREND($B386:$B$751,$A386:$A$751,A386) -> 15282.849 | F386: =IF(B386<>"",H386 - 2.6*STDEV(B386:B400),"") -> 12779.784 | G386: =(B386-G387)*2/51+G387 -> 14819.81 | H386: =(B386-H387)*0.125+H387 -> 14728.843 | I386: =(B386-I387)*1/3+I387 -> 14288.345 | J386: =IF(B386<>"",H386 + 2.6*STDEV(B386:B400),"") -> 16677.903 | K386: =ln(B386)-ln(B387) -> 0.0055694838 | L386: =SQRT(_xlfn.VAR.S($K386:K$750)) -> 0.0071167949 | M386: =L386*SQRT(365) -> 0.13596618 | N386: =PERCENTILE($K386:K$750,0.05) -> -0.0072069959 | O386: =PERCENTILE(K386:K415, 0.05) -> -0.018766758 | P386: =-IF(B386<>"",B386/MAX($B386:B$826)-1,"") -> 0.091231572 | U386: =(B386-H386)/STDEV(B386:B400) -> -0.57271933
A387: 45713 | B387: 14220.092 | C387: =AVERAGE($B387:B$826) -> 12488.741 | D387: =B387-C387 -> 1731.351 | E387: =TREND($B387:$B$751,$A387:$A$751,A387) -> 15280.914 | F387: =IF(B387<>"",H387 - 2.6*STDEV(B387:B401),"") -> 12847.166 | G387: =(B387-G388)*2/51+G388 -> 14841.046 | H387: =(B387-H388)*0.125+H388 -> 14790.177 | I387: =(B387-I388)*1/3+I388 -> 14282.762 | J387: =IF(B387<>"",H387 + 2.6*STDEV(B387:B401),"") -> 16733.187 | K387: =ln(B387)-ln(B388) -> 0.0061056701 | L387: =SQRT(_xlfn.VAR.S($K387:K$750)) -> 0.007122292 | M387: =L387*SQRT(365) -> 0.1360712 | N387: =PERCENTILE($K387:K$750,0.05) -> -0.0072195031 | O387: =PERCENTILE(K387:K416, 0.05) -> -0.018766758 | P387: =-IF(B387<>"",B387/MAX($B387:B$826)-1,"") -> 0.096278874 | U387: =(B387-H387)/STDEV(B387:B401) -> -0.76284753
... A554: 45546 | B554: 13013.217 | C554: =AVERAGE($B554:B$826) -> 11435.908 | D554: =B554-C554 -> 1577.3089 | E554: =TREND($B554:$B$751,$A554:$A$751,A554) -> 13343.313 | F554: =IF(B554<>"",H554 - 2.6*STDEV(B554:B568),"") -> 12884.938 | G554: =(B554-G555)*2/51+G555 -> 12892.029 | H554: =(B554-H555)*0.125+H555 -> 13051.367 | I554: =(B554-I555)*1/3+I555 -> 13047.384 | J554: =IF(B554<>"",H554 + 2.6*STDEV(B554:B568),"") -> 13217.796 | K554: =ln(B554)-ln(B555) -> -0.002471305 | L554: =SQRT(_xlfn.VAR.S($K554:K$750)) -> 0.0053224309 | M554: =L554*SQRT(365) -> 0.1016849 | N554: =PERCENTILE($K554:K$750,0.05) -> -0.0060043626 | O554: =PERCENTILE(K554:K583, 0.05) -> -0.0040554851 | P554: =-IF(B554<>"",B554/MAX($B554:B$826)-1,"") -> 0.013345439 | U554: =(B554-H554)/STDEV(B554:B568) -> -0.59598524
A555: 45545 | B555: 13045.416 | C555: =AVERAGE($B555:B$826) -> 11430.109 | D555: =B555-C555 -> 1615.3073 | E555: =TREND($B555:$B$751,$A555:$A$751,A555) -> 13335.41 | F555: =IF(B555<>"",H555 - 2.6*STDEV(B555:B569),"") -> 12897.261 | G555: =(B555-G556)*2/51+G556 -> 12887.082 | H555: =(B555-H556)*0.125+H556 -> 13056.817 | I555: =(B555-I556)*1/3+I556 -> 13064.467 | J555: =IF(B555<>"",H555 + 2.6*STDEV(B555:B569),"") -> 13216.373 | K555: =ln(B555)-ln(B556) -> -0.0026394307 | L555: =SQRT(_xlfn.VAR.S($K555:K$750)) -> 0.005329842 | M555: =L555*SQRT(365) -> 0.10182649 | N555: =PERCENTILE($K555:K$750,0.05) -> -0.006006728 | O555: =PERCENTILE(K554:K583, 0.05) -> -0.0040554851 | P555: =-IF(B555<>"",B555/MAX($B555:B$826)-1,"") -> 0.010904099 | U555: =(B555-H555)/STDEV(B555:B569) -> -0.18576964
A556: 45544 | B556: 13079.894 | C556: =AVERAGE($B556:B$826) -> 11424.149 | D556: =B556-C556 -> 1655.7458 | E556: =TREND($B556:$B$751,$A556:$A$751,A556) -> 13326.671 | F556: =IF(B556<>"",H556 - 2.6*STDEV(B556:B570),"") -> 12885.476 | G556: =(B556-G557)*2/51+G557 -> 12880.62 | H556: =(B556-H557)*0.125+H557 -> 13058.445 | I556: =(B556-I557)*1/3+I557 -> 13073.992 | J556: =IF(B556<>"",H556 + 2.6*STDEV(B556:B570),"") -> 13231.414 | K556: =ln(B556)-ln(B557) -> 0.0022180773 | L556: =SQRT(_xlfn.VAR.S($K556:K$750)) -> 0.0053366529 | M556: =L556*SQRT(365) -> 0.10195661 | N556: =PERCENTILE($K556:K$750,0.05) -> -0.0060090934 | O556: =PERCENTILE(K555:K584, 0.05) -> -0.0040554851 | P556: =-IF(B556<>"",B556/MAX($B556:B$826)-1,"") -> 0.0082900005 | U556: =(B556-H556)/STDEV(B556:B570) -> 0.3224139
A557: 45543 | B557: 13050.914 | C557: =AVERAGE($B557:B$826) -> 11418.016 | D557: =B557-C557 -> 1632.8981 | E557: =TREND($B557:$B$751,$A557:$A$751,A557) -> 13317.031 | F557: =IF(B557<>"",H557 - 2.6*STDEV(B557:B571),"") -> 12850.954 | G557: =(B557-G558)*2/51+G558 -> 12872.486 | H557: =(B557-H558)*0.125+H558 -> 13055.381 | I557: =(B557-I558)*1/3+I558 -> 13071.041 | J557: =IF(B557<>"",H557 + 2.6*STDEV(B557:B571),"") -> 13259.809 | K557: =ln(B557)-ln(B558) -> 0.00082173036 | L557: =SQRT(_xlfn.VAR.S($K557:K$750)) -> 0.005349909 | M557: =L557*SQRT(365) -> 0.10220987 | N557: =PERCENTILE($K557:K$750,0.05) -> -0.0060114587 | O557: =PERCENTILE(K556:K585, 0.05) -> -0.0040554851 | P557: =-IF(B557<>"",B557/MAX($B557:B$826)-1,"") -> 0.010487252 | U557: =(B557-H557)/STDEV(B557:B571) -> -0.056811143
A558: 45542 | B558: 13040.194 | C558: =AVERAGE($B558:B$826) -> 11411.946 | D558: =B558-C558 -> 1628.2484 | E558: =TREND($B558:$B$751,$A558:$A$751,A558) -> 13307.776 | F558: =IF(B558<>"",H558 - 2.6*STDEV(B558:B572),"") -> 12825.594 | G558: =(B558-G559)*2/51+G559 -> 12865.203 | H558: =(B558-H559)*0.125+H559 -> 13056.019 | I558: =(B558-I559)*1/3+I559 -> 13081.104 | J558: =IF(B558<>"",H558 + 2.6*STDEV(B558:B572),"") -> 13286.444 | K558: =ln(B558)-ln(B559) -> 0.00070178305 | L558: =SQRT(_xlfn.VAR.S($K558:K$750)) -> 0.005363771 | M558: =L558*SQRT(365) -> 0.1024747 | N558: =PERCENTILE($K558:K$750,0.05) -> -0.0060138241 | O558: =PERCENTILE(K557:K586, 0.05) -> -0.0040554851 | P558: =-IF(B558<>"",B558/MAX($B558:B$826)-1,"") -> 0.011300031 | U558: =(B558-H558)/STDEV(B558:B572) -> -0.17856004
A559: 45541 | B559: 13031.046 | C559: =AVERAGE($B559:B$826) -> 11405.87 | D559: =B559-C559 -> 1625.1758 | E559: =TREND($B559:$B$751,$A559:$A$751,A559) -> 13298.538 | F559: =IF(B559<>"",H559 - 2.6*STDEV(B559:B573),"") -> 12804.949 | G559: =(B559-G560)*2/51+G560 -> 12858.061 | H559: =(B559-H560)*0.125+H560 -> 13058.28 | I559: =(B559-I560)*1/3+I560 -> 13101.559 | J559: =IF(B559<>"",H559 + 2.6*STDEV(B559:B573),"") -> 13311.611 | K559: =ln(B559)-ln(B560) -> -0.00995215 | L559: =SQRT(_xlfn.VAR.S($K559:K$750)) -> 0.0053776958 | M559: =L559*SQRT(365) -> 0.10274073 | N559: =PERCENTILE($K559:K$750,0.05) -> -0.0060161895 | O559: =PERCENTILE(K558:K587, 0.05) -> -0.0040554851 | P559: =-IF(B559<>"",B559/MAX($B559:B$826)-1,"") -> 0.01199364 | U559: =(B559-H559)/STDEV(B559:B573) -> -0.27950699
A560: 45540 | B560: 13161.381 | C560: =AVERAGE($B560:B$826) -> 11399.784 | D560: =B560-C560 -> 1761.597 | E560: =TREND($B560:$B$751,$A560:$A$751,A560) -> 13289.283 | F560: =IF(B560<>"",H560 - 2.6*STDEV(B560:B574),"") -> 12792.494 | G560: =(B560-G561)*2/51+G561 -> 12851 | H560: =(B560-H561)*0.125+H561 -> 13062.171 | I560: =(B560-I561)*1/3+I561 -> 13136.816 | J560: =IF(B560<>"",H560 + 2.6*STDEV(B560:B574),"") -> 13331.847 | K560: =ln(B560)-ln(B561) -> 0.0029376494 | L560: =SQRT(_xlfn.VAR.S($K560:K$750)) -> 0.0053309896 | M560: =L560*SQRT(365) -> 0.10184841 | N560: =PERCENTILE($K560:K$750,0.05) -> -0.0058925912 | O560: =PERCENTILE(K559:K588, 0.05) -> -0.0052986186 | P560: =-IF(B560<>"",B560/MAX($B560:B$826)-1,"") -> 0.0021117614 | U560: =(B560-H560)/STDEV(B560:B574) -> 0.95650263
A561: 45539 | B561: 13122.774 | C561: =AVERAGE($B561:B$826) -> 11393.161 | D561: =B561-C561 -> 1729.6127 | E561: =TREND($B561:$B$751,$A561:$A$751,A561) -> 13277.09 | F561: =IF(B561<>"",H561 - 2.6*STDEV(B561:B575),"") -> 12767.89 | G561: =(B561-G562)*2/51+G562 -> 12838.332 | H561: =(B561-H562)*0.125+H562 -> 13047.998 | I561: =(B561-I562)*1/3+I562 -> 13124.533 | J561: =IF(B561<>"",H561 + 2.6*STDEV(B561:B575),"") -> 13328.105 | K561: =ln(B561)-ln(B562) -> -0.00045160862 | L561: =SQRT(_xlfn.VAR.S($K561:K$750)) -> 0.0053435893 | M561: =L561*SQRT(365) -> 0.10208913 | N561: =PERCENTILE($K561:K$750,0.05) -> -0.0059028222 | O561: =PERCENTILE(K560:K589, 0.05) -> -0.0040554851 | P561: =-IF(B561<>"",B561/MAX($B561:B$826)-1,"") -> 0.0050389057 | U561: =(B561-H561)/STDEV(B561:B575) -> 0.69408403
A562: 45538 | B562: 13128.702 | C562: =AVERAGE($B562:B$826) -> 11386.634 | D562: =B562-C562 -> 1742.0673 | E562: =TREND($B562:$B$751,$A562:$A$751,A562) -> 13265.446 | F562: =IF(B562<>"",H562 - 2.6*STDEV(B562:B576),"") -> 12749.405 | G562: =(B562-G563)*2/51+G563 -> 12826.722 | H562: =(B562-H563)*0.125+H563 -> 13037.315 | I562: =(B562-I563)*1/3+I563 -> 13125.413 | J562: =IF(B562<>"",H562 + 2.6*STDEV(B562:B576),"") -> 13325.226 | K562: =ln(B562)-ln(B563) -> -0.00045690957 | L562: =SQRT(_xlfn.VAR.S($K562:K$750)) -> 0.0053564188 | M562: =L562*SQRT(365) -> 0.10233424 | N562: =PERCENTILE($K562:K$750,0.05) -> -0.0059130532 | O562: =PERCENTILE(K561:K590, 0.05) -> -0.0040554851 | P562: =-IF(B562<>"",B562/MAX($B562:B$826)-1,"") -> 0.0045894712 | U562: =(B562-H562)/STDEV(B562:B576) -> 0.82527104
A563: 45537 | B563: 13134.702 | C563: =AVERAGE($B563:B$826) -> 11380.036 | D563: =B563-C563 -> 1754.666 | E563: =TREND($B563:$B$751,$A563:$A$751,A563) -> 13253.422 | F563: =IF(B563<>"",H563 - 2.6*STDEV(B563:B577),"") -> 12734.237 | G563: =(B563-G564)*2/51+G564 -> 12814.396 | H563: =(B563-H564)*0.125+H564 -> 13024.26 | I563: =(B563-I564)*1/3+I564 -> 13123.769 | J563: =IF(B563<>"",H563 + 2.6*STDEV(B563:B577),"") -> 13314.283 | K563: =ln(B563)-ln(B564) -> -0.00087256691 | L563: =SQRT(_xlfn.VAR.S($K563:K$750)) -> 0.005369331 | M563: =L563*SQRT(365) -> 0.10258092 | N563: =PERCENTILE($K563:K$750,0.05) -> -0.0059232842 | O563: =PERCENTILE(K562:K591, 0.05) -> -0.0044454201 | P563: =-IF(B563<>"",B563/MAX($B563:B$826)-1,"") -> 0.0041345547 | U563: =(B563-H563)/STDEV(B563:B577) -> 0.99008627
A564: 45536 | B564: 13146.167 | C564: =AVERAGE($B564:B$826) -> 11373.364 | D564: =B564-C564 -> 1772.8037 | E564: =TREND($B564:$B$751,$A564:$A$751,A564) -> 13241.007 | F564: =IF(B564<>"",H564 - 2.6*STDEV(B564:B578),"") -> 12722.986 | G564: =(B564-G565)*2/51+G565 -> 12801.322 | H564: =(B564-H565)*0.125+H565 -> 13008.483 | I564: =(B564-I565)*1/3+I565 -> 13118.302 | J564: =IF(B564<>"",H564 + 2.6*STDEV(B564:B578),"") -> 13293.98 | K564: =ln(B564)-ln(B565) -> -0.0032705587 | L564: =SQRT(_xlfn.VAR.S($K564:K$750)) -> 0.0053815494 | M564: =L564*SQRT(365) -> 0.10281436 | N564: =PERCENTILE($K564:K$750,0.05) -> -0.0059335152 | O564: =PERCENTILE(K563:K592, 0.05) -> -0.0044454201 | P564: =-IF(B564<>"",B564/MAX($B564:B$826)-1,"") -> 0.0032652162 | U564: =(B564-H564)/STDEV(B564:B578) -> 1.253885
A565: 45535 | B565: 13189.233 | C565: =AVERAGE($B565:B$826) -> 11366.597 | D565: =B565-C565 -> 1822.6358 | E565: =TREND($B565:$B$751,$A565:$A$751,A565) -> 13228.074 | F565: =IF(B565<>"",H565 - 2.6*STDEV(B565:B579),"") -> 12712.805 | G565: =(B565-G566)*2/51+G566 -> 12787.247 | H565: =(B565-H566)*0.125+H566 -> 12988.814 | I565: =(B565-I566)*1/3+I566 -> 13104.37 | J565: =IF(B565<>"",H565 + 2.6*STDEV(B565:B579),"") -> 13264.822 | K565: =ln(B565)-ln(B566) -> 0.00081201573 | L565: =SQRT(_xlfn.VAR.S($K565:K$750)) -> 0.0053858654 | M565: =L565*SQRT(365) -> 0.10289681 | N565: =PERCENTILE($K565:K$750,0.05) -> -0.0059437462 | O565: =PERCENTILE(K564:K593, 0.05) -> -0.0044454201 | P565: =-IF(B565<>"",B565/MAX($B565:B$826)-1,"") -> 0 | U565: =(B565-H565)/STDEV(B565:B579) -> 1.8879546
A566: 45534 | B566: 13178.528 | C566: =AVERAGE($B566:B$826) -> 11359.614 | D566: =B566-C566 -> 1818.9135 | E566: =TREND($B566:$B$751,$A566:$A$751,A566) -> 13213.931 | F566: =IF(B566<>"",H566 - 2.6*STDEV(B566:B580),"") -> 12721.804 | G566: =(B566-G567)*2/51+G567 -> 12770.84 | H566: =(B566-H567)*0.125+H567 -> 12960.182 | I566: =(B566-I567)*1/3+I567 -> 13061.938 | J566: =IF(B566<>"",H566 + 2.6*STDEV(B566:B580),"") -> 13198.561 | K566: =ln(B566)-ln(B567) -> 0.009815952 | L566: =SQRT(_xlfn.VAR.S($K566:K$750)) -> 0.0054003822 | M566: =L566*SQRT(365) -> 0.10317416 | N566: =PERCENTILE($K566:K$750,0.05) -> -0.0059539772 | O566: =PERCENTILE(K565:K594, 0.05) -> -0.0052986186 | P566: =-IF(B566<>"",B566/MAX($B566:B$826)-1,"") -> 0 | U566: =(B566-H566)/STDEV(B566:B580) -> 2.3814987
... A686: 45414 | B686: 11295.662 | C686: =AVERAGE($B686:B$826) -> 10507.245 | D686: =B686-C686 -> 788.41718 | E686: =TREND($B686:$B$751,$A686:$A$751,A686) -> 11193.921 | F686: =IF(B686<>"",H686 - 2.6*STDEV(B686:B700),"") -> 10818.658 | G686: =(B686-G687)*2/51+G687 -> 11607.564 | H686: =(B686-H687)*0.125+H687 -> 11089.682 | I686: =(B686-I687)*1/3+I687 -> 11178.103 | J686: =IF(B686<>"",H686 + 2.6*STDEV(B686:B700),"") -> 11360.705 | K686: =ln(B686)-ln(B687) -> 0.0092017545 | L686: =SQRT(_xlfn.VAR.S($K686:K$750)) -> 0.0053910076 | M686: =L686*SQRT(365) -> 0.10299506 | N686: =PERCENTILE($K686:K$750,0.05) -> -0.0087645039 | O686: =PERCENTILE(K685:K714, 0.05) -> -0.010664912 | P686: =-IF(B686<>"",B686/MAX($B686:B$826)-1,"") -> 0 | U686: =(B686-H686)/STDEV(B686:B700) -> 1.9760275
A687: 45413 | B687: 11192.199 | C687: =AVERAGE($B687:B$826) -> 10501.614 | D687: =B687-C687 -> 690.58557 | E687: =TREND($B687:$B$751,$A687:$A$751,A687) -> 11177.33 | F687: =IF(B687<>"",H687 - 2.6*STDEV(B687:B701),"") -> 10849.291 | G687: =(B687-G688)*2/51+G688 -> 11620.294 | H687: =(B687-H688)*0.125+H688 -> 11060.256 | I687: =(B687-I688)*1/3+I688 -> 11119.323 | J687: =IF(B687<>"",H687 + 2.6*STDEV(B687:B701),"") -> 11271.221 | K687: =ln(B687)-ln(B688) -> 0.0052792917 | L687: =SQRT(_xlfn.VAR.S($K687:K$750)) -> 0.0053379054 | M687: =L687*SQRT(365) -> 0.10198054 | N687: =PERCENTILE($K687:K$750,0.05) -> -0.008937604 | O687: =PERCENTILE(K686:K715, 0.05) -> -0.010664912 | P687: =-IF(B687<>"",B687/MAX($B687:B$826)-1,"") -> 0
A688: 45412 | B688: 11133.268 | C688: =AVERAGE($B688:B$826) -> 10496.645 | D688: =B688-C688 -> 636.62262 | E688: =TREND($B688:$B$751,$A688:$A$751,A688) -> 11166.218 | F688: =IF(B688<>"",H688 - 2.6*STDEV(B688:B702),"") -> 10854.427 | G688: =(B688-G689)*2/51+G689 -> 11637.768 | H688: =(B688-H689)*0.125+H689 -> 11041.407 | I688: =(B688-I689)*1/3+I689 -> 11082.885 | J688: =IF(B688<>"",H688 + 2.6*STDEV(B688:B702),"") -> 11228.387 | K688: =ln(B688)-ln(B689) -> -0.0030300938 | L688: =SQRT(_xlfn.VAR.S($K688:K$750)) -> 0.0053538585 | M688: =L688*SQRT(365) -> 0.10228532 | N688: =PERCENTILE($K688:K$750,0.05) -> -0.0091107042 | O688: =PERCENTILE(K687:K716, 0.05) -> -0.010664912 | P688: =-IF(B688<>"",B688/MAX($B688:B$826)-1,"") -> 0.0034237503
A689: 45411 | B689: 11167.054 | C689: =AVERAGE($B689:B$826) -> 10492.032 | D689: =B689-C689 -> 675.02184 | E689: =TREND($B689:$B$751,$A689:$A$751,A689) -> 11158.148 | F689: =IF(B689<>"",H689 - 2.6*STDEV(B689:B703),"") -> 10849.312 | G689: =(B689-G690)*2/51+G690 -> 11658.36 | H689: =(B689-H690)*0.125+H690 -> 11028.284 | I689: =(B689-I690)*1/3+I690 -> 11057.693 | J689: =IF(B689<>"",H689 + 2.6*STDEV(B689:B703),"") -> 11207.256 | K689: =ln(B689)-ln(B690) -> 0.012637139 | L689: =SQRT(_xlfn.VAR.S($K689:K$750)) -> 0.0053722826 | M689: =L689*SQRT(365) -> 0.10263731 | N689: =PERCENTILE($K689:K$750,0.05) -> -0.0092838044 | O689: =PERCENTILE(K688:K717, 0.05) -> -0.010664912 | P689: =-IF(B689<>"",B689/MAX($B689:B$826)-1,"") -> 0.0003994512
A690: 45410 | B690: 11026.822 | C690: =AVERAGE($B690:B$826) -> 10487.105 | D690: =B690-C690 -> 539.71732 | E690: =TREND($B690:$B$751,$A690:$A$751,A690) -> 11147.362 | F690: =IF(B690<>"",H690 - 2.6*STDEV(B690:B704),"") -> 10850.68 | G690: =(B690-G691)*2/51+G691 -> 11678.413 | H690: =(B690-H691)*0.125+H691 -> 11008.46 | I690: =(B690-I691)*1/3+I691 -> 11003.013 | J690: =IF(B690<>"",H690 + 2.6*STDEV(B690:B704),"") -> 11166.239 | K690: =ln(B690)-ln(B691) -> 0.0027605223 | L690: =SQRT(_xlfn.VAR.S($K690:K$750)) -> 0.0052037548 | M690: =L690*SQRT(365) -> 0.099417597 | N690: =PERCENTILE($K690:K$750,0.05) -> -0.0094569045 | O690: =PERCENTILE(K689:K718, 0.05) -> -0.010664912 | P690: =-IF(B690<>"",B690/MAX($B690:B$826)-1,"") -> 0.012952061
A691: 45409 | B691: 10996.425 | C691: =AVERAGE($B691:B$826) -> 10483.137 | D691: =B691-C691 -> 513.28802 | E691: =TREND($B691:$B$751,$A691:$A$751,A691) -> 11145.068 | F691: =IF(B691<>"",H691 - 2.6*STDEV(B691:B705),"") -> 10839.242 | G691: =(B691-G692)*2/51+G692 -> 11705.008 | H691: =(B691-H692)*0.125+H692 -> 11005.836 | I691: =(B691-I692)*1/3+I692 -> 10991.108 | J691: =IF(B691<>"",H691 + 2.6*STDEV(B691:B705),"") -> 11172.43 | K691: =ln(B691)-ln(B692) -> 0.00072458389 | L691: =SQRT(_xlfn.VAR.S($K691:K$750)) -> 0.0052419126 | M691: =L691*SQRT(365) -> 0.1001466 | N691: =PERCENTILE($K691:K$750,0.05) -> -0.0095667234 | O691: =PERCENTILE(K690:K724, 0.05) -> -0.010115818 | P691: =-IF(B691<>"",B691/MAX($B691:B$826)-1,"") -> 0.015673071
A692: 45408 | B692: 10988.46 | C692: =AVERAGE($B692:B$826) -> 10479.334 | D692: =B692-C692 -> 509.12521 | E692: =TREND($B692:$B$751,$A692:$A$751,A692) -> 11144.583 | F692: =IF(B692<>"",H692 - 2.6*STDEV(B692:B706),"") -> 10837.346 | G692: =(B692-G693)*2/51+G693 -> 11733.93 | H692: =(B692-H693)*0.125+H693 -> 11007.181 | I692: =(B692-I693)*1/3+I693 -> 10988.45 | J692: =IF(B692<>"",H692 + 2.6*STDEV(B692:B706),"") -> 11177.015 | K692: =ln(B692)-ln(B693) -> 0.0056734446 | L692: =SQRT(_xlfn.VAR.S($K692:K$750)) -> 0.0052868792 | M692: =L692*SQRT(365) -> 0.10100568 | N692: =PERCENTILE($K692:K$750,0.05) -> -0.0096765423 | O692: =PERCENTILE(K691:K725, 0.05) -> -0.010115818 | P692: =-IF(B692<>"",B692/MAX($B692:B$826)-1,"") -> 0.01638604
A693: 45407 | B693: 10926.294 | C693: =AVERAGE($B693:B$826) -> 10475.535 | D693: =B693-C693 -> 450.75874 | E693: =TREND($B693:$B$751,$A693:$A$751,A693) -> 11144.52 | F693: =IF(B693<>"",H693 - 2.6*STDEV(B693:B707),"") -> 10812.887 | G693: =(B693-G694)*2/51+G694 -> 11764.357 | H693: =(B693-H694)*0.125+H694 -> 11009.855 | I693: =(B693-I694)*1/3+I694 -> 10988.445 | J693: =IF(B693<>"",H693 + 2.6*STDEV(B693:B707),"") -> 11206.824 | K693: =ln(B693)-ln(B694) -> -0.0016198938 | L693: =SQRT(_xlfn.VAR.S($K693:K$750)) -> 0.0052941391 | M693: =L693*SQRT(365) -> 0.10114439 | N693: =PERCENTILE($K693:K$750,0.05) -> -0.0097863612 | O693: =PERCENTILE(K692:K726, 0.05) -> -0.010115818 | P693: =-IF(B693<>"",B693/MAX($B693:B$826)-1,"") -> 0.021950719
A694: 45406 | B694: 10944.007 | C694: =AVERAGE($B694:B$826) -> 10472.146 | D694: =B694-C694 -> 471.86169 | E694: =TREND($B694:$B$751,$A694:$A$751,A694) -> 11148.649 | F694: =IF(B694<>"",H694 - 2.6*STDEV(B694:B708),"") -> 10836.4 | G694: =(B694-G695)*2/51+G695 -> 11798.564 | H694: =(B694-H695)*0.125+H695 -> 11021.793 | I694: =(B694-I695)*1/3+I695 -> 11019.52 | J694: =IF(B694<>"",H694 + 2.6*STDEV(B694:B708),"") -> 11207.185 | K694: =ln(B694)-ln(B695) -> -0.0176241 | L694: =SQRT(_xlfn.VAR.S($K694:K$750)) -> 0.005331421 | M694: =L694*SQRT(365) -> 0.10185665 | N694: =PERCENTILE($K694:K$750,0.05) -> -0.0098961801 | O694: =PERCENTILE(K693:K727, 0.05) -> -0.010115818 | P694: =-IF(B694<>"",B694/MAX($B694:B$826)-1,"") -> 0.020365099
A695: 45405 | B695: 11138.595 | C695: =AVERAGE($B695:B$826) -> 10468.571 | D695: =B695-C695 -> 670.02436 | E695: =TREND($B695:$B$751,$A695:$A$751,A695) -> 11151.693 | F695: =IF(B695<>"",H695 - 2.6*STDEV(B695:B709),"") -> 10852.749 | G695: =(B695-G696)*2/51+G696 -> 11833.444 | H695: =(B695-H696)*0.125+H696 -> 11032.905 | I695: =(B695-I696)*1/3+I696 -> 11057.277 | J695: =IF(B695<>"",H695 + 2.6*STDEV(B695:B709),"") -> 11213.061 | K695: =ln(B695)-ln(B696) -> 0.011019569 | L695: =SQRT(_xlfn.VAR.S($K695:K$750)) -> 0.0047587957 | M695: =L695*SQRT(365) -> 0.090916664 | N695: =PERCENTILE($K695:K$750,0.05) -> -0.006860402 | O695: =PERCENTILE(K694:K728, 0.05) -> -0.010115818 | P695: =-IF(B695<>"",B695/MAX($B695:B$826)-1,"") -> 0.0029468766
A696: 45404 | B696: 11016.527 | C696: =AVERAGE($B696:B$826) -> 10463.456 | D696: =B696-C696 -> 553.07033 | E696: =TREND($B696:$B$751,$A696:$A$751,A696) -> 11140.926 | F696: =IF(B696<>"",H696 - 2.6*STDEV(B696:B710),"") -> 10841.366 | G696: =(B696-G697)*2/51+G697 -> 11861.805 | H696: =(B696-H697)*0.125+H697 -> 11017.806 | I696: =(B696-I697)*1/3+I697 -> 11016.617 | J696: =IF(B696<>"",H696 + 2.6*STDEV(B696:B710),"") -> 11194.246 | K696: =ln(B696)-ln(B697) -> 0.00072242031 | L696: =SQRT(_xlfn.VAR.S($K696:K$750)) -> 0.004607397 | M696: =L696*SQRT(365) -> 0.088024195 | N696: =PERCENTILE($K696:K$750,0.05) -> -0.0070335022 | O696: =PERCENTILE(K695:K729, 0.05) -> -0.0070335022 | P696: =-IF(B696<>"",B696/MAX($B696:B$826)-1,"") -> 0.013873658
A697: 45403 | B697: 11008.571 | C697: =AVERAGE($B697:B$826) -> 10459.202 | D697: =B697-C697 -> 549.36903 | E697: =TREND($B697:$B$751,$A697:$A$751,A697) -> 11138.246 | F697: =IF(B697<>"",H697 - 2.6*STDEV(B697:B711),"") -> 10841.026 | G697: =SUM(B697:B751)/50 -> 11896.306 | H697: =(B697-H698)*0.125+H698 -> 11017.989 | I697: =(B697-I698)*1/3+I698 -> 11016.663 | J697: =IF(B697<>"",H697 + 2.6*STDEV(B697:B711),"") -> 11194.952 | K697: =ln(B697)-ln(B698) -> 0.00072277478 | L697: =SQRT(_xlfn.VAR.S($K697:K$750)) -> 0.0046505347 | M697: =L697*SQRT(365) -> 0.088848341 | N697: =PERCENTILE($K697:K$750,0.05) -> -0.0072066023 | O697: =PERCENTILE(K696:K730, 0.05) -> -0.0070335022 | P697: =-IF(B697<>"",B697/MAX($B697:B$826)-1,"") -> 0.014585798
A698: 45402 | B698: 11000.617 | C698: =AVERAGE($B698:B$826) -> 10454.943 | D698: =B698-C698 -> 545.67386 | E698: =TREND($B698:$B$751,$A698:$A$751,A698) -> 11135.873 | F698: =IF(B698<>"",H698 - 2.6*STDEV(B698:B712),"") -> 10844.791 | H698: =(B698-H699)*0.125+H699 -> 11019.334 | I698: =(B698-I699)*1/3+I699 -> 11020.709 | J698: =IF(B698<>"",H698 + 2.6*STDEV(B698:B712),"") -> 11193.878 | K698: =ln(B698)-ln(B699) -> 0.0007231298 | L698: =SQRT(_xlfn.VAR.S($K698:K$750)) -> 0.0046949077 | M698: =L698*SQRT(365) -> 0.089696086 | N698: =PERCENTILE($K698:K$750,0.05) -> -0.0073797025 | O698: =PERCENTILE(K697:K731, 0.05) -> -0.0070335022 | P698: =-IF(B698<>"",B698/MAX($B698:B$826)-1,"") -> 0.015297774
A699: 45401 | B699: 10992.665 | C699: =AVERAGE($B699:B$826) -> 10450.68 | D699: =B699-C699 -> 541.98494 | E699: =TREND($B699:$B$751,$A699:$A$751,A699) -> 11133.831 | F699: =IF(B699<>"",H699 - 2.6*STDEV(B699:B713),"") -> 10852.963 | H699: =(B699-H700)*0.125+H700 -> 11022.008 | I699: =(B699-I700)*1/3+I700 -> 11030.755 | J699: =IF(B699<>"",H699 + 2.6*STDEV(B699:B713),"") -> 11191.054 | K699: =ln(B699)-ln(B700) -> -0.0019057155 | L699: =SQRT(_xlfn.VAR.S($K699:K$750)) -> 0.0047405761 | M699: =L699*SQRT(365) -> 0.090568579 | N699: =PERCENTILE($K699:K$750,0.05) -> -0.0075528027 | O699: =PERCENTILE(K698:K732, 0.05) -> -0.0070335022 | P699: =-IF(B699<>"",B699/MAX($B699:B$826)-1,"") -> 0.016009584
A700: 45400 | B700: 11013.634 | C700: =AVERAGE($B700:B$826) -> 10446.413 | D700: =B700-C700 -> 567.2214 | E700: =TREND($B700:$B$751,$A700:$A$751,A700) -> 11132.145 | F700: =IF(B700<>"",H700 - 2.6*STDEV(B700:B714),"") -> 10865.199 | H700: =(B700-H701)*0.125+H701 -> 11026.2 | I700: =(B700-I701)*1/3+I701 -> 11049.799 | J700: =IF(B700<>"",H700 + 2.6*STDEV(B700:B714),"") -> 11187.202 | K700: =ln(B700)-ln(B701) -> -0.0059949012 | L700: =SQRT(_xlfn.VAR.S($K700:K$750)) -> 0.0047699469 | M700: =L700*SQRT(365) -> 0.091129707 | N700: =PERCENTILE($K700:K$750,0.05) -> -0.0077259029 | O700: =PERCENTILE(K699:K733, 0.05) -> -0.010115818 | P700: =-IF(B700<>"",B700/MAX($B700:B$826)-1,"") -> 0.01413259
A701: 45399 | B701: 11079.858 | C701: =AVERAGE($B701:B$826) -> 10441.911 | D701: =B701-C701 -> 637.94711 | E701: =TREND($B701:$B$751,$A701:$A$751,A701) -> 11128.575 | F701: =IF(B701<>"",H701 - 2.6*STDEV(B701:B715),"") -> 10869.821 | H701: =(B701-H702)*0.125+H702 -> 11027.995 | I701: =(B701-I702)*1/3+I702 -> 11067.882 | J701: =IF(B701<>"",H701 + 2.6*STDEV(B701:B715),"") -> 11186.17 | K701: =ln(B701)-ln(B702) -> -0.0018558204 | L701: =SQRT(_xlfn.VAR.S($K701:K$750)) -> 0.0047102791 | M701: =L701*SQRT(365) -> 0.089989755 | N701: =PERCENTILE($K701:K$750,0.05) -> -0.0068509632 | O701: =PERCENTILE(K700:K734, 0.05) -> -0.010115818 | P701: =-IF(B701<>"",B701/MAX($B701:B$826)-1,"") -> 0.0082046614
A702: 45398 | B702: 11100.439 | C702: =AVERAGE($B702:B$826) -> 10436.807 | D702: =B702-C702 -> 663.63201 | E702: =TREND($B702:$B$751,$A702:$A$751,A702) -> 11119.33 | F702: =IF(B702<>"",H702 - 2.6*STDEV(B702:B716),"") -> 10853.667 | H702: =(B702-H703)*0.125+H703 -> 11020.586 | I702: =(B702-I703)*1/3+I703 -> 11061.894 | J702: =IF(B702<>"",H702 + 2.6*STDEV(B702:B716),"") -> 11187.506 | K702: =ln(B702)-ln(B703) -> 0.00045881328 | L702: =SQRT(_xlfn.VAR.S($K702:K$750)) -> 0.0047384626 | M702: =L702*SQRT(365) -> 0.090528202 | N702: =PERCENTILE($K702:K$750,0.05) -> -0.0071405123 | O702: =PERCENTILE(K701:K735, 0.05) -> -0.010115818 | P702: =-IF(B702<>"",B702/MAX($B702:B$826)-1,"") -> 0.0063623584
A703: 45397 | B703: 11095.347 | C703: =AVERAGE($B703:B$826) -> 10431.455 | D703: =B703-C703 -> 663.89202 | E703: =TREND($B703:$B$751,$A703:$A$751,A703) -> 11107.609 | F703: =IF(B703<>"",H703 - 2.6*STDEV(B703:B717),"") -> 10825.326 | H703: =(B703-H704)*0.125+H704 -> 11009.179 | I703: =(B703-I704)*1/3+I704 -> 11042.621 | J703: =IF(B703<>"",H703 + 2.6*STDEV(B703:B717),"") -> 11193.031 | K703: =ln(B703)-ln(B704) -> 0.012797965 | L703: =SQRT(_xlfn.VAR.S($K703:K$750)) -> 0.0047872153 | M703: =L703*SQRT(365) -> 0.091459621 | N703: =PERCENTILE($K703:K$750,0.05) -> -0.0074300613 | O703: =PERCENTILE(K702:K736, 0.05) -> -0.010115818 | P703: =-IF(B703<>"",B703/MAX($B703:B$826)-1,"") -> 0.006818148
A704: 45396 | B704: 10954.254 | C704: =AVERAGE($B704:B$826) -> 10426.058 | D704: =B704-C704 -> 528.19642 | E704: =TREND($B704:$B$751,$A704:$A$751,A704) -> 11095.32 | F704: =IF(B704<>"",H704 - 2.6*STDEV(B704:B718),"") -> 10798.474 | H704: =(B704-H705)*0.125+H705 -> 10996.869 | I704: =(B704-I705)*1/3+I705 -> 11016.258 | J704: =IF(B704<>"",H704 + 2.6*STDEV(B704:B718),"") -> 11195.264 | K704: =ln(B704)-ln(B705) -> 0.001470724 | L704: =SQRT(_xlfn.VAR.S($K704:K$750)) -> 0.0045231811 | M704: =L704*SQRT(365) -> 0.086415253 | N704: =PERCENTILE($K704:K$750,0.05) -> -0.0077196103 | O704: =PERCENTILE(K703:K737, 0.05) -> -0.010115818 | P704: =-IF(B704<>"",B704/MAX($B704:B$826)-1,"") -> 0.019447865
A705: 45395 | B705: 10938.156 | C705: =AVERAGE($B705:B$826) -> 10421.728 | D705: =B705-C705 -> 516.42706 | E705: =TREND($B705:$B$751,$A705:$A$751,A705) -> 11093.983 | F705: =IF(B705<>"",H705 - 2.6*STDEV(B705:B719),"") -> 10794.428 | H705: =(B705-H706)*0.125+H706 -> 11002.957 | I705: =(B705-I706)*1/3+I706 -> 11047.26 | J705: =IF(B705<>"",H705 + 2.6*STDEV(B705:B719),"") -> 11211.485 | K705: =ln(B705)-ln(B706) -> -0.011653282 | L705: =SQRT(_xlfn.VAR.S($K705:K$750)) -> 0.0045726418 | M705: =L705*SQRT(365) -> 0.087360199 | N705: =PERCENTILE($K705:K$750,0.05) -> -0.0080091594 | O705: =PERCENTILE(K704:K738, 0.05) -> -0.010115818 | P705: =-IF(B705<>"",B705/MAX($B705:B$826)-1,"") -> 0.020888927
A706: 45394 | B706: 11066.367 | C706: =AVERAGE($B706:B$826) -> 10417.46 | D706: =B706-C706 -> 648.90605 | E706: =TREND($B706:$B$751,$A706:$A$751,A706) -> 11093.798 | F706: =IF(B706<>"",H706 - 2.6*STDEV(B706:B720),"") -> 10790.5 | H706: =(B706-H707)*0.125+H707 -> 11012.214 | I706: =(B706-I707)*1/3+I707 -> 11101.812 | J706: =IF(B706<>"",H706 + 2.6*STDEV(B706:B720),"") -> 11233.928 | K706: =ln(B706)-ln(B707) -> -0.0094569045 | L706: =SQRT(_xlfn.VAR.S($K706:K$750)) -> 0.0042027357 | M706: =L706*SQRT(365) -> 0.080293153 | N706: =PERCENTILE($K706:K$750,0.05) -> -0.0032298704 | O706: =PERCENTILE(K705:K739, 0.05) -> -0.010115818 | P706: =-IF(B706<>"",B706/MAX($B706:B$826)-1,"") -> 0.0094123286
A707: 45393 | B707: 11171.517 | C707: =AVERAGE($B707:B$826) -> 10412.053 | D707: =B707-C707 -> 759.46359 | E707: =TREND($B707:$B$751,$A707:$A$751,A707) -> 11082.05 | F707: =IF(B707<>"",H707 - 2.6*STDEV(B707:B721),"") -> 10754.74 | H707: =(B707-H708)*0.125+H708 -> 11004.478 | I707: =(B707-I708)*1/3+I708 -> 11119.535 | J707: =IF(B707<>"",H707 + 2.6*STDEV(B707:B721),"") -> 11254.216 | K707: =ln(B707)-ln(B708) -> 0.007600517 | L707: =SQRT(_xlfn.VAR.S($K707:K$750)) -> 0.0039153289 | M707: =L707*SQRT(365) -> 0.074802253 | N707: =PERCENTILE($K707:K$750,0.05) -> -0.0014856409 | O707: =PERCENTILE(K706:K740, 0.05) -> -0.0054032181 | P707: =-IF(B707<>"",B707/MAX($B707:B$826)-1,"") -> 0
A708: 45392 | B708: 11086.929 | C708: =AVERAGE($B708:B$826) -> 10405.671 | D708: =B708-C708 -> 681.25819 | E708: =TREND($B708:$B$751,$A708:$A$751,A708) -> 11059.647 | F708: =IF(B708<>"",H708 - 2.6*STDEV(B708:B722),"") -> 10723.906 | H708: =(B708-H709)*0.125+H709 -> 10980.615 | I708: =(B708-I709)*1/3+I709 -> 11093.545 | J708: =IF(B708<>"",H708 + 2.6*STDEV(B708:B722),"") -> 11237.325 | K708: =ln(B708)-ln(B709) -> -0.0036659239 | L708: =SQRT(_xlfn.VAR.S($K708:K$750)) -> 0.0038466137 | M708: =L708*SQRT(365) -> 0.073489452 | N708: =PERCENTILE($K708:K$750,0.05) -> -0.0014856461 | O708: =PERCENTILE(K707:K741, 0.05) -> -0.0021397369 | P708: =-IF(B708<>"",B708/MAX($B708:B$826)-1,"") -> 0.0036592126
A709: 45391 | B709: 11127.648 | C709: =AVERAGE($B709:B$826) -> 10399.898 | D709: =B709-C709 -> 727.75 | E709: =TREND($B709:$B$751,$A709:$A$751,A709) -> 11043.124 | F709: =IF(B709<>"",H709 - 2.6*STDEV(B709:B723),"") -> 10686.957 | H709: =(B709-H710)*0.125+H710 -> 10965.428 | I709: =(B709-I710)*1/3+I710 -> 11096.853 | J709: =IF(B709<>"",H709 + 2.6*STDEV(B709:B723),"") -> 11243.898 | K709: =ln(B709)-ln(B710) -> 0.00060530353 | L709: =SQRT(_xlfn.VAR.S($K709:K$750)) -> 0.003810483 | M709: =L709*SQRT(365) -> 0.072799175 | N709: =PERCENTILE($K709:K$750,0.05) -> -0.0014466324 | O709: =PERCENTILE(K708:K742, 0.05) -> -0.0021397369 | P709: =-IF(B709<>"",B709/MAX($B709:B$826)-1,"") -> 0
... A717: 45383 | B717: 10948.451 | C717: =AVERAGE($B717:B$826) -> 10350.466 | D717: =B717-C717 -> 597.9855 | E717: =TREND($B717:$B$751,$A717:$A$751,A717) -> 10842.306 | F717: =IF(B717<>"",H717 - 2.6*STDEV(B717:B731),"") -> 10379.604 | H717: =(B717-H718)*0.125+H718 -> 10726.518 | I717: =(B717-I718)*1/3+I718 -> 10847.876 | J717: =IF(B717<>"",H717 + 2.6*STDEV(B717:B731),"") -> 11073.432 | K717: =ln(B717)-ln(B718) -> 0.00077989245 | L717: =SQRT(_xlfn.VAR.S($K717:K$750)) -> 0.0040967464 | M717: =L717*SQRT(365) -> 0.078268231 | N717: =PERCENTILE($K717:K$750,0.05) -> -0.00097964638 | O717: =PERCENTILE(K716:K750, 0.05) -> -0.00094072251 | P717: =-IF(B717<>"",B717/MAX($B717:B$826)-1,"") -> 0
A718: 45382 | B718: 10939.916 | C718: =AVERAGE($B718:B$826) -> 10344.98 | D718: =B718-C718 -> 594.93632 | E718: =TREND($B718:$B$751,$A718:$A$751,A718) -> 10820.053 | F718: =IF(B718<>"",H718 - 2.6*STDEV(B718:B732),"") -> 10333.929 | H718: =(B718-H724)*0.125+H724 -> 10694.814 | I718: =(B718-I724)*1/3+I724 -> 10797.588 | J718: =IF(B718<>"",H718 + 2.6*STDEV(B718:B732),"") -> 11055.698 | K718: =ln(B718)-ln(B724) -> 0.012966346 | L718: =SQRT(_xlfn.VAR.S($K718:K$750)) -> 0.0041588514 | M718: =L718*SQRT(365) -> 0.079454744 | N718: =PERCENTILE($K718:K$750,0.05) -> -0.0010185703 | P718: =-IF(B718<>"",B718/MAX($B718:B$826)-1,"") -> 0
A719: 45381 | B719: 10916.427 | C719: =AVERAGE($B719:B$826) -> 10339.471 | D719: =B719-C719 -> 576.95582 | E719: =TREND($B719:$B$751,$A719:$A$751,A719) -> 10796.326 | F719: =IF(B719<>"",H719 - 2.6*STDEV(B719:B733),"") -> 10397.262 | H719: =(B719-H720)*0.125+H720 -> 10764.95 | I719: =(B719-I720)*1/3+I720 -> 10866.08 | J719: =IF(B719<>"",H719 + 2.6*STDEV(B719:B733),"") -> 11132.637 | K719: =ln(B719)-ln(B720) -> 0.0021540458 | L719: =SQRT(_xlfn.VAR.S($K719:K$750)) -> 0.0036613823 | M719: =L719*SQRT(365) -> 0.06995061 | N719: =PERCENTILE($K719:K$750,0.05) -> -0.0010574941 | P719: =-IF(B719<>"",B719/MAX($B719:B$826)-1,"") -> 0
A720: 45380 | B720: 10892.938 | C720: =AVERAGE($B720:B$826) -> 10334.079 | D720: =B720-C720 -> 558.85875 | E720: =TREND($B720:$B$751,$A720:$A$751,A720) -> 10772.797 | F720: =IF(B720<>"",H720 - 2.6*STDEV(B720:B734),"") -> 10405.012 | H720: =(B720-H721)*0.125+H721 -> 10743.31 | I720: =(B720-I721)*1/3+I721 -> 10840.907 | J720: =IF(B720<>"",H720 + 2.6*STDEV(B720:B734),"") -> 11081.607 | K720: =ln(B720)-ln(B721) -> 0.0021586958 | L720: =SQRT(_xlfn.VAR.S($K720:K$750)) -> 0.0037161777 | M720: =L720*SQRT(365) -> 0.070997476 | N720: =PERCENTILE($K720:K$750,0.05) -> -0.001096418 | P720: =-IF(B720<>"",B720/MAX($B720:B$826)-1,"") -> 0
A721: 45379 | B721: 10869.448 | C721: =AVERAGE($B721:B$826) -> 10328.807 | D721: =B721-C721 -> 540.64183 | E721: =TREND($B721:$B$751,$A721:$A$751,A721) -> 10749.504 | F721: =IF(B721<>"",H721 - 2.6*STDEV(B721:B735),"") -> 10413.74 | H721: =(B721-H722)*0.125+H722 -> 10721.934 | I721: =(B721-I722)*1/3+I722 -> 10814.891 | J721: =IF(B721<>"",H721 + 2.6*STDEV(B721:B735),"") -> 11030.129 | K721: =ln(B721)-ln(B722) -> 0.0021633658 | L721: =SQRT(_xlfn.VAR.S($K721:K$750)) -> 0.0037734327 | M721: =L721*SQRT(365) -> 0.072091331 | N721: =PERCENTILE($K721:K$750,0.05) -> -0.0011353419 | P721: =-IF(B721<>"",B721/MAX($B721:B$826)-1,"") -> 0
A722: 45378 | B722: 10845.959 | C722: =AVERAGE($B722:B$826) -> 10323.658 | D722: =B722-C722 -> 522.30162 | E722: =TREND($B722:$B$751,$A722:$A$751,A722) -> 10726.497 | F722: =IF(B722<>"",H722 - 2.6*STDEV(B722:B736),"") -> 10423.548 | H722: =(B722-H723)*0.125+H723 -> 10700.861 | I722: =(B722-I723)*1/3+I723 -> 10787.613 | J722: =IF(B722<>"",H722 + 2.6*STDEV(B722:B736),"") -> 10978.174 | K722: =ln(B722)-ln(B723) -> 0.0021680561 | L722: =SQRT(_xlfn.VAR.S($K722:K$750)) -> 0.0038333334 | M722: =L722*SQRT(365) -> 0.073235731 | N722: =PERCENTILE($K722:K$750,0.05) -> -0.0011742657 | P722: =-IF(B722<>"",B722/MAX($B722:B$826)-1,"") -> 0
A723: 45377 | B723: 10822.47 | C723: =AVERAGE($B723:B$826) -> 10318.636 | D723: =B723-C723 -> 503.83458 | E723: =TREND($B723:$B$751,$A723:$A$751,A723) -> 10703.831 | F723: =IF(B723<>"",H723 - 2.6*STDEV(B723:B737),"") -> 10434.081 | H723: =(B723-H724)*0.125+H724 -> 10680.133 | I723: =(B723-I724)*1/3+I724 -> 10758.44 | J723: =IF(B723<>"",H723 + 2.6*STDEV(B723:B737),"") -> 10926.184 | K723: =ln(B723)-ln(B724) -> 0.0021727668 | L723: =SQRT(_xlfn.VAR.S($K723:K$750)) -> 0.0038960857 | M723: =L723*SQRT(365) -> 0.074434612 | N723: =PERCENTILE($K723:K$750,0.05) -> -0.0012131896 | P723: =-IF(B723<>"",B723/MAX($B723:B$826)-1,"") -> 0
A724: 45376 | B724: 10798.981 | C724: =AVERAGE($B724:B$826) -> 10313.744 | D724: =B724-C724 -> 485.237 | E724: =TREND($B724:$B$751,$A724:$A$751,A724) -> 10681.577 | F724: =IF(B724<>"",H724 - 2.6*STDEV(B724:B738),"") -> 10445.318 | H724: =(B724-H725)*0.125+H725 -> 10659.799 | I724: =(B724-I725)*1/3+I725 -> 10726.424 | J724: =IF(B724<>"",H724 + 2.6*STDEV(B724:B738),"") -> 10874.28 | K724: =ln(B724)-ln(B725) -> 0.0050341622 | L724: =SQRT(_xlfn.VAR.S($K724:K$750)) -> 0.0039619181 | M724: =L724*SQRT(365) -> 0.075692339 | N724: =PERCENTILE($K724:K$750,0.05) -> -0.0012521135 | P724: =-IF(B724<>"",B724/MAX($B724:B$826)-1,"") -> 0
A725: 45375 | B725: 10744.754 | C725: =AVERAGE($B725:B$826) -> 10308.987 | D725: =B725-C725 -> 435.76701 | E725: =TREND($B725:$B$751,$A725:$A$751,A725) -> 10659.82 | F725: =IF(B725<>"",H725 - 2.6*STDEV(B725:B739),"") -> 10456.888 | H725: =(B725-H726)*0.125+H726 -> 10639.916 | I725: =(B725-I726)*1/3+I726 -> 10690.146 | J725: =IF(B725<>"",H725 + 2.6*STDEV(B725:B739),"") -> 10822.943 | K725: =ln(B725)-ln(B726) -> 0.002138989 | L725: =SQRT(_xlfn.VAR.S($K725:K$750)) -> 0.0039486356 | M725: =L725*SQRT(365) -> 0.075438578 | N725: =PERCENTILE($K725:K$750,0.05) -> -0.0012910374 | P725: =B725/MAX($B725:B$826)-1 -> 0
A726: 45374 | B726: 10721.795 | C726: =AVERAGE($B726:B$826) -> 10304.672 | D726: =B726-C726 -> 417.12319 | E726: =TREND($B726:$B$751,$A726:$A$751,A726) -> 10643.393 | F726: =IF(B726<>"",H726 - 2.6*STDEV(B726:B740),"") -> 10460.421 | H726: =(B726-H727)*0.125+H727 -> 10624.939 | I726: =(B726-I727)*1/3+I727 -> 10662.843 | J726: =IF(B726<>"",H726 + 2.6*STDEV(B726:B740),"") -> 10789.457 | K726: =ln(B726)-ln(B727) -> 0.003936817 | L726: =SQRT(_xlfn.VAR.S($K726:K$750)) -> 0.0040184729 | M726: =L726*SQRT(365) -> 0.076772817 | N726: =PERCENTILE($K726:K$750,0.05) -> -0.0013299612 | P726: =B726/MAX($B726:B$826)-1 -> 0
...

Sheet BALANCE
B3: DIAS OPERACIÓN | E3: DEPOSITOS
B4: INICIO | C4: 45274 | E4: INVERSIÓN | F4: =DATOS!C2 -> 26552325 | G4: =F4/$F$6 -> 0.78089734
B5: HOY | C5: =TODAY() -> 46090 | E5: APALANCAMIENTO | F5: =-FVA!K25 -> 7450000 | G5: =F5/$F$6 -> 0.21910266
B6: DIAS | C6: =C5-C4 -> 816 | E6: TOTAL DEPOSITO | F6: =SUM(F4:F5) -> 34002325
E7: =F7-F5 -> 515697.52 | F7: =F4*30% -> 7965697.5 | G7: =F7/SUM(F4+F7) -> 0.23076923
B8: VALOR DE LA UNIDAD | E8: VALORIZACIÓN
B9: VU inicial | C9: 10000 | E9: ACTIVO BRUTO | F9: =FVA!P11 -> 37025616
B10: VU actual | C10: =F12/C18 -> 20664.604 | E10: PASIVOS | F10: =CUENTAS!AC2 -> 8273161.2 | G10: =F10/$F$9 -> 0.22344425
B11: VU futuro (1) | E11: GASTOS | F11: =CUENTAS!AD2 -> 5288.0822 | G11: =F11/$F$9 -> 0.00014282226
B12: max. historico | C12: =MAX(GRAFICO!$B:$B) -> 22081.303 | E12: ACTIVO NETO | F12: =F9-F10-abs(F11) -> 28747167 | G12: =F12/$F$9 -> 0.77641292
B13: hoy | C13: =SUMIF(GRAFICO!$A:$A,TODAY(),GRAFICO!$B:$B) -> 0
B14: % distancia | C14: =C13/C12 -> 0 | E14: DISTRIBUCIÓN DE ACTIVOS
E15: Renta fija | F15: =SUM(CUENTAS!S2:Z2) -> 16120098 | G15: =F15/(SUM($F$15:$F$17)) -> 0.43537691
B16: UNIDADES | E16: Renta variable | F16: =SUM(CUENTAS!G2:R2) -> 17029018 | G16: =F16/(SUM($F$15:$F$17)) -> 0.45992531
B17: U creadas | C17: 10000 | E17: Efectivo | F17: =CUENTAS!AA2 -> 3876499.8 | G17: =F17/(SUM($F$15:$F$17)) -> 0.10469778
B18: U circulantes | C18: =DATOS!D2 -> 1391.1308 | E18: Total | F18: =SUM(F15:F17) -> 37025616 | G18: =ROUND(F9,3)=ROUND(F18,3) -> TRUE
B19: U disponibles | C19: =C17-C18 -> 8608.8692
E20: ACTIVOS LÍQUIDOS VS ACTIVOS ILÍQUIDOS
E21: LÍQUIDOS | F21: =F16+F17+SUMIF(FVA!J:J,"Bitcoin",FVA!L:L) -> 20905518 | G21: =F21/SUM($F$21:$F$22) -> 0.56462309
E22: ILÍQUIDOS | F22: =F18-F21 -> 16120098 | G22: =F22/SUM($F$21:$F$22) -> 0.43537691

Sheet CUENTAS
A1: FECHA | B1: DOLAR | C1: BVC | D1: TES | E1: TES2 | F1: MINEROS | G1: ACTIVO 1 | H1: ACTIVO 2 | I1: ACTIVO 3 | J1: ACTIVO 4 | K1: ACTIVO 5 | L1: ACTIVO 6 | M1: ACTIVO 7 | N1: ACTIVO 8 | O1: ACTIVO 9 | P1: ACTIVO 10 | Q1: ACTIVO 11 | R1: ACTIVO 12 | S1: ACTIVO 13 | T1: ACTIVO 14 | U1: ACTIVO 15 | V1: ACTIVO 16 | W1: ACTIVO 17 | X1: ACTIVO 18 | Y1: ACTIVO 19 | Z1: ACTIVO 20 | AA1: CARTERA | AB1: ACTIVOS | AC1: apalancamiento | AD1: gastos | AE1: A BRUTO | AF1: EFC/ACT
A2: =IFERROR(__xludf.DUMMYFUNCTION("MIN(FILTER(ROW($AG$4:$AG1388),MMULT(N(LEN($G$4:$AG1388)>0), TRANSPOSE(COLUMN($G$4:$AG$4)^0)) = COLUMNS($G$4:$AG1388)))"),13.0) -> 13 | B2: =INDIRECT(ADDRESS($A$2, COLUMN())) | C2: =INDIRECT(ADDRESS($A$2, COLUMN())) | D2: =INDIRECT(ADDRESS($A$2, COLUMN())) | E2: =INDIRECT(ADDRESS($A$2, COLUMN())) | F2: =INDIRECT(ADDRESS($A$2, COLUMN())) | G2: =INDIRECT(ADDRESS($A$2, COLUMN())) -> 2604140 | H2: =INDIRECT(ADDRESS($A$2, COLUMN())) -> 2470500 | I2: =INDIRECT(ADDRESS($A$2, COLUMN())) -> 373680 | ... AG2: =INDIRECT(ADDRESS($A$2, COLUMN())) -> 8278449.3
A3: =A2+1 -> 14 | B3: {=(INDIRECT(ADDRESS($A$2, COLUMN()))-INDIRECT(ADDRESS($A$3, COLUMN())))/INDIRECT(ADDRESS($A$3, COLUMN()))} -> #DIV/0! | G3: =(INDIRECT(ADDRESS($A$2, COLUMN()))-INDIRECT(ADDRESS($A$3, COLUMN())))/INDIRECT(ADDRESS($A$3, COLUMN())) -> 0 | H3: =(INDIRECT(ADDRESS($A$2, COLUMN()))-INDIRECT(ADDRESS($A$3, COLUMN())))/INDIRECT(ADDRESS($A$3, COLUMN())) -> 0 | I3: =(INDIRECT(ADDRESS($A$2, COLUMN()))-INDIRECT(ADDRESS($A$3, COLUMN())))/INDIRECT(ADDRESS($A$3, COLUMN())) -> 0 | J3: =(INDIRECT(ADDRESS($A$2, COLUMN()))-INDIRECT(ADDRESS($A$3, COLUMN())))/INDIRECT(ADDRESS($A$3, COLUMN())) -> 0 | K3: =(INDIRECT(ADDRESS($A$2, COLUMN()))-INDIRECT(ADDRESS($A$3, COLUMN())))/INDIRECT(ADDRESS($A$3, COLUMN())) -> #DIV/0! | L3: =(INDIRECT(ADDRESS($A$2, COLUMN()))-INDIRECT(ADDRESS($A$3, COLUMN())))/INDIRECT(ADDRESS($A$3, COLUMN())) -> 0 | M3: =(INDIRECT(ADDRESS($A$2, COLUMN()))-INDIRECT(ADDRESS($A$3, COLUMN())))/INDIRECT(ADDRESS($A$3, COLUMN())) -> 0 | N3: =(INDIRECT(ADDRESS($A$2, COLUMN()))-INDIRECT(ADDRESS($A$3, COLUMN())))/INDIRECT(ADDRESS($A$3, COLUMN())) -> 0 | ... AG3: =(INDIRECT(ADDRESS($A$2, COLUMN()))-INDIRECT(ADDRESS($A$3, COLUMN())))/INDIRECT(ADDRESS($A$3, COLUMN())) -> -0.0040087102
A4: =A5+1 -> 46098
A5: =A6+1 -> 46097
A6: =A7+1 -> 46096
A7: =A8+1 -> 46095
A8: =A9+1 -> 46094
A9: =A10+1 -> 46093
A10: =A11+1 -> 46092
A11: =A12+1 -> 46091 | AB11: =IF((SUM(C11:AA11)-AC11-abs(AD11))<18000000,,SUM(C11:AA11)-AC11-abs(AD11))
A12: =A13+1 -> 46090 | AB12: =IF((SUM(C12:AA12)-AC12-abs(AD12))<18000000,,SUM(C12:AA12)-AC12-abs(AD12))
A13: =A14+1 -> 46089 | G13: =209*12460 -> 2604140 | H13: =45*54900 -> 2470500 | I13: =6*62280 -> 373680 | J13: =80*41600 -> 3328000 | K13: 0 | L13: =2*67500 -> 135000 | M13: =59*16320 -> 962880 | N13: =124*18960 -> 2351040 | O13: =1*814000 -> 814000 | P13: =5*218000 -> 1090000 | Q13: =493*2425 -> 1195525 | R13: =R14 -> 1704253 | S13: =S14+877.8473 -> 578622.2 | T13: =T14+3860+2122000 -> 5071335 | U13: =U14+0 -> 1344990.1 | V13: =V14*1.0002-40000 -> 3649929.6 | W13: =W14+417 -> 1019085 | X13: =X14+1731.342590164 -> 1139540.2 | Y13: =Y14+2155.77 -> 3032988.4 | Z13: =Z14+608 -> 283608 | AA13: =AA14 -> 3876499.8 | AB13: =IF((SUM(C13:AA13)-AC13-abs(AD13))<18000000,,SUM(C13:AA13)-AC13-abs(AD13)) -> 28747167 | AC13: =AC14+1218.527778+1962 -> 8273161.2 | AD13: =AD14+3500-40000 -> 5288.0822 | AE13: =IF(AB13="",,(AB13+AC13+abs(AD13))) -> 37025616 | AF13: =AA13/AB13 -> 0.13484806 | AG13: =AE13-AB13 -> 8278449.3
A14: =A15+1 -> 46088 | G14: =209*12460 -> 2604140 | H14: =45*54900 -> 2470500 | I14: =6*62280 -> 373680 | J14: =80*41600 -> 3328000 | K14: 0 | L14: =2*67500 -> 135000 | M14: =59*16320 -> 962880 | N14: =124*18960 -> 2351040 | O14: =1*814000 -> 814000 | P14: =5*218000 -> 1090000 | Q14: =493*2425 -> 1195525 | R14: =R15 -> 1704253 | S14: =S15+877.8473 -> 577744.36 | T14: =T15+3860 -> 2945475 | U14: =U15+0 -> 1344990.1 | V14: =V15*1.0002 -> 3689191.8 | W14: =W15+417 -> 1018668 | X14: =X15+1731.342590164 -> 1137808.9 | Y14: =Y15+2155.77 -> 3030832.6 | Z14: =283000 -> 283000 | AA14: =AA15+4000000-283000 -> 3876499.8 | AB14: =IF((SUM(C14:AA14)-AC14-abs(AD14))<18000000,,SUM(C14:AA14)-AC14-abs(AD14)) -> 26621460 | AC14: =AC15+1218.527778+4000000 -> 8269980.7 | AD14: =AD15+3500 -> 41788.082 | AE14: =IF(AB14="",,(AB14+AC14+abs(AD14))) -> 34933228 | AF14: =AA14/AB14 -> 0.1456156 | AG14: =AE14-AB14 -> 8311768.7
A15: =A16+1 -> 46087 | G15: =209*12460 -> 2604140 | H15: =45*54900 -> 2470500 | I15: =6*62280 -> 373680 | J15: =80*41600 -> 3328000 | K15: 0 | L15: =2*67500 -> 135000 | M15: =59*16320 -> 962880 | N15: =124*18960 -> 2351040 | O15: =1*814000 -> 814000 | P15: =5*218000 -> 1090000 | Q15: =493*2425 -> 1195525 | R15: =R16 -> 1704253 | S15: =S16+877.8473 -> 576866.51 | T15: =T16+3860 -> 2941615 | U15: =U16+0 -> 1344990.1 | V15: =V16*1.0002 -> 3688454.1 | W15: =W16+417 -> 1018251 | X15: =X16+1731.342590164 -> 1136077.5 | Y15: =Y16+2155.77 -> 3028676.8 | Z15: 0 | AA15: =AA16 -> 159499.8 | AB15: =IF((SUM(C15:AA15)-AC15-abs(AD15))<18000000,,SUM(C15:AA15)-AC15-abs(AD15)) -> 26616399 | AC15: =AC16+1218.527778 -> 4268762.1 | AD15: =AD16+3500 -> 38288.082 | AE15: =IF(AB15="",,(AB15+AC15+abs(AD15))) -> 30923449 | AF15: =AA15/AB15 -> 0.0059925387 | AG15: =AE15-AB15 -> 4307050.2
A16: =A17+1 -> 46086 | G16: =209*12500 -> 2612500 | H16: =45*56000 -> 2520000 | I16: =6*61500 -> 369000 | J16: =80*41500 -> 3320000 | K16: 0 | L16: =2*67700 -> 135400 | M16: =59*16920 -> 998280 | N16: =124*18980 -> 2353520 | O16: =1*825000 -> 825000 | P16: =5*218000 -> 1090000 | Q16: =493*2370 -> 1168410 | R16: =R17 -> 1704253 | S16: =S17+877.8473 -> 575988.66 | T16: =T17+3860 -> 2937755 | U16: =U17+0 -> 1344990.1 | V16: =V17*1.0002 -> 3687716.5 | W16: =W17+417 -> 1017834 | X16: =X17+1731.342590164 -> 1134346.2 | Y16: =Y17+2155.77 -> 3026521.1 | Z16: 0 | AA16: =AA17 -> 159499.8 | AB16: =IF((SUM(C16:AA16)-AC16-abs(AD16))<18000000,,SUM(C16:AA16)-AC16-abs(AD16)) -> 26678683 | AC16: =AC17+1218.527778 -> 4267543.6 | AD16: =AD17+3500 -> 34788.082 | AE16: =IF(AB16="",,(AB16+AC16+abs(AD16))) -> 30981014 | AF16: =AA16/AB16 -> 0.0059785486 | AG16: =AE16-AB16 -> 4302331.7
A17: =A18+1 -> 46085 | G17: =209*12480 -> 2608320 | H17: =45*56660 -> 2549700 | I17: =6*63000 -> 378000 | J17: =80*41520 -> 3321600 | K17: 0 | L17: =2*65260 -> 130520 | M17: =59*17200 -> 1014800 | N17: =124*19420 -> 2408080 | O17: =1*812500 -> 812500 | P17: =5*221000 -> 1105000 | Q17: =493*2180 -> 1074740 | R17: =R18 -> 1704253 | S17: =S18+877.8473 -> 575110.82 | T17: =T18+3860 -> 2933895 | U17: =U18+0 -> 1344990.1 | V17: =V18*1.0002 -> 3686979.2 | W17: =W18+417 -> 1017417 | X17: =X18+1731.342590164 -> 1132614.9 | Y17: =Y18+2155.77 -> 3024365.3 | Z17: 0 | AA17: =AA18 -> 159499.8 | AB17: =IF((SUM(C17:AA17)-AC17-abs(AD17))<18000000,,SUM(C17:AA17)-AC17-abs(AD17)) -> 26684772 | AC17: =AC18+1218.527778 -> 4266325.1 | AD17: =AD18+3500 -> 31288.082 | AE17: =IF(AB17="",,(AB17+AC17+abs(AD17))) -> 30982385 | AF17: =AA17/AB17 -> 0.0059771843 | AG17: =AE17-AB17 -> 4297613.2
A18: =A19+1 -> 46084 | G18: =209*12500 -> 2612500 | H18: =45*56200 -> 2529000 | I18: =6*62800 -> 376800 | J18: =80*41500 -> 3320000 | K18: 0 | L18: =2*64900 -> 129800 | M18: =59*17940 -> 1058460 | N18: =124*19200 -> 2380800 | O18: =1*794000 -> 794000 | P18: =5*223780 -> 1118900 | Q18: =493*2215 -> 1091995 | R18: =R19-15402 -> 1704253 | S18: =S19+877.8473 -> 574232.97 | T18: =T19+3860 -> 2930035 | U18: =U19+0 -> 1344990.1 | V18: =V19*1.0002 -> 3686241.9 | W18: =W19+417 -> 1017000 | X18: =X19+1731.342590164 -> 1130883.5 | Y18: =Y19+2155.77 -> 3022209.5 | Z18: 0 | AA18: =AA19+50000+60000 -> 159499.8 | AB18: =IF((SUM(C18:AA18)-AC18-abs(AD18))<18000000,,SUM(C18:AA18)-AC18-abs(AD18)) -> 26688706 | AC18: =AC19+1218.527778 -> 4265106.6 | AD18: =AD19+3500 -> 27788.082 | AE18: =IF(AB18="",,(AB18+AC18+abs(AD18))) -> 30981601 | AF18: =AA18/AB18 -> 0.0059763032 | AG18: =AE18-AB18 -> 4292894.6
A19: =A20+1 -> 46083 | G19: =209*12380 -> 2587420 | H19: =45*56880 -> 2559600 | I19: =6*66260 -> 397560 | J19: =80*42020 -> 3361600 | K19: 0 | L19: =2*67500 -> 135000 | M19: =59*17000 -> 1003000 | N19: =124*19040 -> 2360960 | O19: =1*765200 -> 765200 | P19: =5*228680 -> 1143400 | Q19: =493*2280 -> 1124040 | R19: =R20-15402 -> 1719655 | S19: =S20+877.8473 -> 573355.12 | T19: =T20+3860 -> 2926175 | U19: =U20+0 -> 1344990.1 | V19: =V20*1.0002 -> 3685504.8 | W19: =W20+417 -> 1016583 | X19: =X20+1731.342590164 -> 1129152.2 | Y19: =Y20+2155.77 -> 3020053.8 | AA19: =AA20-33*54900 -> 49499.8 | AB19: =IF((SUM(C19:AA19)-AC19-abs(AD19))<18000000,,SUM(C19:AA19)-AC19-abs(AD19)) -> 26614573 | AC19: =AC20+1218.527778 -> 4263888 | AD19: =AD20+3500 -> 24288.082 | AE19: =IF(AB19="",,(AB19+AC19+abs(AD19))) -> 30902749 | AF19: =AA19/AB19 -> 0.0018598758 | AG19: =AE19-AB19 -> 4288176.1
A20: =A21+1 -> 46082 | G20: =209*13300 -> 2779700 | H20: =12*56780 -> 681360 | I20: =6*63620 -> 381720 | J20: =80*46000 -> 3680000 | K20: 0 | L20: =2*67940 -> 135880 | M20: =59*17200 -> 1014800 | N20: =124*19860 -> 2462640 | O20: =1*783000 -> 783000 | P20: =5*232000 -> 1160000 | Q20: =493*2240 -> 1104320 | R20: =R21-15402 -> 1735057 | S20: =S21+877.8473 -> 572477.27 | T20: =T21+3860 -> 2922315 | U20: =U21+0 -> 1344990.1 | V20: =V21*1.0002 -> 3684767.8 | W20: =W21+417 -> 1016166 | X20: =X21+1731.342590164 -> 1127420.8 | Y20: =Y21+2155.77 -> 3017898 | AA20: =AA21 -> 1861199.8 | AB20: =IF((SUM(C20:AA20)-AC20-abs(AD20))<18000000,,SUM(C20:AA20)-AC20-abs(AD20)) -> 27182254 | AC20: =AC21+1218.527778 -> 4262669.5 | AD20: =AD21+3500 -> 20788.082 | AE20: =IF(AB20="",,(AB20+AC20+abs(AD20))) -> 31465712 | AF20: =AA20/AB20 -> 0.068471135 | AG20: =AE20-AB20 -> 4283457.6
A21: =A22+1 -> 46081 | G21: =209*13300 -> 2779700 | H21: =12*56780 -> 681360 | I21: =6*63620 -> 381720 | J21: =80*46000 -> 3680000 | K21: 0 | L21: =2*67940 -> 135880 | M21: =59*17200 -> 1014800 | N21: =124*19860 -> 2462640 | O21: =1*783000 -> 783000 | P21: =5*232000 -> 1160000 | Q21: =493*2240 -> 1104320 | R21: =R22-15402 -> 1750459 | S21: =S22+877.8473 -> 571599.43 | T21: =T22+3860 -> 2918455 | U21: =U22+0 -> 1344990.1 | V21: =V22*1.0002 -> 3684031 | W21: =W22+417 -> 1015749 | X21: =X22+1731.342590164 -> 1125689.5 | Y21: =Y22+2155.77 -> 3015742.2 | AA21: =AA22 -> 1861199.8 | AB21: =IF((SUM(C21:AA21)-AC21-abs(AD21))<18000000,,SUM(C21:AA21)-AC21-abs(AD21)) -> 27192596 | AC21: =AC22+1218.527778 -> 4261451 | AD21: =AD22+3500 -> 17288.082 | AE21: =IF(AB21="",,(AB21+AC21+abs(AD21))) -> 31471335 | AF21: =AA21/AB21 -> 0.068445094 | AG21: =AE21-AB21 -> 4278739.1
A22: =A23+1 -> 46080 | G22: =209*13300 -> 2779700 | H22: =12*56780 -> 681360 | I22: =6*63620 -> 381720 | J22: =80*46000 -> 3680000 | K22: =66*28200*0 -> 0 | L22: =2*67940 -> 135880 | M22: =59*17200 -> 1014800 | N22: =124*19860 -> 2462640 | O22: =1*783000 -> 783000 | P22: =5*232000 -> 1160000 | Q22: =493*2240 -> 1104320 | R22: =R23-15402 -> 1765861 | S22: =S23+877.8473 -> 570721.58 | T22: =T23+3860 -> 2914595 | U22: =U23+0 -> 1344990.1 | V22: =V23*1.0002 -> 3683294.4 | W22: =W23+417 -> 1015332 | X22: =X23+1731.342590164 -> 1123958.1 | Y22: =Y23+2155.77 -> 3013586.4 | AA22: =AA23+1861200 -> 1861199.8 | AB22: =IF((SUM(C22:AA22)-AC22-abs(AD22))<18000000,,SUM(C22:AA22)-AC22-abs(AD22)) -> 27202938 | AC22: =AC23+1218.527778 -> 4260232.4 | AD22: =AD23+3500 -> 13788.082 | AE22: =IF(AB22="",,(AB22+AC22+abs(AD22))) -> 31476958 | AF22: =AA22/AB22 -> 0.068419073 | AG22: =AE22-AB22 -> 4274020.5
A23: =A24+1 -> 46079 | G23: =209*13160 -> 2750440 | H23: =12*57000 -> 684000 | I23: =6*65200 -> 391200 | J23: =80*49720 -> 3977600 | K23: =66*29000 -> 1914000 | L23: =2*72500 -> 145000 | M23: =59*17460 -> 1030140 | N23: =124*19860 -> 2462640 | O23: =1*783000 -> 783000 | P23: =5*234160 -> 1170800 | Q23: =493*2250 -> 1109250 | R23: =R24-15402 -> 1781263 | S23: =S24+877.8473 -> 569843.73 | T23: =T24+3860 -> 2910735 | U23: =U24+0 -> 1344990.1 | V23: =V24*1.0002 -> 3682557.9 | W23: =W24+417 -> 1014915 | X23: =X24+1731.342590164 -> 1122226.8 | Y23: =Y24+2155.77 -> 3011430.7 | AA23: =AA24 -> -0.2 | AB23: =IF((SUM(C23:AA23)-AC23-abs(AD23))<18000000,,SUM(C23:AA23)-AC23-abs(AD23)) -> 27586730 | AC23: =AC24+1218.527778 -> 4259013.9 | AD23: =AD24+3500 -> 10288.082 | AE23: =IF(AB23="",,(AB23+AC23+abs(AD23))) -> 31856032 | AF23: =AA23/AB23 -> -7.2498625e-09 | AG23: =AE23-AB23 -> 4269302
A24: =A25+1 -> 46078 | G24: =209*13500 -> 2821500 | H24: =12*61160 -> 733920 | I24: =6*68700 -> 412200 | J24: =80*52420 -> 4193600 | K24: =66*28880 -> 1906080 | L24: =2*72720 -> 145440 | M24: =59*18600 -> 1097400 | N24: =124*19980 -> 2477520 | O24: =1*780000 -> 780000 | P24: =5*231100 -> 1155500 | Q24: =493*2330 -> 1148690 | R24: =R25-15402 -> 1796665 | S24: =S25+877.8473 -> 568965.88 | T24: =T25+3860 -> 2906875 | U24: =U25+0 -> 1344990.1 | V24: =V25*1.0002 -> 3681821.5 | W24: =W25+417 -> 1014498 | X24: =X25+1731.342590164 -> 1120495.5 | Y24: =Y25+2155.77 -> 3009274.9 | AA24: =AA25 -> -0.2 | AB24: =IF((SUM(C24:AA24)-AC24-abs(AD24))<18000000,,SUM(C24:AA24)-AC24-abs(AD24)) -> 28050852 | AC24: =AC25+1218.527778 -> 4257795.4 | AD24: =AD25+3500 -> 6788.0822 | AE24: =IF(AB24="",,(AB24+AC24+abs(AD24))) -> 32315436 | AF24: =AA24/AB24 -> -7.1299082e-09 | AG24: =AE24-AB24 -> 4264583.5
A25: =A26+1 -> 46077 | G25: =209*13580 -> 2838220 | H25: =12*61300 -> 735600 | I25: =6*70760 -> 424560 | J25: =80*52300 -> 4184000 | K25: =66*28780 -> 1899480 | L25: =2*72940 -> 145880 | M25: =59*18900 -> 1115100 | N25: =124*19700 -> 2442800 | O25: =1*775000 -> 775000 | P25: =5*233120 -> 1165600 | Q25: =493*2300 -> 1133900 | R25: =R26-15402 -> 1812067 | S25: =S26+877.8473 -> 568088.04 | T25: =T26+3860 -> 2903015 | U25: =U26+0 -> 1344990.1 | V25: =V26*1.0002 -> 3681085.3 | W25: =W26+417 -> 1014081 | X25: =X26+1731.342590164 -> 1118764.1 | Y25: =Y26+2155.77 -> 3007119.1 | AA25: =AA26 -> -0.2 | AB25: =IF((SUM(C25:AA25)-AC25-abs(AD25))<18000000,,SUM(C25:AA25)-AC25-abs(AD25)) -> 28049485 | AC25: =AC26+1218.527778 -> 4256576.9 | AD25: =AD26+3500 -> 3288.0822 | AE25: =IF(AB25="",,(AB25+AC25+abs(AD25))) -> 32309349 | AF25: =AA25/AB25 -> -7.1302558e-09 | AG25: =AE25-AB25 -> 4259864.9
A26: =A27+1 -> 46076 | G26: =209*13880 -> 2900920 | H26: =12*59900 -> 718800 | I26: =6*75000 -> 450000 | J26: =80*50800 -> 4064000 | K26: =66*28800 -> 1900800 | L26: =2*73200 -> 146400 | M26: =59*18800 -> 1109200 | N26: =124*19780 -> 2452720 | O26: =1*752100 -> 752100 | P26: =5*230040 -> 1150200 | Q26: =493*2330 -> 1148690 | R26: =R27-15402 -> 1827469 | S26: =S27+877.8473 -> 567210.19 | T26: =T27+3860 -> 2899155 | U26: =U27+0 -> 1344990.1 | V26: =V27*1.0002-83276 -> 3680349.2 | W26: =W27+427 -> 1013664 | X26: =X27+1731.342590164 -> 1117032.8 | Y26: =Y27+735+597.83-197090+662000 -> 3004963.4 | AA26: =AA27+200000-662000+83276 -> -0.2 | AB26: =IF((SUM(C26:AA26)-AC26-abs(AD26))<18000000,,SUM(C26:AA26)-AC26-abs(AD26)) -> 27993093 | AC26: =AC27+1218.527778 -> 4255358.3 | AD26: =AD27+2400+5000 -> -211.91777 | AE26: =IF(AB26="",,(AB26+AC26+abs(AD26))) -> 32248663 | AF26: =AA26/AB26 -> -7.1446195e-09 | AG26: =AE26-AB26 -> 4255570.3
A27: =A28+1 -> 46075 | B27: 0 | G27: =209*13900 -> 2905100 | H27: =12*64800 -> 777600 | I27: =6*74300 -> 445800 | J27: =80*52740 -> 4219200 | K27: =66*27400 -> 1808400 | L27: =2*72500 -> 145000 | M27: =59*19200 -> 1132800 | N27: =124*19580 -> 2427920 | O27: =1*772060 -> 772060 | P27: =5*242500 -> 1212500 | Q27: =493*2305 -> 1136365 | R27: =R28-15402 -> 1842871 | S27: =S28+1177.8473-200000 -> 566332.34 | T27: =T28+3860 -> 2895295 | U27: =U28+0 -> 1344990.1 | V27: =V28*1.0002 -> 3762872.6 | W27: =W28+427 -> 1013237 | X27: =X28+1731.342590164 -> 1115301.4 | Y27: =Y28+735+597.83 -> 2538720.5 | AA27: =AA28+200000 -> 378723.8 | AB27: =IF((SUM(C27:AA27)-AC27-abs(AD27))<18000000,,SUM(C27:AA27)-AC27-abs(AD27)) -> 28179337 | AC27: =AC28+1218.527778 -> 4254139.8 | AD27: =AD28+2400 -> -7611.9178 | AE27: =IF(AB27="",,(AB27+AC27+abs(AD27))) -> 32441089 | AF27: =AA27/AB27 -> 0.01343977 | AG27: =AE27-AB27 -> 4261751.7
A28: =A29+1 -> 46074 | B28: 0 | G28: =209*13900 -> 2905100 | H28: =12*64800 -> 777600 | I28: =6*74300 -> 445800 | J28: =80*52740 -> 4219200 | K28: =66*27400 -> 1808400 | L28: =2*72500 -> 145000 | M28: =59*19200 -> 1132800 | N28: =124*19580 -> 2427920 | O28: =1*772060 -> 772060 | P28: =5*242500 -> 1212500 | Q28: =493*2305 -> 1136365 | R28: =R29-15402 -> 1858273 | S28: =S29+1177.8473 -> 765154.5 | T28: =T29+3860 -> 2891435 | U28: =U29+0 -> 1344990.1 | V28: =V29*1.0002 -> 3762120.2 | W28: =W29+427 -> 1012810 | X28: =X29+1731.342590164 -> 1113570.1 | Y28: =Y29+735+597.83 -> 2537387.7 | AA28: =AA29 -> 178723.8 | AB28: =IF((SUM(C28:AA28)-AC28-abs(AD28))<18000000,,SUM(C28:AA28)-AC28-abs(AD28)) -> 28184276 | AC28: =AC29+1218.527778 -> 4252921.3 | AD28: =AD29+2400 -> -10011.918 | AE28: =IF(AB28="",,(AB28+AC28+abs(AD28))) -> 32447209 | AF28: =AA28/AB28 -> 0.0063412592 | AG28: =AE28-AB28 -> 4262933.2
A29: =A30+1 -> 46073 | B29: 0 | G29: =209*13900 -> 2905100 | H29: =12*64800 -> 777600 | I29: =6*74300 -> 445800 | J29: =80*52740 -> 4219200 | K29: =66*27400 -> 1808400 | L29: =2*72500 -> 145000 | M29: =59*19200 -> 1132800 | N29: =124*19580 -> 2427920 | O29: =1*772060 -> 772060 | P29: =5*242500 -> 1212500 | Q29: =493*2305 -> 1136365 | R29: =R30-15402 -> 1873675 | S29: =S30+1177.8473 -> 763976.65 | T29: =T30+3860 -> 2887575 | U29: =U30+0 -> 1344990.1 | V29: =V30*1.0002 -> 3761367.9 | W29: =W30+427 -> 1012383 | X29: =X30+1731.342590164 -> 1111838.8 | Y29: =Y30+735+597.83 -> 2536054.9 | AA29: =AA30-1136365 -> 178723.8 | AB29: =IF((SUM(C29:AA29)-AC29-abs(AD29))<18000000,,SUM(C29:AA29)-AC29-abs(AD29)) -> 28189215 | AC29: =AC30+1218.527778 -> 4251702.8 | AD29: =AD30+2400 -> -12411.918 | AE29: =IF(AB29="",,(AB29+AC29+abs(AD29))) -> 32453330 | AF29: =AA29/AB29 -> 0.0063401481 | AG29: =AE29-AB29 -> 4264114.7
A30: =A31+1 -> 46072 | B30: 0 | G30: =209*13900 -> 2905100 | H30: =12*61500 -> 738000 | I30: =6*73280 -> 439680 | J30: =80*52360 -> 4188800 | K30: =66*27900 -> 1841400 | L30: =2*73660 -> 147320 | M30: =59*19000 -> 1121000 | N30: =124*19180 -> 2378320 | O30: =1*759000 -> 759000 | P30: =5*228520 -> 1142600 | Q30: =0 -> 0 | R30: =R31-15402 -> 1889077 | S30: =S31+1177.8473 -> 762798.8 | T30: =T31+3860 -> 2883715 | U30: =U31+0 -> 1344990.1 | V30: =V31*1.0002 -> 3760615.8 | W30: =W31+427 -> 1011956 | X30: =X31+1731.342590164 -> 1110107.4 | Y30: =Y31+735+597.83 -> 2534722 | AA30: =AA31+21*52360 -> 1315088.8 | AB30: =IF((SUM(C30:AA30)-AC30-abs(AD30))<18000000,,SUM(C30:AA30)-AC30-abs(AD30)) -> 28008995 | AC30: =AC31+1218.527778 -> 4250484.2 | AD30: =AD31+2400 -> -14811.918 | AE30: =IF(AB30="",,(AB30+AC30+abs(AD30))) -> 32274291 | AF30: =AA30/AB30 -> 0.046952374 | AG30: =AE30-AB30 -> 4265296.1
A31: =A32+1 -> 46071 | B31: 0 | G31: =209*13900 -> 2905100 | H31: =12*61500 -> 738000 | I31: =6*71580 -> 429480 | J31: =101*51660 -> 5217660 | K31: =66*26940 -> 1778040 | L31: =2*73580 -> 147160 | M31: =59*18800 -> 1109200 | N31: =124*19040 -> 2360960 | O31: =1*733000 -> 733000 | P31: =5*228520 -> 1142600 | Q31: =0 -> 0 | R31: =R32-15402+60000 -> 1904479 | S31: =S32+1177.8473 -> 761620.95 | T31: =T32+3860 -> 2879855 | U31: =U32+0 -> 1344990.1 | V31: =V32*1.0002 -> 3759863.9 | W31: =W32+427 -> 1011529 | X31: =X32+1731.342590164 -> 1108376.1 | Y31: =Y32+735+597.83 -> 2533389.2 | AA31: =AA32 -> 215528.8 | AB31: =IF((SUM(C31:AA31)-AC31-abs(AD31))<18000000,,SUM(C31:AA31)-AC31-abs(AD31)) -> 27814354 | AC31: =AC32+1218.527778 -> 4249265.7 | AD31: =AD32+2400 -> -17211.918 | AE31: =IF(AB31="",,(AB31+AC31+abs(AD31))) -> 32080832 | AF31: =AA31/AB31 -> 0.0077488335 | AG31: =AE31-AB31 -> 4266477.6
A32: =A33+1 -> 46070 | B32: 0 | G32: =209*13740 -> 2871660 | H32: =12*61500 -> 738000 | I32: =6*71300 -> 427800 | J32: =101*51660 -> 5217660 | K32: =66*27360 -> 1805760 | L32: =2*73600 -> 147200 | M32: =59*18520 -> 1092680 | N32: =124*19000 -> 2356000 | O32: =1*733000 -> 733000 | P32: =5*228520 -> 1142600 | Q32: =0 -> 0 | R32: =R33-15402 -> 1859881 | S32: =S33+1177.8473 -> 760443.11 | T32: =T33+2860 -> 2875995 | U32: =U33+0 -> 1344990.1 | V32: =V33*1.0002 -> 3759112 | W32: =W33+427 -> 1011102 | X32: =X33+1731.342590164 -> 1106644.7 | Y32: =Y33+735+597.83 -> 2532056.4 | AA32: =AA33+90000 -> 215528.8 | AB32: =IF((SUM(C32:AA32)-AC32-abs(AD32))<18000000,,SUM(C32:AA32)-AC32-abs(AD32)) -> 27730454 | AC32: =AC33+1218.527778 -> 4248047.2 | AD32: =AD33+2400 -> -19611.918 | AE32: =IF(AB32="",,(AB32+AC32+abs(AD32))) -> 31998113 | AF32: =AA32/AB32 -> 0.0077722781 | AG32: =AE32-AB32 -> 4267659.1
A33: =A34+1 -> 46069 | B33: 0 | G33: =209*13960 -> 2917640 | H33: =12*61500 -> 738000 | I33: =6*70460 -> 422760 | J33: =101*51520 -> 5203520 | K33: =66*27460 -> 1812360 | L33: =2*72400 -> 144800 | M33: =59*18420 -> 1086780 | N33: =124*18700 -> 2318800 | O33: =1*733000 -> 733000 | P33: =5*228520 -> 1142600 | Q33: =0 -> 0 | R33: =R34-15402 -> 1875283 | S33: =S34+1177.8473 -> 759265.26 | T33: =T34+2860 -> 2873135 | U33: =U34+0 -> 1344990.1 | V33: =V34*1.0002 -> 3758360.4 | W33: =W34+427 -> 1010675 | X33: =X34+1731.342590164 -> 1104913.4 | Y33: =Y34+735+597.83 -> 2530723.5 | AA33: =AA34-6*70900+250000 -> 125528.8 | AB33: =IF((SUM(C33:AA33)-AC33-abs(AD33))<18000000,,SUM(C33:AA33)-AC33-abs(AD33)) -> 27634294 | AC33: =AC34+1218.527778 -> 4246828.6 | AD33: =AD34+2400 -> -22011.918 | AE33: =IF(AB33="",,(AB33+AC33+abs(AD33))) -> 31903134 | AF33: =AA33/AB33 -> 0.0045425007 | AG33: =AE33-AB33 -> 4268840.6
A34: =A35+1 -> 46068 | B34: 0 | G34: =209*13940 -> 2913460 | H34: =12*61500 -> 738000 | I34: 0 | J34: =101*51400 -> 5191400 | K34: =66*28100 -> 1854600 | L34: =2*73960 -> 147920 | M34: =59*18500 -> 1091500 | N34: =124*19100 -> 2368400 | O34: =1*733000 -> 733000 | P34: =5*228520 -> 1142600 | Q34: =0 -> 0 | R34: =R35-15402 -> 1890685 | S34: =S35+1177.8473 -> 758087.41 | T34: =T35+2860 -> 2870275 | U34: =U35+0 -> 1344990.1 | V34: =V35*1.0002 -> 3757608.8 | W34: =W35+427 -> 1010248 | X34: =X35+1731.342590164 -> 1103182 | Y34: =Y35+735+597.83 -> 2529390.7 | AA34: =AA35+104250-203044+11687 -> 300928.8 | AB34: =IF((SUM(C34:AA34)-AC34-abs(AD34))<18000000,,SUM(C34:AA34)-AC34-abs(AD34)) -> 27476254 | AC34: =AC35+1618.527778 -> 4245610.1 | AD34: =AD35+2400 -> -24411.918 | AE34: =IF(AB34="",,(AB34+AC34+abs(AD34))) -> 31746276 | AF34: =AA34/AB34 -> 0.010952323 | AG34: =AE34-AB34 -> 4270022
A35: =A36+1 -> 46067 | B35: 0 | G35: =209*13940 -> 2913460 | H35: =12*61500 -> 738000 | I35: 0 | J35: =101*51400 -> 5191400 | K35: =66*28100 -> 1854600 | L35: =2*73960 -> 147920 | M35: =59*18500 -> 1091500 | N35: =124*19100 -> 2368400 | O35: =1*733000 -> 733000 | P35: =5*228520 -> 1142600 | Q35: =0 -> 0 | R35: =R36-15402 -> 1906087 | S35: =S36+1177.8473 -> 756909.56 | T35: =T36+2860 -> 2867415 | U35: =U36+0 -> 1344990.1 | V35: =V36*1.0002 -> 3756857.5 | W35: =W36+427 -> 1009821 | X35: =X36+1731.342590164 -> 1101450.7 | Y35: =Y36+735+597.83 -> 2528057.9 | AA35: =AA36+367393 -> 388035.8 | AB35: =IF((SUM(C35:AA35)-AC35-abs(AD35))<18000000,,SUM(C35:AA35)-AC35-abs(AD35)) -> 27569701 | AC35: =AC36+1618.527778 -> 4243991.6 | AD35: =AD36+2400 -> -26811.918 | AE35: =IF(AB35="",,(AB35+AC35+abs(AD35))) -> 31840504 | AF35: =AA35/AB35 -> 0.014074719 | AG35: =AE35-AB35 -> 4270803.5
A36: =A37+1 -> 46066 | B36: =101.56*3620 -> 367647.2 | G36: =209*13940 -> 2913460 | H36: =12*61500 -> 738000 | I36: 0 | J36: =101*51400 -> 5191400 | K36: =66*28100 -> 1854600 | L36: =2*73960 -> 147920 | M36: =59*18500 -> 1091500 | N36: =124*19100 -> 2368400 | O36: =1*733000 -> 733000 | P36: =5*228520 -> 1142600 | Q36: =0 -> 0 | R36: =R37-15402 -> 1921489 | S36: =S37+1177.8473 -> 755731.72 | T36: =T37+2860 -> 2864555 | U36: =U37+0 -> 1344990.1 | V36: =V37*1.0002 -> 3756106.2 | W36: =W37+427 -> 1009394 | X36: =X37+1731.342590164 -> 1099719.4 | Y36: =Y37+735+597.83 -> 2526725.1 | AA36: =AA37 -> 20642.8 | AB36: =IF((SUM(C36:AA36)-AC36-abs(AD36))<18000000,,SUM(C36:AA36)-AC36-abs(AD36)) -> 27208648 | AC36: =AC37+1618.527778 -> 4242373.1 | AD36: =AD37+2400 -> -29211.918 | AE36: =IF(AB36="",,(AB36+AC36+abs(AD36))) -> 31480233 | AF36: =AA36/AB36 -> 0.00075868525 | AG36: =AE36-AB36 -> 4271585
A37: =A38+1 -> 46065 | B37: =101.56*3620 -> 367647.2 | G37: =209*13900 -> 2905100 | H37: =12*62600 -> 751200 | I37: 0 | J37: =101*49500 -> 4999500 | K37: =66*28100 -> 1854600 | L37: =2*73400 -> 146800 | M37: =59*18500 -> 1091500 | N37: =124*19420 -> 2408080 | O37: =1*730000 -> 730000 | P37: =5*229840 -> 1149200 | Q37: =0 -> 0 | R37: =R38-15402 -> 1936891 | S37: =S38+1177.8473 -> 754553.87 | T37: =T38+2860 -> 2861695 | U37: =U38+0 -> 1344990.1 | V37: =V38*1.0002 -> 3755355.2 | W37: =W38+427 -> 1008967 | X37: =X38+1731.342590164 -> 1097988 | Y37: =Y38+735+597.83 -> 2525392.2 | AA37: =AA38 -> 20642.8 | AB37: =IF((SUM(C37:AA37)-AC37-abs(AD37))<18000000,,SUM(C37:AA37)-AC37-abs(AD37)) -> 27070089 | AC37: =AC38+1618.527778 -> 4240754.5 | AD37: =AD38+2400 -> -31611.918 | AE37: =IF(AB37="",,(AB37+AC37+abs(AD37))) -> 31342455 | AF37: =AA37/AB37 -> 0.00076256861 | AG37: =AE37-AB37 -> 4272366.4
A38: =A39+1 -> 46064 | B38: =101.56*3620 -> 367647.2 | G38: =209*13980 -> 2921820 | H38: =12*64040 -> 768480 | I38: 0 | J38: =101*49480 -> 4997480 | K38: =66*28100 -> 1854600 | L38: =2*73000 -> 146000 | M38: =59*19320 -> 1139880 | N38: =124*19940 -> 2472560 | O38: =1*748800 -> 748800 | P38: =5*233940 -> 1169700 | Q38: =0 -> 0 | R38: =R39-15402 -> 1952293 | S38: =S39+1177.8473 -> 753376.02 | T38: =T39+2860 -> 2858835 | U38: =U39+0 -> 1344990.1 | V38: =V39*1.0002 -> 3754604.3 | W38: =W39+427 -> 1008540 | X38: =X39+1731.342590164 -> 1096256.7 | Y38: =Y39+735+597.83 -> 2524059.4 | AA38: =AA39-48200*21+440760 -> 20642.8 | AB38: =IF((SUM(C38:AA38)-AC38-abs(AD38))<18000000,,SUM(C38:AA38)-AC38-abs(AD38)) -> 27259769 | AC38: =AC39+1618.527778 -> 4239136 | AD38: =AD39+2400 -> -34011.918 | AE38: =IF(AB38="",,(AB38+AC38+abs(AD38))) -> 31532917 | AF38: =AA38/AB38 -> 0.00075726246 | AG38: =AE38-AB38 -> 4273147.9
A39: =A40+1 -> 46063 | B39: =101.56*3620 -> 367647.2 | G39: =209*14380 -> 3005420 | H39: =12*64240 -> 770880 | I39: =6*73460 -> 440760 | J39: =80*51520 -> 4121600 | K39: =66*28100 -> 1854600 | L39: =2*73700 -> 147400 | M39: =59*19780 -> 1167020 | N39: =124*19960 -> 2475040 | O39: =1*763040 -> 763040 | P39: =5*230260 -> 1151300 | Q39: =0 -> 0 | R39: =R40-15402 -> 1967695 | S39: =S40+1177.8473 -> 752198.18 | T39: =T40+2860 -> 2855975 | U39: =U40+0 -> 1344990.1 | V39: =V40*1.0002 -> 3753853.5 | W39: =W40+427 -> 1008113 | X39: =X40+1731.342590164 -> 1094525.3 | Y39: =Y40+735+597.83 -> 2522726.6 | AA39: =AA40 -> 592082.8 | AB39: =IF((SUM(C39:AA39)-AC39-abs(AD39))<18000000,,SUM(C39:AA39)-AC39-abs(AD39)) -> 27515290 | AC39: =AC40+1618.527778 -> 4237517.5 | AD39: =AD40+2400 -> -36411.918 | AE39: =IF(AB39="",,(AB39+AC39+abs(AD39))) -> 31789219 | AF39: =AA39/AB39 -> 0.021518319 | AG39: =AE39-AB39 -> 4273929.4
A40: =A41+1 -> 46062 | B40: =101.56*3620 -> 367647.2 | G40: =209*14360 -> 3001240 | H40: =12*64900 -> 778800 | I40: =6*73300 -> 439800 | J40: =80*51700 -> 4136000 | K40: =66*28100 -> 1854600 | L40: =2*73120 -> 146240 | M40: =59*19740 -> 1164660 | N40: =124*19680 -> 2440320 | O40: =1*770980 -> 770980 | P40: =5*229500 -> 1147500 | Q40: =0 -> 0 | R40: =R41-15402 -> 1983097 | S40: =S41+1177.8473 -> 751020.33 | T40: =T41+2860 -> 2853115 | U40: =U41+0 -> 1344990.1 | V40: =V41*1.0002 -> 3753102.9 | W40: =W41+427 -> 1007686 | X40: =X41+1731.342590164 -> 1092794 | Y40: =Y41+735+597.83 -> 2521393.7 | AA40: =AA41 -> 592082.8 | AB40: =IF((SUM(C40:AA40)-AC40-abs(AD40))<18000000,,SUM(C40:AA40)-AC40-abs(AD40)) -> 27504711 | AC40: =AC41+1618.527778 -> 4235898.9 | AD40: =AD41+2400 -> -38811.918 | AE40: =IF(AB40="",,(AB40+AC40+abs(AD40))) -> 31779422 | AF40: =AA40/AB40 -> 0.021526596 | AG40: =AE40-AB40 -> 4274710.9
A41: =A42+1 -> 46061 | B41: =101.56*3620 -> 367647.2 | G41: =209*14200 -> 2967800 | H41: =12*63500 -> 762000 | I41: =6*72400 -> 434400 | J41: =80*51200 -> 4096000 | K41: =66*28100 -> 1854600 | L41: =2*72640 -> 145280 | M41: =59*19800 -> 1168200 | N41: =124*19200 -> 2380800 | O41: =1*769100 -> 769100 | P41: =5*231020 -> 1155100 | Q41: =0 -> 0 | R41: =R42-15402 -> 1998499 | S41: =S42+1177.8473 -> 749842.48 | T41: =T42+2860 -> 2850255 | U41: =U42+0 -> 1344990.1 | V41: =V42*1.0002 -> 3752352.4 | W41: =W42+427 -> 1007259 | X41: =X42+1731.342590164 -> 1091062.6 | Y41: =Y42+735+597.83 -> 2520060.9 | AA41: =AA42 -> 592082.8 | AB41: =IF((SUM(C41:AA41)-AC41-abs(AD41))<18000000,,SUM(C41:AA41)-AC41-abs(AD41)) -> 27364192 | AC41: =AC42+1618.527778 -> 4234280.4 | AD41: =AD42+2400 -> -41211.918 | AE41: =IF(AB41="",,(AB41+AC41+abs(AD41))) -> 31639684 | AF41: =AA41/AB41 -> 0.021637138 | AG41: =AE41-AB41 -> 4275492.3
A42: =A43+1 -> 46060 | B42: =101.56*3620 -> 367647.2 | G42: =209*14200 -> 2967800 | H42: =12*63500 -> 762000 | I42: =6*72400 -> 434400 | J42: =80*51200 -> 4096000 | K42: =66*28100 -> 1854600 | L42: =2*72640 -> 145280 | M42: =59*19800 -> 1168200 | N42: =124*19200 -> 2380800 | O42: =1*769100 -> 769100 | P42: =5*231020 -> 1155100 | Q42: =0 -> 0 | R42: =R43-15402 -> 2013901 | S42: =S43+1177.8473 -> 748664.63 | T42: =T43+2860 -> 2847395 | U42: =U43+0 -> 1344990.1 | V42: =V43*1.0002 -> 3751602.1 | W42: =W43+427 -> 1006832 | X42: =X43+1731.342590164 -> 1089331.3 | Y42: =Y43+735+597.83 -> 2518728.1 | AA42: =AA43 -> 592082.8 | AB42: =IF((SUM(C42:AA42)-AC42-abs(AD42))<18000000,,SUM(C42:AA42)-AC42-abs(AD42)) -> 27370533 | AC42: =AC43+1618.527778 -> 4232661.9 | AD42: =AD43+2400 -> -43611.918 | AE42: =IF(AB42="",,(AB42+AC42+abs(AD42))) -> 31646807 | AF42: =AA42/AB42 -> 0.021632125 | AG42: =AE42-AB42 -> 4276273.8
A43: =A44+1 -> 46059 | B43: =101.56*3620 -> 367647.2 | G43: =209*14200 -> 2967800 | H43: =12*63500 -> 762000 | I43: =6*72400 -> 434400 | J43: =80*51200 -> 4096000 | K43: =66*28100 -> 1854600 | L43: =2*72640 -> 145280 | M43: =59*19800 -> 1168200 | N43: =124*19200 -> 2380800 | O43: =1*769100 -> 769100 | P43: =5*231020 -> 1155100 | Q43: =0 -> 0 | R43: =R44-15402 -> 2029303 | S43: =S44+1177.8473 -> 747486.79 | T43: =T44+2860 -> 2844535 | U43: =U44+0 -> 1344990.1 | V43: =V44*1.0002 -> 3750851.9 | W43: =W44+427 -> 1006405 | X43: =X44+1731.342590164 -> 1087600 | Y43: =Y44+735+597.83 -> 2517395.2 | AA43: =AA44 -> 592082.8 | AB43: =IF((SUM(C43:AA43)-AC43-abs(AD43))<18000000,,SUM(C43:AA43)-AC43-abs(AD43)) -> 27376874 | AC43: =AC44+1618.527778 -> 4231043.4 | AD43: =AD44+2400 -> -46011.918 | AE43: =IF(AB43="",,(AB43+AC43+abs(AD43))) -> 31653930 | AF43: =AA43/AB43 -> 0.021627115 | AG43: =AE43-AB43 -> 4277055.3
A44: =A45+1 -> 46058 | B44: =101.56*3620 -> 367647.2 | G44: =209*14000 -> 2926000 | H44: =12*61900 -> 742800 | I44: =6*70300 -> 421800 | J44: =80*50000 -> 4000000 | K44: =66*28100 -> 1854600 | L44: =2*71300 -> 142600 | M44: =59*19640 -> 1158760 | N44: =124*18320 -> 2271680 | O44: =1*854840 -> 854840 | P44: =5*231000 -> 1155000 | Q44: =0 -> 0 | R44: =R45-8402+120000 -> 2044705 | S44: =S45+1177.8473 -> 746308.94 | T44: =T45+2860 -> 2841675 | U44: =U45+0 -> 1344990.1 | V44: =V45*1.0002 -> 3750101.9 | W44: =W45+427 -> 1005978 | X44: =X45+1731.342590164 -> 1085868.6 | Y44: =Y45+735+597.83 -> 2516062.4 | AA44: =AA45-120000 -> 592082.8 | AB44: =IF((SUM(C44:AA44)-AC44-abs(AD44))<18000000,,SUM(C44:AA44)-AC44-abs(AD44)) -> 27178016 | AC44: =AC45+1618.527778 -> 4229424.8 | AD44: =AD45+2400 -> -48411.918 | AE44: =IF(AB44="",,(AB44+AC44+abs(AD44))) -> 31455853 | AF44: =AA44/AB44 -> 0.021785358 | AG44: =AE44-AB44 -> 4277836.8
A45: =A46+1 -> 46057 | B45: =101.56*3620 -> 367647.2 | G45: =209*14360 -> 3001240 | H45: =12*62500 -> 750000 | I45: =6*71480 -> 428880 | J45: =80*51960 -> 4156800 | K45: =66*28100 -> 1854600 | L45: =2*73000 -> 146000 | M45: =59*19700 -> 1162300 | N45: =124*19000 -> 2356000 | O45: =1*885000 -> 885000 | P45: =5*234500 -> 1172500 | Q45: =0 -> 0 | R45: =R46-8402+100000 -> 1933107 | S45: =S46+1177.8473 -> 745131.09 | T45: =T46+2860 -> 2838815 | U45: =U46+0 -> 1344990.1 | V45: =V46*1.0002 -> 3749352 | W45: =W46+427 -> 1005551 | X45: =X46+1731.342590164 -> 1084137.3 | Y45: =Y46+735+597.83 -> 2514729.6 | AA45: =AA46-100000 -> 712082.8 | AB45: =IF((SUM(C45:AA45)-AC45-abs(AD45))<18000000,,SUM(C45:AA45)-AC45-abs(AD45)) -> 27562598 | AC45: =AC46+1618.527778 -> 4227806.3 | AD45: =AD46+2400 -> -50811.918 | AE45: =IF(AB45="",,(AB45+AC45+abs(AD45))) -> 31841216 | AF45: =AA45/AB45 -> 0.025835112 | AG45: =AE45-AB45 -> 4278618.2
A46: =A47+1 -> 46056 | B46: =101.56*3620 -> 367647.2 | G46: =209*14500 -> 3030500 | H46: =12*66000 -> 792000 | I46: =6*75020 -> 450120 | J46: =80*52500 -> 4200000 | K46: =66*28100 -> 1854600 | L46: =2*74920 -> 149840 | M46: =59*20000 -> 1180000 | N46: =124*19200 -> 2380800 | O46: =1*873000 -> 873000 | P46: =5*215000 -> 1075000 | Q46: =0 -> 0 | R46: =R47-8402 -> 1841509 | S46: =S47+1177.8473 -> 743953.24 | T46: =T47+2860 -> 2835955 | U46: =U47+0 -> 1344990.1 | V46: =V47*1.0002 -> 3748602.3 | W46: =W47+427 -> 1005124 | X46: =X47+1731.342590164 -> 1082405.9 | Y46: =Y47+735+597.83 -> 2513396.8 | AA46: =AA47-10000 -> 812082.8 | AB46: =IF((SUM(C46:AA46)-AC46-abs(AD46))<18000000,,SUM(C46:AA46)-AC46-abs(AD46)) -> 27634479 | AC46: =AC47+1618.527778 -> 4226187.8 | AD46: =AD47+2400 -> -53211.918 | AE46: =IF(AB46="",,(AB46+AC46+abs(AD46))) -> 31913879 | AF46: =AA46/AB46 -> 0.029386579 | AG46: =AE46-AB46 -> 4279399.7
A47: =A48+1 -> 46055 | B47: =101.56*3620 -> 367647.2 | G47: =209*14580 -> 3047220 | H47: =12*65680 -> 788160 | I47: =6*74660 -> 447960 | J47: =80*51880 -> 4150400 | K47: =66*28100 -> 1854600 | L47: =2*75500 -> 151000 | M47: =59*19760 -> 1165840 | N47: =124*19100 -> 2368400 | O47: =1*879000 -> 879000 | P47: =5*225200 -> 1126000 | Q47: =0 -> 0 | R47: =R48-8402+50000 -> 1849911 | S47: =S48+1177.8473 -> 742775.4 | T47: =T48+2860 -> 2833095 | U47: =U48+0 -> 1344990.1 | V47: =V48*1.0002 -> 3747852.7 | W47: =W48+427 -> 1004697 | X47: =X48+1731.342590164-174000 -> 1080674.6 | Y47: =Y48+735+597.83 -> 2512063.9 | AA47: =AA48+174000-10000-50000 -> 822082.8 | AB47: =IF((SUM(C47:AA47)-AC47-abs(AD47))<18000000,,SUM(C47:AA47)-AC47-abs(AD47)) -> 27636541 | AC47: =AC48+1618.527778 -> 4224569.2 | AD47: =AD48+2400 -> -55611.918 | AE47: =IF(AB47="",,(AB47+AC47+abs(AD47))) -> 31916722 | AF47: =AA47/AB47 -> 0.029746226 | AG47: =AE47-AB47 -> 4280181.2
A48: =A49+1 -> 46054 | B48: =101.56*3620 -> 367647.2 | G48: =209*14580 -> 3047220 | H48: =12*65500 -> 786000 | I48: =6*75500 -> 453000 | J48: =80*52100 -> 4168000 | K48: =66*28100 -> 1854600 | L48: =2*76460 -> 152920 | M48: =59*20200 -> 1191800 | N48: =124*19840 -> 2460160 | O48: =1*890160 -> 890160 | P48: =5*236540 -> 1182700 | Q48: =0 -> 0 | R48: =R49-8402 -> 1808313 | S48: =S49+1177.8473 -> 741597.55 | T48: =T49+2860 -> 2830235 | U48: =U49+0 -> 1344990.1 | V48: =V49*1.0002 -> 3747103.3 | W48: =W49+427 -> 1004270 | X48: =X49+2031.342590164 -> 1252943.2 | Y48: =Y49+735+597.83 -> 2510731.1 | AA48: =AA49 -> 708082.8 | AB48: =IF((SUM(C48:AA48)-AC48-abs(AD48))<18000000,,SUM(C48:AA48)-AC48-abs(AD48)) -> 27853863 | AC48: =AC49+1618.527778 -> 4222950.7 | AD48: =AD49+1400 -> -58011.918 | AE48: =IF(AB48="",,(AB48+AC48+abs(AD48))) -> 32134826 | AF48: =AA48/AB48 -> 0.02542135 | AG48: =AE48-AB48 -> 4280962.6
A49: =A50+1 -> 46053 | B49: =101.56*3700 -> 375772 | G49: =209*14580 -> 3047220 | H49: =12*65500 -> 786000 | I49: =6*75500 -> 453000 | J49: =80*52100 -> 4168000 | K49: =66*28100 -> 1854600 | L49: =2*76460 -> 152920 | M49: =59*20200 -> 1191800 | N49: =124*19840 -> 2460160 | O49: =1*890160 -> 890160 | P49: =5*236540 -> 1182700 | Q49: =0 -> 0 | R49: =R50-8402 -> 1816715 | S49: =S50+1177.8473 -> 740419.7 | T49: =T50+2860 -> 2827375 | U49: =U50+0 -> 1344990.1 | V49: =V50*1.0002 -> 3746354 | W49: =W50+427 -> 1003843 | X49: =X50+2031.342590164 -> 1250911.9 | Y49: =Y50+735+597.83 -> 2509398.3 | AA49: =AA50 -> 708082.8 | AB49: =IF((SUM(C49:AA49)-AC49-abs(AD49))<18000000,,SUM(C49:AA49)-AC49-abs(AD49)) -> 27853906 | AC49: =AC50+1618.527778 -> 4221332.2 | AD49: =AD50+1400 -> -59411.918 | AE49: =IF(AB49="",,(AB49+AC49+abs(AD49))) -> 32134650 | AF49: =AA49/AB49 -> 0.025421311 | AG49: =AE49-AB49 -> 4280744.1
A50: =A51+1 -> 46052 | B50: =101.56*3700 -> 375772 | G50: =209*14580 -> 3047220 | H50: =12*65500 -> 786000 | I50: =6*75500 -> 453000 | J50: =80*52100 -> 4168000 | K50: =66*28100 -> 1854600 | L50: =2*76460 -> 152920 | M50: =59*20200 -> 1191800 | N50: =124*19840 -> 2460160 | O50: =1*890160 -> 890160 | P50: =5*241880 -> 1209400 | Q50: =0 -> 0 | R50: =R51-8402+100000 -> 1825117 | S50: =S51+1177.8473 -> 739241.85 | T50: =T51+2860 -> 2824515 | U50: =U51+0 -> 1344990.1 | V50: =V51*1.0002 -> 3745604.9 | W50: =W51+427 -> 1003416 | X50: =X51+2031.342590164 -> 1248880.6 | Y50: =Y51+735+597.83+1549463 -> 2508065.4 | AA50: =AA51-1549463-100000 -> 708082.8 | AB50: =IF((SUM(C50:AA50)-AC50-abs(AD50))<18000000,,SUM(C50:AA50)-AC50-abs(AD50)) -> 27880648 | AC50: =AC51+1618.527778 -> 4219713.7 | AD50: =AD51+1400 -> -60811.918 | AE50: =IF(AB50="",,(AB50+AC50+abs(AD50))) -> 32161174 | AF50: =AA50/AB50 -> 0.025396928 | AG50: =AE50-AB50 -> 4280525.6
A51: =A52+1 -> 46051 | B51: =101.56*3700 -> 375772 | G51: =209*14580 -> 3047220 | H51: =12*68040 -> 816480 | I51: =6*76300 -> 457800 | J51: =80*50900 -> 4072000 | K51: =66*28700 -> 1894200 | L51: =2*76860 -> 153720 | M51: =59*20580 -> 1214220 | N51: =124*20160 -> 2499840 | O51: =1*874200 -> 874200 | P51: =5*230000 -> 1150000 | Q51: =0 -> 0 | R51: =R52-8402 -> 1733519 | S51: =S52+1177.8473 -> 738064.01 | T51: =T52+2860 -> 2821655 | U51: =U52+0 -> 1344990.1 | V51: =V52*1.0002 -> 3744855.9 | W51: =W52+427 -> 1002989 | X51: =X52+2031.342590164 -> 1246849.2 | Y51: =Y52+735+597.83+793500 -> 957269.61 | AA51: =AA52-793500-87000+1000000 -> 2357545.8 | AB51: =IF((SUM(C51:AA51)-AC51-abs(AD51))<18000000,,SUM(C51:AA51)-AC51-abs(AD51)) -> 27847111 | AC51: =AC52+1618.527778 -> 4218095.1 | AD51: =AD52+1400 -> -62211.918 | AE51: =IF(AB51="",,(AB51+AC51+abs(AD51))) -> 32127418 | AF51: =AA51/AB51 -> 0.084660338 | AG51: =AE51-AB51 -> 4280307.1
A52: =A53+1 -> 46050 | B52: =101.56*3700 -> 375772 | G52: =209*14680 -> 3068120 | H52: =12*68380 -> 820560 | I52: =6*76800 -> 460800 | J52: =80*51620 -> 4129600 | K52: =66*29000 -> 1914000 | L52: =2*76960 -> 153920 | M52: =59*20760 -> 1224840 | N52: =124*20300 -> 2517200 | O52: =1*889260 -> 889260 | P52: =5*229400 -> 1147000 | Q52: =0 -> 0 | R52: =R53-8402 -> 1741921 | S52: =S53+1177.8473 -> 736886.16 | T52: =T53+2860 -> 2818795 | U52: =U53+0 -> 1344990.1 | V52: =V53*1.0002 -> 3744107.1 | W52: =W53+427 -> 1002562 | X52: =X53+2031.342590164 -> 1244817.9 | Y52: =Y53+735+597.83 -> 162436.78 | AA52: =AA53 -> 2238045.8 | AB52: =IF((SUM(C52:AA52)-AC52-abs(AD52))<18000000,,SUM(C52:AA52)-AC52-abs(AD52)) -> 27079773 | AC52: =AC53+1618.527778 -> 4216476.6 | AD52: =AD53+1400 -> -63611.918 | AE52: =IF(AB52="",,(AB52+AC52+abs(AD52))) -> 31359862 | AF52: =AA52/AB52 -> 0.082646401 | AG52: =AE52-AB52 -> 4280088.5
A53: =A54+1 -> 46049 | B53: =101.56*3700 -> 375772 | G53: =209*14580 -> 3047220 | H53: =12*66900 -> 802800 | I53: =6*77020 -> 462120 | J53: =80*51980 -> 4158400 | K53: =66*28300 -> 1867800 | L53: =2*75900 -> 151800 | M53: =59*20360 -> 1201240 | N53: =124*20000 -> 2480000 | O53: =1*892120 -> 892120 | P53: =5*228500 -> 1142500 | Q53: =0 -> 0 | R53: =R54-8402 -> 1750323 | S53: =S54+1177.8473 -> 735708.31 | T53: =T54+2860 -> 2815935 | U53: =U54+0 -> 1344990.1 | V53: =V54*1.0002 -> 3743358.4 | W53: =W54+427 -> 1002135 | X53: =X54+2031.342590164 -> 1242786.5 | Y53: =Y54+735+597.83 -> 161103.95 | AA53: =AA54 -> 2238045.8 | AB53: =IF((SUM(C53:AA53)-AC53-abs(AD53))<18000000,,SUM(C53:AA53)-AC53-abs(AD53)) -> 26960516 | AC53: =AC54+1618.527778 -> 4214858.1 | AD53: =AD54+1400 -> -65011.918 | AE53: =IF(AB53="",,(AB53+AC53+abs(AD53))) -> 31240386 | AF53: =AA53/AB53 -> 0.083011979 | AG53: =AE53-AB53 -> 4279870
A54: =A55+1 -> 46048 | B54: =101.56*3700 -> 375772 | G54: =209*14700 -> 3072300 | H54: =12*66960 -> 803520 | I54: =6*77800 -> 466800 | J54: =80*52720 -> 4217600 | K54: =66*27040 -> 1784640 | L54: =2*76180 -> 152360 | M54: =59*20180 -> 1190620 | N54: =124*20300 -> 2517200 | O54: =1*885940 -> 885940 | P54: =5*227260 -> 1136300 | Q54: =0 -> 0 | R54: =R55-8402 -> 1758725 | S54: =S55+1177.8473 -> 734530.47 | T54: =T55+2860 -> 2813075 | U54: =U55+0 -> 1344990.1 | V54: =V55*1.0002 -> 3742609.9 | W54: =W55+427 -> 1001708 | X54: =X55+2031.342590164 -> 1240755.2 | Y54: =Y55+735+597.83 -> 159771.12 | AA54: =AA55 -> 2238045.8 | AB54: =IF((SUM(C54:AA54)-AC54-abs(AD54))<18000000,,SUM(C54:AA54)-AC54-abs(AD54)) -> 26981839 | AC54: =AC55+1618.527778 -> 4213239.6 | AD54: =AD55+1400 -> -66411.918 | AE54: =IF(AB54="",,(AB54+AC54+abs(AD54))) -> 31261491 | AF54: =AA54/AB54 -> 0.082946377 | AG54: =AE54-AB54 -> 4279651.5
A55: =A56+1 -> 46047 | B55: =101.56*3735 -> 379326.6 | G55: =209*14640 -> 3059760 | H55: =12*65480 -> 785760 | I55: =6*75300 -> 451800 | J55: =80*51800 -> 4144000 | K55: =66*27280 -> 1800480 | L55: =2*76560 -> 153120 | M55: =59*19600 -> 1156400 | N55: =124*20000 -> 2480000 | O55: =1*869260 -> 869260 | P55: =5*236540 -> 1182700 | Q55: =0 -> 0 | R55: =R56-3402+220000 -> 1767127 | S55: =S56+1177.8473 -> 733352.62 | T55: =T56+2860 -> 2810215 | U55: =U56+0 -> 1344990.1 | V55: =V56*1.0002 -> 3741861.5 | W55: =W56+427 -> 1001281 | X55: =X56+2031.342590164 -> 1238723.8 | Y55: =Y56+735+597.83-200000 -> 158438.29 | AA55: =AA56+30000+200000-100000-220000+200000 -> 2238045.8 | AB55: =IF((SUM(C55:AA55)-AC55-abs(AD55))<18000000,,SUM(C55:AA55)-AC55-abs(AD55)) -> 26837882 | AC55: =AC56+1618.527778 -> 4211621 | AD55: =AD56+1400+100000 -> -67811.918 | AE55: =IF(AB55="",,(AB55+AC55+abs(AD55))) -> 31117315 | AF55: =AA55/AB55 -> 0.083391297 | AG55: =AE55-AB55 -> 4279432.9
A56: =A57+1 -> 46046 | B56: =101.56*3735 -> 379326.6 | G56: =209*14640 -> 3059760 | H56: =12*65480 -> 785760 | I56: =6*75300 -> 451800 | J56: =80*51800 -> 4144000 | K56: =66*27280 -> 1800480 | L56: =2*76560 -> 153120 | M56: =59*19600 -> 1156400 | N56: =124*20000 -> 2480000 | O56: =1*869260 -> 869260 | P56: =5*236540 -> 1182700 | Q56: =0 -> 0 | R56: =R57-3402 -> 1550529 | S56: =S57+1177.8473 -> 732174.77 | T56: =T57+2860 -> 2807355 | U56: =U57+0 -> 1344990.1 | V56: =V57*1.0002 -> 3741113.3 | W56: =W57+427 -> 1000854 | X56: =X57+2031.342590164 -> 1236692.5 | Y56: =Y57+735+597.83 -> 357105.46 | AA56: =AA57 -> 2128045.8 | AB56: =IF((SUM(C56:AA56)-AC56-abs(AD56))<18000000,,SUM(C56:AA56)-AC56-abs(AD56)) -> 26602926 | AC56: =AC57+1618.527778 -> 4210002.5 | AD56: =AD57+1400 -> -169211.92 | AE56: =IF(AB56="",,(AB56+AC56+abs(AD56))) -> 30982140 | AF56: =AA56/AB56 -> 0.079992924 | AG56: =AE56-AB56 -> 4379214.4
A57: =A58+1 -> 46045 | B57: =101.56*3735 -> 379326.6 | G57: =209*14640 -> 3059760 | H57: =12*65480 -> 785760 | I57: =6*75300 -> 451800 | J57: =80*51800 -> 4144000 | K57: =66*27280 -> 1800480 | L57: =2*76560 -> 153120 | M57: =59*19600 -> 1156400 | N57: =124*20000 -> 2480000 | O57: =1*869260 -> 869260 | P57: =5*236540 -> 1182700 | Q57: =0 -> 0 | R57: =R58-3402 -> 1553931 | S57: =S58+1177.8473 -> 730996.92 | T57: =T58+2860 -> 2804495 | U57: =U58+0 -> 1344990.1 | V57: =V58*1.0002 -> 3740365.3 | W57: =W58+427 -> 1000427 | X57: =X58+2031.342590164 -> 1234661.2 | Y57: =Y58+735+597.83 -> 355772.63 | AA57: =AA58 -> 2128045.8 | AB57: =IF((SUM(C57:AA57)-AC57-abs(AD57))<18000000,,SUM(C57:AA57)-AC57-abs(AD57)) -> 26597969 | AC57: =AC58+1618.527778 -> 4208384 | AD57: =AD58+1400 -> -170611.92 | AE57: =IF(AB57="",,(AB57+AC57+abs(AD57))) -> 30976965 | AF57: =AA57/AB57 -> 0.080007831 | AG57: =AE57-AB57 -> 4378995.9
A58: =A59+1 -> 46044 | B58: =101.56*3735 -> 379326.6 | G58: =209*14560 -> 3043040 | H58: =12*64500 -> 774000 | I58: =6*71000 -> 426000 | J58: =80*50900 -> 4072000 | K58: =66*27020 -> 1783320 | L58: =2*77000 -> 154000 | M58: =59*19500 -> 1150500 | N58: =124*19980 -> 2477520 | O58: =1*842000 -> 842000 | P58: =5*237000 -> 1185000 | Q58: =0 -> 0 | R58: =R59-3402 -> 1557333 | S58: =S59+1177.8473 -> 729819.08 | T58: =T59+2860 -> 2801635 | U58: =U59+0 -> 1344990.1 | V58: =V59*1.0002 -> 3739617.3 | W58: =1000000 -> 1000000 | X58: =X59+2031.342590164 -> 1232629.8 | Y58: =Y59+735+597.83 -> 354439.8 | AA58: =AA59-1000000 -> 2128045.8 | AB58: =IF((SUM(C58:AA58)-AC58-abs(AD58))<18000000,,SUM(C58:AA58)-AC58-abs(AD58)) -> 26417113 | AC58: =AC59+1618.527778 -> 4206765.4 | AD58: =AD59+1400 -> -172011.92 | AE58: =IF(AB58="",,(AB58+AC58+abs(AD58))) -> 30795890 | AF58: =AA58/AB58 -> 0.080555579 | AG58: =AE58-AB58 -> 4378777.4
A59: =A60+1 -> 46043 | B59: =101.56*3735 -> 379326.6 | G59: =209*14480 -> 3026320 | H59: =12*63220 -> 758640 | I59: =6*73200 -> 439200 | J59: =80*51580 -> 4126400 | K59: =66*27000 -> 1782000 | L59: =2*76940 -> 153880 | M59: =59*19500 -> 1150500 | N59: =124*20100 -> 2492400 | O59: =1*852540 -> 852540 | P59: =5*235040 -> 1175200 | Q59: =0 -> 0 | R59: =R60-3402 -> 1560735 | S59: =S60+1177.8473-7500 -> 728641.23 | T59: =T60+2860 -> 2798775 | U59: =U60+0 -> 1344990.1 | V59: =V60*1.0002 -> 3738869.6 | W59: =W60-442500 -> 0 | X59: =X60+2031.342590164 -> 1230598.5 | Y59: =Y60+735+597.83 -> 353106.97 | AA59: =AA60+450000 -> 3128045.8 | AB59: =IF((SUM(C59:AA59)-AC59-abs(AD59))<18000000,,SUM(C59:AA59)-AC59-abs(AD59)) -> 26462283 | AC59: =AC60+1618.527778 -> 4205146.9 | AD59: =AD60+1400 -> -173411.92 | AE59: =IF(AB59="",,(AB59+AC59+abs(AD59))) -> 30840842 | AF59: =AA59/AB59 -> 0.11820771 | AG59: =AE59-AB59 -> 4378558.8
A60: =A61+1 -> 46042 | B60: =101.56*3735 -> 379326.6 | G60: =209*14260 -> 2980340 | H60: =12*62440 -> 749280 | I60: =6*70800 -> 424800 | J60: =80*50600 -> 4048000 | K60: =66*26980 -> 1780680 | L60: =2*77000 -> 154000 | M60: =59*19480 -> 1149320 | N60: =124*20200 -> 2504800 | O60: =1*850200 -> 850200 | P60: =5*232360 -> 1161800 | Q60: =0 -> 0 | R60: =R61-3402 -> 1564137 | S60: =S61+1177.8473 -> 734963.38 | T60: =T61+2560 -> 2795915 | U60: =U61+2036 -> 1344990.1 | V60: =V61*1.0002 -> 3738121.9 | W60: =W61 -> 442500 | X60: =X61+2031.342590164 -> 1228567.1 | Y60: =Y61+735+597.83 -> 351774.14 | AA60: =AA61 -> 2678045.8 | AB60: =IF((SUM(C60:AA60)-AC60-abs(AD60))<18000000,,SUM(C60:AA60)-AC60-abs(AD60)) -> 26303894 | AC60: =AC61+1618.527778 -> 4203528.4 | AD60: =AD61+1400 -> -174811.92 | AE60: =IF(AB60="",,(AB60+AC60+abs(AD60))) -> 30682234 | AF60: =AA60/AB60 -> 0.10181176 | AG60: =AE60-AB60 -> 4378340.3
A61: =A62+1 -> 46041 | B61: =101.56*3735 -> 379326.6 | G61: =209*13900 -> 2905100 | H61: =12*61320 -> 735840 | I61: =6*71460 -> 428760 | J61: =80*49600 -> 3968000 | K61: =66*26700 -> 1762200 | L61: =2*77960 -> 155920 | M61: =59*19340 -> 1141060 | N61: =124*20000 -> 2480000 | O61: =1*884760 -> 884760 | P61: =5*238200 -> 1191000 | Q61: =0 -> 0 | R61: =R62-3402+120000 -> 1567539 | S61: =S62+1177.8473 -> 733785.53 | T61: =T62+2560 -> 2793355 | U61: =U62+2036-275000 -> 1342954.1 | V61: =V62*1.0002 -> 3737374.5 | W61: =W62 -> 442500 | X61: =X62+2031.342590164 -> 1226535.8 | Y61: =Y62+735+597.83 -> 350441.31 | AA61: =AA62+275000-120000 -> 2678045.8 | AB61: =IF((SUM(C61:AA61)-AC61-abs(AD61))<18000000,,SUM(C61:AA61)-AC61-abs(AD61)) -> 26147049 | AC61: =AC62+1618.527778 -> 4201909.9 | AD61: =AD62+1400 -> -176211.92 | AE61: =IF(AB61="",,(AB61+AC61+abs(AD61))) -> 30525171 | AF61: =AA61/AB61 -> 0.10242249 | AG61: =AE61-AB61 -> 4378121.8
A62: =A63+1 -> 46040 | B62: =101.56*3735 -> 379326.6 | G62: =209*13800 -> 2884200 | H62: =12*61320 -> 735840 | I62: =6*69980 -> 419880 | J62: =80*48200 -> 3856000 | K62: =66*26300 -> 1735800 | L62: =2*77780 -> 155560 | M62: =59*19280 -> 1137520 | N62: =124*19880 -> 2465120 | O62: =1*881200 -> 881200 | P62: =5*236080 -> 1180400 | Q62: =0 -> 0 | R62: =R63-3402 -> 1450941 | S62: =S63+1177.8473 -> 732607.69 | T62: =T63+1860 -> 2790795 | U62: =U63+2036 -> 1615918.1 | V62: =V63*1.0002-50000 -> 3736627.1 | W62: =W63 -> 442500 | X62: =X63+2031.342590164 -> 1224504.4 | Y62: =Y63+735+597.83 -> 349108.48 | AA62: =AA63+250000 -> 2523045.8 | AB62: =IF((SUM(C62:AA62)-AC62-abs(AD62))<18000000,,SUM(C62:AA62)-AC62-abs(AD62)) -> 25939664 | AC62: =AC63+1618.527778 -> 4200291.3 | AD62: =AD63+1400 -> -177611.92 | AE62: =IF(AB62="",,(AB62+AC62+abs(AD62))) -> 30317568 | AF62: =AA62/AB62 -> 0.097265939 | AG62: =AE62-AB62 -> 4377903.3
A63: =A64+1 -> 46039 | B63: =101.56*3735 -> 379326.6 | G63: =209*13800 -> 2884200 | H63: =12*61320 -> 735840 | I63: =6*69980 -> 419880 | J63: =80*48200 -> 3856000 | K63: =66*26300 -> 1735800 | L63: =2*77780 -> 155560 | M63: =59*19280 -> 1137520 | N63: =124*19880 -> 2465120 | O63: =1*881200 -> 881200 | P63: =5*236080 -> 1180400 | Q63: =0 -> 0 | R63: =R64-3402 -> 1454343 | S63: =S64+1177.8473 -> 731429.84 | T63: =T64+1830+305690 -> 2788935 | U63: =U64+2036 -> 1613882.1 | V63: =V64*1.0002 -> 3785870 | W63: =W64 -> 442500 | X63: =X64+2031.342590164 -> 1222473.1 | Y63: =Y64+735+597.83 -> 347775.65 | AA63: =AA64- 1245186.2-305960+800+39230 -> 2273045.8 | AB63: =IF((SUM(C63:AA63)-AC63-abs(AD63))<18000000,,SUM(C63:AA63)-AC63-abs(AD63)) -> 25734090 | AC63: =AC64+2018.527778 -> 4198672.8 | AD63: =AD64+1400 -> -179011.92 | AE63: =IF(AB63="",,(AB63+AC63+abs(AD63))) -> 30111774 | AF63: =AA63/AB63 -> 0.088328199 | AG63: =AE63-AB63 -> 4377684.7
A64: =A65+1 -> 46038 | B64: =101.56*3735 -> 379326.6 | G64: =209*13800 -> 2884200 | H64: =12*61320 -> 735840 | I64: =6*69980 -> 419880 | J64: =80*48200 -> 3856000 | K64: =66*26300 -> 1735800 | L64: =2*77780 -> 155560 | M64: =59*19280 -> 1137520 | N64: =124*19880 -> 2465120 | O64: =1*881200 -> 881200 | P64: =5*236080 -> 1180400 | Q64: =0 -> 0 | R64: =R65-3402 -> 1457745 | S64: =S65+1177.8473 -> 730251.99 | T64: =T65+1830 -> 2481415 | U64: =U65+2036 -> 1611846.1 | V64: =V65*1.0002 -> 3785112.9 | W64: =W65 -> 442500 | X64: =X65+2031.342590164 -> 1220441.8 | Y64: =Y65+735+597.83 -> 346442.82 | AA64: =AA65 -> 3784162 | AB64: =IF((SUM(C64:AA64)-AC64-abs(AD64))<18000000,,SUM(C64:AA64)-AC64-abs(AD64)) -> 26934371 | AC64: =AC65+2018.527778 -> 4196654.3 | AD64: =AD65+1400 -> -180411.92 | AE64: =IF(AB64="",,(AB64+AC64+abs(AD64))) -> 31311438 | AF64: =AA64/AB64 -> 0.14049565 | AG64: =AE64-AB64 -> 4377066.2
A65: =A66+1 -> 46037 | B65: =101.56*3735 -> 379326.6 | G65: =209*13380 -> 2796420 | H65: =12*61240 -> 734880 | I65: =6*68300 -> 409800 | J65: =80*46000 -> 3680000 | K65: =66*26040 -> 1718640 | L65: =2*77780 -> 155560 | M65: =59*18900 -> 1115100 | N65: =124*19900 -> 2467600 | O65: =1*882000 -> 882000 | P65: =5*239180 -> 1195900 | Q65: =0 -> 0 | R65: =R66-3402 -> 1461147 | S65: =S66+1177.8473 -> 729074.15 | T65: =T66+1830 -> 2479585 | U65: =U66+2036 -> 1609810.1 | V65: =V66*1.0002 -> 3784356.1 | W65: =W66 -> 442500 | X65: =X66+2031.342590164 -> 1218410.4 | Y65: =Y66+735+597.83 -> 345109.99 | AA65: =AA66 -> 3784162 | AB65: =IF((SUM(C65:AA65)-AC65-abs(AD65))<18000000,,SUM(C65:AA65)-AC65-abs(AD65)) -> 26633607 | AC65: =AC66+2018.527778 -> 4194635.8 | AD65: =AD66+1400 -> -181811.92 | AE65: =IF(AB65="",,(AB65+AC65+abs(AD65))) -> 31010055 | AF65: =AA65/AB65 -> 0.14208222 | AG65: =AE65-AB65 -> 4376447.7
A66: =A67+1 -> 46036 | B66: =101.56*3735 -> 379326.6 | G66: =209*13280 -> 2775520 | H66: =12*61420 -> 737040 | I66: =6*67620 -> 405720 | J66: =80*45280 -> 3622400 | K66: =66*26180 -> 1727880 | L66: =2*77920 -> 155840 | M66: =59*18980 -> 1119820 | N66: =124*19600 -> 2430400 | O66: =1*871000 -> 871000 | P66: =5*240880 -> 1204400 | Q66: =0 -> 0 | R66: =R67-3402 -> 1464549 | S66: =S67+1177.8473 -> 727896.3 | T66: =T67+1830 -> 2477755 | U66: =U67+2036 -> 1607774.1 | V66: =V67*1.0002 -> 3783599.3 | W66: =W67 -> 442500 | X66: =X67+2031.342590164 -> 1216379.1 | Y66: =Y67+735+597.83 -> 343777.16 | AA66: =AA67 -> 3784162 | AB66: =IF((SUM(C66:AA66)-AC66-abs(AD66))<18000000,,SUM(C66:AA66)-AC66-abs(AD66)) -> 26522583 | AC66: =AC67+2018.527778 -> 4192617.2 | AD66: =AD67+1400 -> -183211.92 | AE66: =IF(AB66="",,(AB66+AC66+abs(AD66))) -> 30898412 | AF66: =AA66/AB66 -> 0.14267698 | AG66: =AE66-AB66 -> 4375829.1
A67: =A68+1 -> 46035 | B67: =101.56*3735 -> 379326.6 | G67: =209*13400 -> 2800600 | H67: =12*60480 -> 725760 | I67: =6*66520 -> 399120 | J67: =80*45400 -> 3632000 | K67: =66*26280 -> 1734480 | L67: =2*78240 -> 156480 | M67: =59*19060 -> 1124540 | N67: =124*19200 -> 2380800 | O67: =1*882980 -> 882980 | P67: =5*241000 -> 1205000 | Q67: =0 -> 0 | R67: =R68-3402 -> 1467951 | S67: =S68+1177.8473 -> 726718.45 | T67: =T68+1830 -> 2475925 | U67: =U68+2036 -> 1605738.1 | V67: =V68*1.0002 -> 3782842.8 | W67: =W68 -> 442500 | X67: =X68+2031.342590164 -> 1214347.7 | Y67: =Y68+735+597.83 -> 342444.33 | AA67: =AA68+50000 -> 3784162 | AB67: =IF((SUM(C67:AA67)-AC67-abs(AD67))<18000000,,SUM(C67:AA67)-AC67-abs(AD67)) -> 26509179 | AC67: =AC68+2018.527778 -> 4190598.7 | AD67: =AD68+1400 -> -184611.92 | AE67: =IF(AB67="",,(AB67+AC67+abs(AD67))) -> 30884389 | AF67: =AA67/AB67 -> 0.14274912 | AG67: =AE67-AB67 -> 4375210.6
A68: =A69+1 -> 46034 | B68: =101.56*3735 -> 379326.6 | G68: =209*13380 -> 2796420 | H68: =12*65160 -> 781920 | I68: =6*65800 -> 394800 | J68: =80*44400 -> 3552000 | K68: =66*26120 -> 1723920 | L68: =2*79000 -> 158000 | M68: =59*18840 -> 1111560 | N68: =124*19720 -> 2445280 | O68: =1*918600 -> 918600 | P68: =5*244000 -> 1220000 | Q68: =0 -> 0 | R68: =R69-3402 -> 1471353 | S68: =S69+1177.8473 -> 725540.6 | T68: =T69+1830 -> 2474095 | U68: =U69+2036 -> 1603702.1 | V68: =V69*1.0002 -> 3782086.4 | W68: =W69 -> 442500 | X68: =X69+2031.342590164 -> 1212316.4 | Y68: =Y69+735+597.83 -> 341111.5 | AA68: =AA69 -> 3734162 | AB68: =IF((SUM(C68:AA68)-AC68-abs(AD68))<18000000,,SUM(C68:AA68)-AC68-abs(AD68)) -> 26514775 | AC68: =AC69+2018.527778 -> 4188580.2 | AD68: =AD69+1400 -> -186011.92 | AE68: =IF(AB68="",,(AB68+AC68+abs(AD68))) -> 30889367 | AF68: =AA68/AB68 -> 0.14083325 | AG68: =AE68-AB68 -> 4374592.1
A69: =A70+1 -> 46033 | B69: =101.56*3735 -> 379326.6 | G69: =209*13380 -> 2796420 | H69: =12*65160 -> 781920 | I69: =6*65800 -> 394800 | J69: =80*44400 -> 3552000 | K69: =66*26120 -> 1723920 | L69: =2*79000 -> 158000 | M69: =59*18840 -> 1111560 | N69: =124*19720 -> 2445280 | O69: =1*918600 -> 918600 | P69: =5*244000 -> 1220000 | Q69: =0 -> 0 | R69: =R70-3402 -> 1474755 | S69: =S70+1177.8473 -> 724362.76 | T69: =T70+1830 -> 2472265 | U69: =U70+2036 -> 1601666.1 | V69: =V70*1.0002 -> 3781330.1 | W69: =W70 -> 442500 | X69: =X70+2031.342590164 -> 1210285 | Y69: =Y70+735+597.83 -> 339778.67 | AA69: =AA70 -> 3734162 | AB69: =IF((SUM(C69:AA69)-AC69-abs(AD69))<18000000,,SUM(C69:AA69)-AC69-abs(AD69)) -> 26509631 | AC69: =AC70+2018.527778 -> 4186561.6 | AD69: =AD70+1400 -> -187411.92 | AE69: =IF(AB69="",,(AB69+AC69+abs(AD69))) -> 30883605 | AF69: =AA69/AB69 -> 0.14086058 | AG69: =AE69-AB69 -> 4373973.6
A70: =A71+1 -> 46032 | B70: =101.56*3735 -> 379326.6 | G70: =209*13380 -> 2796420 | H70: =12*65160 -> 781920 | I70: =6*65800 -> 394800 | J70: =80*44400 -> 3552000 | K70: =66*26120 -> 1723920 | L70: =2*79000 -> 158000 | M70: =59*18840 -> 1111560 | N70: =124*19720 -> 2445280 | O70: =1*918600 -> 918600 | P70: =5*244000 -> 1220000 | Q70: =0 -> 0 | R70: =R71-3402 -> 1478157 | S70: =S71+1177.8473 -> 723184.91 | T70: =T71+1830 -> 2470435 | U70: =U71+2036 -> 1599630.1 | V70: =V71*1.0002 -> 3780574 | W70: =W71 -> 442500 | X70: =X71+2031.342590164-44000 -> 1208253.7 | Y70: =Y71+735+597.83 -> 338445.84 | AA70: =AA71+44000 -> 3734162 | AB70: =IF((SUM(C70:AA70)-AC70-abs(AD70))<18000000,,SUM(C70:AA70)-AC70-abs(AD70)) -> 26504487 | AC70: =AC71+2018.527778 -> 4184543.1 | AD70: =AD71+1400 -> -188811.92 | AE70: =IF(AB70="",,(AB70+AC70+abs(AD70))) -> 30877842 | AF70: =AA70/AB70 -> 0.14088792 | AG70: =AE70-AB70 -> 4373355
A71: =A72+1 -> 46031 | B71: =101.56*3735 -> 379326.6 | G71: =209*13380 -> 2796420 | H71: =12*65160 -> 781920 | I71: =6*65800 -> 394800 | J71: =80*44400 -> 3552000 | K71: =66*26120 -> 1723920 | L71: =2*79000 -> 158000 | M71: =59*18840 -> 1111560 | N71: =124*19720 -> 2445280 | O71: =1*918600 -> 918600 | P71: =5*244000 -> 1220000 | Q71: =0 -> 0 | R71: =R72-3402+60000 -> 1481559 | S71: =S72+1177.8473 -> 722007.06 | T71: =T72+1830 -> 2468605 | U71: =U72+2036 -> 1597594.1 | V71: =V72*1.0002 -> 3779818 | W71: =W72 -> 442500 | X71: =X72+2031.342590164 -> 1250222.4 | Y71: =Y72+735+597.83 -> 337113.01 | AA71: =AA72-60000 -> 3690162 | AB71: =IF((SUM(C71:AA71)-AC71-abs(AD71))<18000000,,SUM(C71:AA71)-AC71-abs(AD71)) -> 26499344 | AC71: =AC72+2018.527778 -> 4182524.6 | AD71: =AD72+1400 -> -190211.92 | AE71: =IF(AB71="",,(AB71+AC71+abs(AD71))) -> 30872081 | AF71: =AA71/AB71 -> 0.13925484 | AG71: =AE71-AB71 -> 4372736.5
A72: =A73+1 -> 46030 | B72: =101.56*3734 -> 379225.04 | G72: =209*13260 -> 2771340 | H72: =12*65040 -> 780480 | I72: =6*65060 -> 390360 | J72: =80*44980 -> 3598400 | K72: =66*25920 -> 1710720 | L72: =2*79300 -> 158600 | M72: =59*18880 -> 1113920 | N72: =124*19500 -> 2418000 | O72: =1*912500 -> 912500 | P72: =5*241900 -> 1209500 | Q72: =0 -> 0 | R72: =R73-3402+100000 -> 1424961 | S72: =S73+1177.8473 -> 720829.21 | T72: =T73+1830 -> 2466775 | U72: =U73+2036 -> 1595558.1 | V72: =V73*1.0002 -> 3779062.2 | W72: =W73 -> 442500 | X72: =X73+2031.342590164 -> 1248191 | Y72: =Y73+735+597.83 -> 335780.18 | AA72: =AA73-100000 -> 3750162 | AB72: =IF((SUM(C72:AA72)-AC72-abs(AD72))<18000000,,SUM(C72:AA72)-AC72-abs(AD72)) -> 26455521 | AC72: =AC73+2018.527778 -> 4180506.1 | AD72: =AD73+1400 -> -191611.92 | AE72: =IF(AB72="",,(AB72+AC72+abs(AD72))) -> 30827639 | AF72: =AA72/AB72 -> 0.14175348 | AG72: =AE72-AB72 -> 4372118
A73: =A74+1 -> 46029 | B73: =101.56*3730 -> 378818.8 | G73: =209*13180 -> 2754620 | H73: =12*66500 -> 798000 | I73: =6*64000 -> 384000 | J73: =80*45240 -> 3619200 | K73: =66*25600 -> 1689600 | L73: =2*80000 -> 160000 | M73: =59*18920 -> 1116280 | N73: =124*19400 -> 2405600 | O73: =1*912840 -> 912840 | P73: =5*239460 -> 1197300 | Q73: =0 -> 0 | R73: =R74-3402+80000 -> 1328363 | S73: =S74+1177.8473 -> 719651.37 | T73: =T74+1830 -> 2464945 | U73: =U74+2036 -> 1593522.1 | V73: =V74*1.0002 -> 3778306.5 | W73: =W74 -> 442500 | X73: =X74+2031.342590164 -> 1246159.7 | Y73: =Y74+735+597.83 -> 334447.35 | AA73: =AA74-48*25600-80000 -> 3850162 | AB73: =IF((SUM(C73:AA73)-AC73-abs(AD73))<18000000,,SUM(C73:AA73)-AC73-abs(AD73)) -> 26423998 | AC73: =AC74+2018.527778 -> 4178487.5 | AD73: =AD74+1400 -> -193011.92 | AE73: =IF(AB73="",,(AB73+AC73+abs(AD73))) -> 30795497 | AF73: =AA73/AB73 -> 0.14570702 | AG73: =AE73-AB73 -> 4371499.4
A74: =A75+1 -> 46028 | B74: =101.56*3742 -> 380037.52 | G74: =209*13360 -> 2792240 | H74: =12*66540 -> 798480 | I74: =6*63200 -> 379200 | J74: =80*45100 -> 3608000 | K74: =18*25100 -> 451800 | L74: =2*80300 -> 160600 | M74: =59*19000 -> 1121000 | N74: =124*19500 -> 2418000 | O74: =1*894800 -> 894800 | P74: =5*243000 -> 1215000 | Q74: =0 -> 0 | R74: =R75-3402 -> 1251765 | S74: =S75+1177.8473 -> 718473.52 | T74: =T75+1830 -> 2463115 | U74: =U75+2036 -> 1591486.1 | V74: =V75*1.0002+300000 -> 3777551 | W74: =W75 -> 442500 | X74: =X75+2031.342590164 -> 1244128.3 | Y74: =Y75+735+597.83 -> 333114.52 | AA74: =AA75-500000 -> 5158962 | AB74: =IF((SUM(C74:AA74)-AC74-abs(AD74))<18000000,,SUM(C74:AA74)-AC74-abs(AD74)) -> 26449335 | AC74: =AC75+2018.527778 -> 4176469 | AD74: =AD75+1200-200000 -> -194411.92 | AE74: =IF(AB74="",,(AB74+AC74+abs(AD74))) -> 30820215 | AF74: =AA74/AB74 -> 0.19505073 | AG74: =AE74-AB74 -> 4370880.9
A75: =A76+1 -> 46027 | B75: =101.56*3742 -> 380037.52 | G75: =209*13200 -> 2758800 | H75: =12*66780 -> 801360 | I75: =6*61980 -> 371880 | J75: =80*44000 -> 3520000 | K75: =18*25000 -> 450000 | L75: =2*80900 -> 161800 | M75: =59*18820 -> 1110380 | N75: =124*19200 -> 2380800 | O75: =1*864680 -> 864680 | P75: =5*242500 -> 1212500 | Q75: =0 -> 0 | R75: =R76-3402 -> 1255167 | S75: =S76+1177.8473 -> 717295.67 | T75: =T76+1830 -> 2461285 | U75: =U76+2036 -> 1589450.1 | V75: =V76*1.0002 -> 3476855.7 | W75: =W76 -> 442500 | X75: =X76+2031.342590164-129000 -> 1242097 | Y75: =Y76+735+597.83 -> 331781.69 | AA75: =AA76+129000 -> 5658962 | AB75: =IF((SUM(C75:AA75)-AC75-AD75)<18000000,,SUM(C75:AA75)-AC75-AD75) -> 26628756 | AC75: =AC76+2018.527778 -> 4174450.5 | AD75: =AD76+1200 -> 4388.0822 | AE75: =IF(AB75="",,(AB75+AC75+abs(AD75))) -> 30807594 | AF75: =AA75/AB75 -> 0.2125132 | AG75: =AE75-AB75 -> 4178838.6
A76: =A77+1 -> 46026 | B76: =101.56*3742 -> 380037.52 | G76: =209*12980 -> 2712820 | H76: =12*64100 -> 769200 | I76: =6*59520 -> 357120 | J76: =80*42900 -> 3432000 | K76: =18*24820 -> 446760 | L76: =2*79960 -> 159920 | M76: =59*18260 -> 1077340 | N76: =124*18700 -> 2318800 | O76: =1*865000 -> 865000 | P76: =5*230000 -> 1150000 | Q76: =0 -> 0 | R76: =R77-3402 -> 1258569 | S76: =S77+1177.8473 -> 716117.82 | T76: =T77+1830 -> 2459455 | U76: =U77+2036 -> 1587414.1 | V76: =V77*1.0002 -> 3476160.4 | W76: =W77 -> 442500 | X76: =X77+2031.342590164 -> 1369065.6 | Y76: =Y77+735+597.83 -> 330448.86 | AA76: =AA77 -> 5529962 | AB76: =IF((SUM(C76:AA76)-AC76-AD76)<18000000,,SUM(C76:AA76)-AC76-AD76) -> 26283033 | AC76: =AC77+2018.527778 -> 4172431.9 | AD76: =AD77+1200 -> 3188.0822 | AE76: =IF(AB76="",,(AB76+AC76+abs(AD76))) -> 30458653 | AF76: =AA76/AB76 -> 0.21040045 | AG76: =AE76-AB76 -> 4175620
A77: =A78+1 -> 46025 | B77: =101.56*3742 -> 380037.52 | G77: =209*12980 -> 2712820 | H77: =12*64100 -> 769200 | I77: =6*59520 -> 357120 | J77: =80*42900 -> 3432000 | K77: =18*24820 -> 446760 | L77: =2*79960 -> 159920 | M77: =59*18260 -> 1077340 | N77: =124*18700 -> 2318800 | O77: =1*865000 -> 865000 | P77: =5*230000 -> 1150000 | Q77: =0 -> 0 | R77: =R78-3402 -> 1261971 | S77: =S78+1177.8473 -> 714939.98 | T77: =T78+1830 -> 2457625 | U77: =U78+2036 -> 1585378.1 | V77: =V78*1.0002 -> 3475465.3 | W77: =W78 -> 442500 | X77: =X78+2031.342590164 -> 1367034.3 | Y77: =Y78+735+597.83 -> 329116.03 | AA77: =AA78 -> 5529962 | AB77: =IF((SUM(C77:AA77)-AC77-AD77)<18000000,,SUM(C77:AA77)-AC77-AD77) -> 26280550 | AC77: =AC78+2018.527778 -> 4170413.4 | AD77: =AD78+1200 -> 1988.0822 | AE77: =IF(AB77="",,(AB77+AC77+abs(AD77))) -> 30452952 | AF77: =AA77/AB77 -> 0.21042033 | AG77: =AE77-AB77 -> 4172401.5
A78: =A79+1 -> 46024 | B78: =101.56*3742 -> 380037.52 | G78: =209*12980 -> 2712820 | H78: =12*64100 -> 769200 | I78: =6*59520 -> 357120 | J78: =80*42900 -> 3432000 | K78: =18*24820 -> 446760 | L78: =2*79960 -> 159920 | M78: =59*18260 -> 1077340 | N78: =124*18700 -> 2318800 | O78: =1*865000 -> 865000 | P78: =5*230000 -> 1150000 | Q78: =0 -> 0 | R78: =R79-3402 -> 1265373 | S78: =S79+1377.8473-150000 -> 713762.13 | T78: =T79+1830 -> 2455795 | U78: =U79+2036 -> 1583342.1 | V78: =V79*1.0002 -> 3474770.4 | W78: =W79 -> 442500 | X78: =X79+2031.342590164 -> 1365003 | Y78: =Y79+735+597.83 -> 327783.2 | AA78: =AA79-50000-1122000+150000-865000-250000 -> 5529962 | AB78: =IF((SUM(C78:AA78)-AC78-AD78)<18000000,,SUM(C78:AA78)-AC78-AD78) -> 26278068 | AC78: =AC79+2018.527778 -> 4168394.9 | AD78: =AD79+1200-50000 -> 788.08223 | AE78: =IF(AB78="",,(AB78+AC78+abs(AD78))) -> 30447251 | AF78: =AA78/AB78 -> 0.21044021 | AG78: =AE78-AB78 -> 4169183
A79: =A80+1 -> 46023 | B79: =101.56*3742 -> 380037.52 | G79: =209*12900 -> 2696100 | H79: =12*63060 -> 756720 | I79: 0 | J79: =80*43000 -> 3440000 | K79: =18*24720 -> 444960 | L79: =2*79960 -> 159920 | M79: =59*18260 -> 1077340 | N79: =64*18700 -> 1196800 | O79: =0*865000 -> 0 | P79: =5*230000 -> 1150000 | Q79: =0 -> 0 | R79: =R80-3402 -> 1268775 | S79: =S80+1377.8473 -> 862384.28 | T79: =T80+1830 -> 2453965 | U79: =U80+2036 -> 1581306.1 | V79: =V80*1.0002+100000 -> 3474075.6 | W79: =W80 -> 442500 | X79: =X80+2031.342590164 -> 1362971.6 | Y79: =Y80+735+597.83 -> 326450.37 | AA79: =AA80+200000+3000000 -> 7666962 | AB79: =IF((SUM(C79:AA79)-AC79-AD79)<18000000,,SUM(C79:AA79)-AC79-AD79) -> 26145265 | AC79: =AC80+2018.527778 -> 4166376.4 | AD79: =AD80+1200 -> 49588.082 | AE79: =IF(AB79="",,(AB79+AC79+abs(AD79))) -> 30361230 | AF79: =AA79/AB79 -> 0.29324476 | AG79: =AE79-AB79 -> 4215964.4
A80: =A81+1 -> 46022 | B80: =101.56*3742 -> 380037.52 | G80: =209*12900 -> 2696100 | H80: =12*63060 -> 756720 | I80: 0 | J80: =80*43000 -> 3440000 | K80: =18*24720 -> 444960 | L80: =2*79960 -> 159920 | M80: =59*18260 -> 1077340 | N80: =64*18700 -> 1196800 | O80: =0*865000 -> 0 | P80: =5*230000 -> 1150000 | Q80: =0 -> 0 | R80: =R81-3402 -> 1272177 | S80: =S81+1377.8473 -> 861006.44 | T80: =T81+1830 -> 2452135 | U80: =U81+2036 -> 1579270.1 | V80: =V81*1.0002 -> 3373400.9 | W80: =W81 -> 442500 | X80: =X81+2031.342590164 -> 1360940.3 | Y80: =Y81+735+597.83 -> 325117.54 | AA80: =AA81-3440000 -> 4466962 | AB80: =IF((SUM(C80:AA80)-AC80-AD80)<18000000,,SUM(C80:AA80)-AC80-AD80) -> 22842603 | AC80: =AC81+2018.527778 -> 4164357.8 | AD80: =AD81+1200 -> 48388.082 | AE80: =IF(AB80="",,(AB80+AC80+AD80)) -> 27055349 | AF80: =AA80/AB80 -> 0.19555398 | AG80: =AE80-AB80 -> 4212745.9
A81: =A82+1 -> 46021 | B81: =101.56*3742 -> 380037.52 | G81: =209*12900 -> 2696100 | H81: =12*63060 -> 756720 | I81: 0 | J81: 0 | K81: =18*24720 -> 444960 | L81: =2*79960 -> 159920 | M81: =59*18260 -> 1077340 | N81: =64*18700 -> 1196800 | O81: =0*865000 -> 0 | P81: =5*230000 -> 1150000 | Q81: =0 -> 0 | R81: =R82-3402 -> 1275579 | S81: =S82+1377.8473 -> 859628.59 | T81: =T82+1830 -> 2450305 | U81: =U82+2036 -> 1577234.1 | V81: =V82*1.0002 -> 3372726.3 | W81: =W82 -> 442500 | X81: =X82+2031.342590164 -> 1358908.9 | Y81: =Y82+735+597.83 -> 323784.71 | AA81: =AA82-903000+1106560+3967600+1633500+692160-380000-1150000+200000 -> 7906962 | AB81: =IF((SUM(C81:AA81)-AC81-AD81)<18000000,,SUM(C81:AA81)-AC81-AD81) -> 22839941 | AC81: =AC82+2018.527778 -> 4162339.3 | AD81: =AD82+1200 -> 47188.082 | AE81: =IF(AB81="",,(AB81+AC81+AD81)) -> 27049469 | AF81: =AA81/AB81 -> 0.34619012 | AG81: =AE81-AB81 -> 4209527.4
A82: =A83+1 -> 46020 | G82: =139*13280 -> 1845920 | H82: =12*62080 -> 744960 | I82: =27*61400 -> 1657800 | J82: =91*43960 -> 4000360 | K82: =46*25680 -> 1181280 | L82: =2*78780 -> 157560 | M82: =59*19060 -> 1124540 | N82: =64*19400 -> 1241600 | Q82: =608*1845 -> 1121760 | R82: =R83-3402 -> 1278981 | S82: =S83+1377.8473 -> 858250.74 | T82: =T83+1830 -> 2448475 | U82: =U83+2036 -> 1575198.1 | V82: =V83*1.0002 -> 3372051.9 | W82: =W83 -> 442500 | X82: =X83+2031.342590164 -> 1356877.6 | Y82: =Y83+735+597.83 -> 322451.88 | AA82: =AA83 -> 2740142 | AB82: =IF((SUM(C82:AA82)-AC82-AD82)<18000000,,SUM(C82:AA82)-AC82-AD82) -> 23264399 | AC82: =AC83+2018.527778 -> 4160320.8 | AD82: =AD83+1200 -> 45988.082 | AE82: =IF(AB82="",,(AB82+AC82+AD82)) -> 27470708 | AF82: =AA82/AB82 -> 0.11778262 | AG82: =AE82-AB82 -> 4206308.9
A83: =A84+1 -> 46019 | G83: =139*12980 -> 1804220 | H83: =12*62060 -> 744720 | I83: =27*60160 -> 1624320 | J83: =91*44000 -> 4004000 | K83: =46*25680 -> 1181280 | L83: =2*78580 -> 157160 | M83: =59*19000 -> 1121000 | N83: =64*19420 -> 1242880 | Q83: =608*1800 -> 1094400 | R83: =R84-3402 -> 1282383 | S83: =S84+1377.8473 -> 856872.89 | T83: =T84+1830 -> 2446645 | U83: =U84+2036 -> 1573162.1 | V83: =V84*1.0002 -> 3371377.6 | W83: =W84 -> 442500 | X83: =X84+2031.342590164 -> 1354846.2 | Y83: =Y84+735+597.83 -> 321119.05 | AA83: =AA84 -> 2740142 | AB83: =IF((SUM(C83:AA83)-AC83-AD83)<18000000,,SUM(C83:AA83)-AC83-AD83) -> 23159938 | AC83: =AC84+2018.527778 -> 4158302.2 | AD83: =AD84+1200 -> 44788.082 | AE83: =IF(AB83="",,(AB83+AC83+AD83)) -> 27363028 | AF83: =AA83/AB83 -> 0.11831388 | AG83: =AE83-AB83 -> 4203090.3
A84: =A85+1 -> 46018 | G84: =139*12980 -> 1804220 | H84: =12*62060 -> 744720 | I84: =27*60160 -> 1624320 | J84: =91*44000 -> 4004000 | K84: =46*25680 -> 1181280 | L84: =2*78580 -> 157160 | M84: =59*19000 -> 1121000 | N84: =64*19420 -> 1242880 | Q84: =608*1800 -> 1094400 | R84: =R85-3402-87675 -> 1285785 | S84: =S85+1377.8473 -> 855495.05 | T84: =T85+1830+87675+1000000 -> 2444815 | U84: =U85+2036 -> 1571126.1 | V84: =V85*1.0002 -> 3370703.5 | W84: =W85 -> 442500 | X84: =X85+2031.342590164 -> 1352814.9 | Y84: =Y85+735+597.83 -> 319786.22 | AA84: =AA85-1000000 -> 2740142 | AB84: =IF((SUM(C84:AA84)-AC84-AD84)<18000000,,SUM(C84:AA84)-AC84-AD84) -> 23157276 | AC84: =AC85+2018.527778 -> 4156283.7 | AD84: =AD85+1200 -> 43588.082 | AE84: =IF(AB84="",,(AB84+AC84+AD84)) -> 27357148 | AF84: =AA84/AB84 -> 0.11832748 | AG84: =AE84-AB84 -> 4199871.8
A85: =A86+1 -> 46017 | G85: =139*12980 -> 1804220 | H85: =12*62060 -> 744720 | I85: =27*60160 -> 1624320 | J85: =91*44000 -> 4004000 | K85: =46*25680 -> 1181280 | L85: =2*78580 -> 157160 | M85: =59*19000 -> 1121000 | N85: =64*19420 -> 1242880 | Q85: =608*1800 -> 1094400 | R85: =R86-3402+120000 -> 1376862 | S85: =S86+1377.8473 -> 854117.2 | T85: =T86+1830 -> 1355310 | U85: =U86+2036 -> 1569090.1 | V85: =V86*1.0002 -> 3370029.5 | W85: =W86 -> 442500 | X85: =X86+2031.342590164 -> 1350783.6 | Y85: =Y86+735+597.83-200000 -> 318453.39 | AA85: =AA86+80000 -> 3740142 | AB85: =IF((SUM(C85:AA85)-AC85-AD85)<18000000,,SUM(C85:AA85)-AC85-AD85) -> 23154614 | AC85: =AC86+2018.527778 -> 4154265.2 | AD85: =AD86+1200 -> 42388.082 | AE85: =IF(AB85="",,(AB85+AC85+AD85)) -> 27351268 | AF85: =AA85/AB85 -> 0.16152901 | AG85: =AE85-AB85 -> 4196653.3
A86: =A87+1 -> 46016 | G86: =139*12980 -> 1804220 | H86: =12*63280 -> 759360 | I86: =27*60160 -> 1624320 | J86: =91*44000 -> 4004000 | K86: =46*25220 -> 1160120 | L86: =2*78600 -> 157200 | M86: =59*18900 -> 1115100 | N86: =64*19400 -> 1241600 | Q86: =608*1800 -> 1094400 | R86: =R87-3402 -> 1260264 | S86: =S87+1377.8473 -> 852739.35 | T86: =T87+1830 -> 1353480 | U86: =U87+2036 -> 1567054.1 | V86: =V87*1.0002 -> 3369355.6 | W86: =W87 -> 442500 | X86: =X87+2031.342590164 -> 1348752.2 | Y86: =Y87+735+597.83 -> 517120.56 | AA86: =AA87+2750000 -> 3660142 | AB86: =IF((SUM(C86:AA86)-AC86-AD86)<18000000,,SUM(C86:AA86)-AC86-AD86) -> 23138293 | AC86: =AC87+2018.527778 -> 4152246.7 | AD86: =AD87+1200 -> 41188.082 | AE86: =IF(AB86="",,(AB86+AC86+AD86)) -> 27331728 | AF86: =AA86/AB86 -> 0.15818548 | AG86: =AE86-AB86 -> 4193434.7
A87: =A88+1 -> 46015 | G87: =139*12980 -> 1804220 | H87: =12*63280 -> 759360 | I87: =27*60000 -> 1620000 | J87: =91*44000 -> 4004000 | K87: =46*25220 -> 1160120 | L87: =2*78600 -> 157200 | M87: =59*18900 -> 1115100 | N87: =64*19400 -> 1241600 | Q87: =608*1800 -> 1094400 | R87: =R88-3402 -> 1263666 | S87: =S88+1377.8473 -> 851361.5 | T87: =T88+1830 -> 1351650 | U87: =U88+2036 -> 1565018.1 | V87: =V88*1.0002 -> 3368681.9 | W87: =W88 -> 442500 | X87: =X88+2031.342590164 -> 1346720.9 | Y87: =Y88+735+597.83 -> 515787.73 | AA87: =AA88 -> 910142 | AB87: =IF((SUM(C87:AA87)-AC87-AD87)<18000000,,SUM(C87:AA87)-AC87-AD87) -> 20381312 | AC87: =AC88+2018.527778 -> 4150228.1 | AD87: =AD88+1200 -> 39988.082 | AE87: =IF(AB87="",,(AB87+AC87+AD87)) -> 24571528 | AF87: =AA87/AB87 -> 0.044655712 | AG87: =AE87-AB87 -> 4190216.2
A88: =A89+1 -> 46014 | G88: =139*12800 -> 1779200 | H88: =12*63280 -> 759360 | I88: =27*60500 -> 1633500 | J88: =91*44000 -> 4004000 | K88: =46*25200 -> 1159200 | L88: =2*78300 -> 156600 | M88: =59*18980 -> 1119820 | N88: =64*19660 -> 1258240 | Q88: =608*1800 -> 1094400 | R88: =R89-3402 -> 1267068 | S88: =S89+1377.8473 -> 849983.66 | T88: =T89+1830 -> 1349820 | U88: =U89+2036 -> 1562982.1 | V88: =V89*1.0002 -> 3368008.3 | W88: =W89+7500 -> 442500 | X88: =X89+2031.342590164 -> 1344689.5 | Y88: =Y89+735+597.83 -> 514454.9 | AA88: =AA89 -> 910142 | AB88: =IF((SUM(C88:AA88)-AC88-AD88)<18000000,,SUM(C88:AA88)-AC88-AD88) -> 20386971 | AC88: =AC89+2018.527778 -> 4148209.6 | AD88: =AD89+1200 -> 38788.082 | AE88: =IF(AB88="",,(AB88+AC88+AD88)) -> 24573968 | AF88: =AA88/AB88 -> 0.044643317 | AG88: =AE88-AB88 -> 4186997.7
A89: =A90+1 -> 46013 | G89: =139*12680 -> 1762520 | H89: =12*62560 -> 750720 | I89: =27*59240 -> 1599480 | J89: =91*44000 -> 4004000 | K89: =46*25120 -> 1155520 | L89: =2*79380 -> 158760 | M89: =59*18900 -> 1115100 | N89: =64*19600 -> 1254400 | Q89: =608*1770 -> 1076160 | R89: =R90-3402+100000 -> 1270470 | S89: =S90+1377.8473 -> 848605.81 | T89: =T90+1830 -> 1347990 | U89: =U90+2036 -> 1560946.1 | V89: =V90*1.0002+580000-100000 -> 3367334.8 | W89: =W90+10000 -> 435000 | X89: =X90+2031.342590164 -> 1342658.2 | Y89: =Y90+735+597.83 -> 513122.07 | AA89: =AA90-580000 -> 910142 | AB89: =IF((SUM(C89:AA89)-AC89-AD89)<18000000,,SUM(C89:AA89)-AC89-AD89) -> 20289150 | AC89: =AC90+2018.527778 -> 4146191.1 | AD89: =AD90+1200 -> 37588.082 | AE89: =IF(AB89="",,(AB89+AC89+AD89)) -> 24472929 | AF89: =AA89/AB89 -> 0.044858558 | AG89: =AE89-AB89 -> 4183779.2
A90: =A91+1 -> 46012 | G90: =139*12360 -> 1718040 | H90: =12*62700 -> 752400 | I90: =27*59520 -> 1607040 | J90: =91*43700 -> 3976700 | K90: =46*25120 -> 1155520 | L90: =2*79000 -> 158000 | M90: =59*19100 -> 1126900 | N90: =64*19700 -> 1260800 | Q90: =608*1765 -> 1073120 | R90: =R91-3402 -> 1173872 | S90: =S91+1377.8473 -> 847227.96 | T90: =T91+1830 -> 1346160 | U90: =U91+2036 -> 1558910.1 | V90: =V91*1.0002 -> 2886757.5 | W90: =W91+10000 -> 425000 | X90: =X91+2031.342590164 -> 1340626.9 | Y90: =Y91+735+597.83 -> 511789.24 | AA90: =AA91 -> 1490142 | AB90: =IF((SUM(C90:AA90)-AC90-AD90)<18000000,,SUM(C90:AA90)-AC90-AD90) -> 20228445 | AC90: =AC91+2018.527778 -> 4144172.6 | AD90: =AD91+1200 -> 36388.082 | AE90: =IF(AB90="",,(AB90+AC90+AD90)) -> 24409006 | AF90: =AA90/AB90 -> 0.073665672 | AG90: =AE90-AB90 -> 4180560.6
A91: =A92+1 -> 46011 | G91: =139*12360 -> 1718040 | H91: =12*62700 -> 752400 | I91: =27*59520 -> 1607040 | J91: =91*43700 -> 3976700 | K91: =46*25120 -> 1155520 | L91: =2*79000 -> 158000 | M91: =59*19100 -> 1126900 | N91: =64*19700 -> 1260800 | Q91: =608*1765 -> 1073120 | R91: =R92-3402 -> 1177274 | S91: =S92+1377.8473 -> 845850.12 | T91: =T92+1830 -> 1344330 | U91: =U92+2036 -> 1556874.1 | V91: =V92*1.0002 -> 2886180.2 | W91: =W92+10000 -> 415000 | X91: =X92+2031.342590164 -> 1338595.5 | Y91: =Y92+735+597.83 -> 510456.41 | AA91: =AA92 -> 1490142 | AB91: =IF((SUM(C91:AA91)-AC91-AD91)<18000000,,SUM(C91:AA91)-AC91-AD91) -> 20215880 | AC91: =AC92+2018.527778 -> 4142154 | AD91: =AD92+1200 -> 35188.082 | AE91: =IF(AB91="",,(AB91+AC91+AD91)) -> 24393222 | AF91: =AA91/AB91 -> 0.073711458 | AG91: =AE91-AB91 -> 4177342.1
A92: =A93+1 -> 46010 | G92: =139*12360 -> 1718040 | H92: =12*62700 -> 752400 | I92: =27*59520 -> 1607040 | J92: =91*43700 -> 3976700 | K92: =46*25120 -> 1155520 | L92: =2*79000 -> 158000 | M92: =59*19100 -> 1126900 | N92: =64*19700 -> 1260800 | Q92: =608*1765 -> 1073120 | R92: =R93-3402 -> 1180676 | S92: =S93+1377.8473 -> 844472.27 | T92: =T93+1830 -> 1342500 | U92: =U93+2036 -> 1554838.1 | V92: =V93*1.0002 -> 2885603.1 | W92: =W93+10000 -> 405000 | X92: =X93+2031.342590164 -> 1336564.2 | Y92: =Y93+735+597.83 -> 509123.58 | AA92: =AA93 -> 1490142 | AB92: =IF((SUM(C92:AA92)-AC92-AD92)<18000000,,SUM(C92:AA92)-AC92-AD92) -> 20203316 | AC92: =AC93+2018.527778 -> 4140135.5 | AD92: =AD93+1200 -> 33988.082 | AE92: =IF(AB92="",,(AB92+AC92+AD92)) -> 24377439 | AF92: =AA92/AB92 -> 0.073757299 | AG92: =AE92-AB92 -> 4174123.6
A93: =A94+1 -> 46009 | G93: =139*12600 -> 1751400 | H93: =12*62780 -> 753360 | I93: =27*59300 -> 1601100 | J93: =91*44780 -> 4074980 | K93: =46*25320 -> 1164720 | L93: =2*78500 -> 157000 | M93: =59*18900 -> 1115100 | N93: =64*19500 -> 1248000 | Q93: =608*1785 -> 1085280 | R93: =R94-3402 -> 1184078 | S93: =S94+1377.8473 -> 843094.42 | T93: =T94+1830 -> 1340670 | U93: =U94+2036 -> 1552802.1 | V93: =V94*1.0002 -> 2885026.1 | W93: =W94+10000 -> 395000 | X93: =X94+2031.342590164 -> 1334532.8 | Y93: =Y94+735+597.83 -> 507790.75 | AA93: =AA94-492580-274500 -> 1490142 | AB93: =IF((SUM(C93:AA93)-AC93-AD93)<18000000,,SUM(C93:AA93)-AC93-AD93) -> 20313171 | AC93: =AC94+2018.527778 -> 4138117 | AD93: =AD94+1200 -> 32788.082 | AE93: =IF(AB93="",,(AB93+AC93+AD93)) -> 24484076 | AF93: =AA93/AB93 -> 0.073358413 | AG93: =AE93-AB93 -> 4170905.1
A94: =A95+1 -> 46008 | G94: =139*12700 -> 1765300 | H94: =12*61660 -> 739920 | I94: =27*59360 -> 1602720 | J94: =80*43500 -> 3480000 | K94: =46*25500 -> 1173000 | L94: =2*77340 -> 154680 | M94: =59*18720 -> 1104480 | N94: =64*19480 -> 1246720 | Q94: =608*1815 -> 1103520 | R94: =R95-3402 -> 1187480 | S94: =S95+1377.8473 -> 841716.57 | T94: =T95+1830 -> 1338840 | U94: =U95+2036 -> 1550766.1 | V94: =V95*1.0002 -> 2884449.2 | W94: =W95+274500 -> 385000 | X94: =X95+2031.342590164 -> 1332501.5 | Y94: =Y95+735+597.83 -> 506457.92 | AA94: =AA95 -> 2257222 | AB94: =IF((SUM(C94:AA94)-AC94-AD94)<18000000,,SUM(C94:AA94)-AC94-AD94) -> 20487087 | AC94: =AC95+2018.527778 -> 4136098.4 | AD94: =AD95+1200 -> 31588.082 | AE94: =IF(AB94="",,(AB94+AC94+AD94)) -> 24654773 | AF94: =AA94/AB94 -> 0.11017779 | AG94: =AE94-AB94 -> 4167686.5
A95: =A96+1 -> 46007 | G95: =139*12900 -> 1793100 | H95: =12*62120 -> 745440 | I95: =27*60500 -> 1633500 | J95: =80*45020 -> 3601600 | K95: =46*26020 -> 1196920 | L95: =2*77480 -> 154960 | M95: =59*19160 -> 1130440 | N95: =64*19000 -> 1216000 | Q95: =608*1800 -> 1094400 | R95: =R96-3402 -> 1190882 | S95: =S96+1377.8473 -> 840338.73 | T95: =T96+1830 -> 1337010 | U95: =U96+2036 -> 1548730.1 | V95: =V96*1.0002 -> 2883872.5 | W95: =W96 -> 110500 | X95: =X96+2031.342590164 -> 1330470.1 | Y95: =Y96+735+597.83 -> 505125.09 | AA95: =AA96 -> 2257222 | AB95: =IF((SUM(C95:AA95)-AC95-AD95)<18000000,,SUM(C95:AA95)-AC95-AD95) -> 20406042 | AC95: =AC96+2018.527778 -> 4134079.9 | AD95: =AD96+1200 -> 30388.082 | AE95: =IF(AB95="",,(AB95+AC95+AD95)) -> 24570510 | AF95: =AA95/AB95 -> 0.11061537 | AG95: =AE95-AB95 -> 4164468
A96: =A97+1 -> 46006 | G96: =139*13000 -> 1807000 | H96: =12*63820 -> 765840 | I96: =27*60120 -> 1623240 | J96: =80*46100 -> 3688000 | K96: =46*26240 -> 1207040 | L96: =2*76000 -> 152000 | M96: =59*19400 -> 1144600 | N96: =64*19440 -> 1244160 | Q96: =608*1845 -> 1121760 | R96: =R97-3402 -> 1194284 | S96: =S97+1377.8473 -> 838960.88 | T96: =T97+1830 -> 1335180 | U96: =U97+2036 -> 1546694.1 | V96: =V97*1.0002 -> 2883295.8 | W96: =W97 -> 110500 | X96: =X97+2031.342590164 -> 1328438.8 | Y96: =Y97+735+597.83 -> 503792.26 | AA96: =AA97 -> 2257222 | AB96: =IF((SUM(C96:AA96)-AC96-AD96)<18000000,,SUM(C96:AA96)-AC96-AD96) -> 20590758 | AC96: =AC97+2018.527778 -> 4132061.4 | AD96: =AD97+1200 -> 29188.082 | AE96: =IF(AB96="",,(AB96+AC96+AD96)) -> 24752008 | AF96: =AA96/AB96 -> 0.10962306 | AG96: =AE96-AB96 -> 4161249.5
A97: =A98+1 -> 46005 | G97: =139*13060 -> 1815340 | H97: =12*64600 -> 775200 | I97: =27*60900 -> 1644300 | J97: =80*46640 -> 3731200 | K97: =46*26400 -> 1214400 | L97: =2*77800 -> 155600 | M97: =59*19120 -> 1128080 | N97: =64*19120 -> 1223680 | Q97: =608*1865 -> 1133920 | R97: =R98-3402 -> 1197686 | S97: =S98+1377.8473 -> 837583.03 | T97: =T98+1830 -> 1333350 | U97: =U98+2036 -> 1544658.1 | V97: =V98*1.0002 -> 2882719.2 | W97: =W98 -> 110500 | X97: =X98+2031.342590164 -> 1326407.5 | Y97: =Y98+735+597.83 -> 502459.43 | AA97: =AA98 -> 2257222 | AB97: =IF((SUM(C97:AA97)-AC97-AD97)<18000000,,SUM(C97:AA97)-AC97-AD97) -> 20656274 | AC97: =AC98+2018.527778 -> 4130042.9 | AD97: =AD98+1200 -> 27988.082 | AE97: =IF(AB97="",,(AB97+AC97+AD97)) -> 24814305 | AF97: =AA97/AB97 -> 0.10927537 | AG97: =AE97-AB97 -> 4158030.9
A98: =A99+1 -> 46004 | G98: =139*13060 -> 1815340 | H98: =12*64600 -> 775200 | I98: =27*60900 -> 1644300 | J98: =80*46640 -> 3731200 | K98: =46*26400 -> 1214400 | L98: =2*77800 -> 155600 | M98: =59*19120 -> 1128080 | N98: =64*19120 -> 1223680 | Q98: =608*1865 -> 1133920 | R98: =R99-3402 -> 1201088 | S98: =S99+1377.8473 -> 836205.18 | T98: =T99+1830 -> 1331520 | U98: =U99+2036 -> 1542622.1 | V98: =V99*1.0002 -> 2882142.8 | W98: =W99 -> 110500 | X98: =X99+2031.342590164 -> 1324376.1 | Y98: =Y99+735+597.83 -> 501126.6 | AA98: =AA99 -> 2257222 | AB98: =IF((SUM(C98:AA98)-AC98-AD98)<18000000,,SUM(C98:AA98)-AC98-AD98) -> 20653710 | AC98: =AC99+2018.527778 -> 4128024.3 | AD98: =AD99+1200 -> 26788.082 | AE98: =IF(AB98="",,(AB98+AC98+AD98)) -> 24808523 | AF98: =AA98/AB98 -> 0.10928893 | AG98: =AE98-AB98 -> 4154812.4
A99: =A100+1 -> 46003 | G99: =139*13060 -> 1815340 | H99: =12*64600 -> 775200 | I99: =27*60900 -> 1644300 | J99: =80*46640 -> 3731200 | K99: =46*26400 -> 1214400 | L99: =2*77800 -> 155600 | M99: =59*19120 -> 1128080 | N99: =64*19120 -> 1223680 | Q99: =608*1865 -> 1133920 | R99: =R100-3402 -> 1204490 | S99: =S100+1377.8473+400000 -> 834827.34 | T99: =T100+1830+573000 -> 1329690 | U99: =U100+2036 -> 1540586.1 | V99: =V100*1.0002 -> 2881566.5 | W99: =W100-400000 -> 110500 | X99: =X100+2031.342590164 -> 1322344.8 | Y99: =Y100+735+597.83 -> 499793.77 | AA99: =AA100-573000 -> 2257222 | AB99: =IF((SUM(C99:AA99)-AC99-AD99)<18000000,,SUM(C99:AA99)-AC99-AD99) -> 20651147 | AC99: =AC100+2018.527778 -> 4126005.8 | AD99: =AD100+1200 -> 25588.082 | AE99: =IF(AB99="",,(AB99+AC99+AD99)) -> 24802740 | AF99: =AA99/AB99 -> 0.1093025 | AG99: =AE99-AB99 -> 4151593.9
A100: =A101+1 -> 46002 | G100: =139*12900 -> 1793100 | H100: =12*64360 -> 772320 | I100: =27*61000 -> 1647000 | J100: =80*46980 -> 3758400 | K100: =46*26400 -> 1214400 | L100: =2*77900 -> 155800 | M100: =59*19020 -> 1122180 | N100: =64*18600 -> 1190400 | Q100: =608*1880 -> 1143040 | R100: =R101-3402 -> 1207892 | S100: =S101+877.8473 -> 433449.49 | T100: =T101+1830 -> 754860 | U100: =U101+2036 -> 1538550.1 | V100: =V101*1.0002 -> 2880990.3 | W100: =W101 -> 510500 | X100: =X101+2031.342590164 -> 1320313.4 | Y100: =Y101+735+597.83 -> 498460.94 | AA100: =AA101+1500000 -> 2830222 | AB100: =IF((SUM(C100:AA100)-AC100-AD100)<18000000,,SUM(C100:AA100)-AC100-AD100) -> 20623503 | AC100: =AC101+2018.527778 -> 4123987.3 | AD100: =AD101+1200 -> 24388.082 | AE100: =IF(AB100="",,(AB100+AC100+AD100)) -> 24771878 | AF100: =AA100/AB100 -> 0.13723285 | AG100: =AE100-AB100 -> 4148375.4
...

Sheet COLCAP VS VU
A1: Fecha | B1: Nemotécnico | C1: Precio cierre | D1: V UNIDAD | E1: escala 1= 02/01 | F1: escala 1= 02/01 | G1: diferencia
A2: 46024 | B2: ICOLCAP | C2: 20480.5 | D2: =SUMIF(GRAFICO!A:A,A2,GRAFICO!B:B) -> 20853.22 | E2: =C2/$C$2 -> 1 | F2: =D2/$D$2 -> 1 | G2: =F2-E2 -> 0 | I2: varianza
A3: 46027 | B3: ICOLCAP | C3: 20994 | D3: =SUMIF(GRAFICO!A:A,A3,GRAFICO!B:B) -> 21131.511 | E3: =C3/$C$2 -> 1.0250726 | F3: =D3/$D$2 -> 1.0133453 | G3: =F3-E3 -> -0.011727366 | I3: =VAR(C2:C48) -> 1294521.3 | J3: =VAR(D2:D48) -> 141363.23
A4: 46028 | B4: ICOLCAP | C4: 21308 | D4: =SUMIF(GRAFICO!A:A,A4,GRAFICO!B:B) -> 20989.13 | E4: =C4/$C$2 -> 1.0404043 | F4: =D4/$D$2 -> 1.0065175 | G4: =F4-E4 -> -0.033886807 | I4: desviación
A5: 46029 | B5: ICOLCAP | C5: 21466 | D5: =SUMIF(GRAFICO!A:A,A5,GRAFICO!B:B) -> 20969.024 | E5: =C5/$C$2 -> 1.0481189 | F5: =D5/$D$2 -> 1.0055533 | G5: =F5-E5 -> -0.04256565 | I5: =STDEV(C2:C48) -> 1137.7703 | J5: =STDEV(D2:D48) -> 375.98301
A6: 46030 | B6: ICOLCAP | C6: 21461.5 | D6: =SUMIF(GRAFICO!A:A,A6,GRAFICO!B:B) -> 20994.039 | E6: =C6/$C$2 -> 1.0478992 | F6: =D6/$D$2 -> 1.0067529 | G6: =F6-E6 -> -0.04114633 | I6: correlación | J6: max diferencia
